Workbook
Name STATUS_PROCESSO: #REF!
Name STATUSINFRA: '[2]Apoio IE'!$F$2:$F$16

Sheet PARÂMETROS
A1: BASE CONSOLIDADA LPU LS — PARÂMETROS
A3: Parâmetro | B3: Valor | C3: O que significa
A4: Fator sobre o MERCADO | B4: 0.9 | C4: LS OFFICE = MERCADO da região × este fator. 0,90 = entrar 10% abaixo da mediana dos fornecedores. Altere e as colunas LS OFFICE recalculam, aqui e na aba LPU ADEQUAÇÃO.
A5: Fator sobre o CUSTO | B5: 3.34 | C5: PREÇO POR CUSTO = CUSTO LS × este fator. O valor sugerido é a mediana do que a LS já praticou sobre o próprio custo nas linhas onde as duas pontas existem — não é uma meta, é o retrato do que vem sendo cobrado. Calibre.
A6: MERCADO — critério | B6: Mediana | C6: Mediana das cotações de fornecedor válidas da região, ignorando n/a, N/A e zeros. Mediana e não média: em vários itens a Clemar cota 5x a Brasilsat, e a média sozinha seria puxada pelo extremo.
A7: MERCADO NORTE / NORDESTE | B7: Por região | C7: Cada uma usa só os fornecedores daquele bloco da LPU: 7 no Norte, 8 no Nordeste.
A8: MERCADO N+NE | B8: Duas regiões juntas | C8: Mediana das cotações do Norte e do Nordeste somadas — as regiões onde a LS opera. É esta, não a do Brasil, que serve de referência geral.
A9: MERCADO BRASIL | B9: As 6 regiões | C9: Mediana de todas as cotações das 6 regiões. Fica na base só como referência: Leste e Sul são muito mais caros e distorcem o número para cima.
A10: CUSTO LS | B10: Média | C10: Média do valor unitário efetivamente pago, apenas documentos marcados SIM na planilha de itens comprados. É material posto na obra: sem mão de obra, sem BDI.
A11: PRATICADO | B11: Média | C11: Média das PVs que precificaram o item — 36 PVs, uma por site, revisão mais recente.
A12: Rastreabilidade | B12: — | C12: Cada cotação de fornecedor que entra em qualquer mediana está na aba ABERTURA DE MERCADO, linha por linha, com região e nome do fornecedor.

Sheet BASE CONSOLIDADA
A1: Linha LPU | B1: Família | C1: Grupo | D1: Subgrupo | E1: Item | F1: Un. | G1: Simples | H1: Macro | I1: Altura (m) | J1: AeV (m²) | K1: Vento (m/s) | L1: Nº forn. Norte | M1: MERCADO NORTE (mediana) | N1: LS OFFICE NORTE | O1: Nº forn. Nordeste | P1: MERCADO NORDESTE (mediana) | Q1: LS OFFICE NORDESTE | R1: Nº cot. N+NE | S1: MERCADO N+NE (mediana) | T1: CUSTO LS (compras) | U1: Nº compras | V1: PREÇO POR CUSTO | W1: PRATICADO (PV média) | X1: Nº PVs | Y1: Praticado ÷ Custo | Z1: LS Office ÷ Custo | AA1: LS Office ÷ Praticado | AB1: Dispersão forn. Norte (maior÷menor) | AC1: MÉDIA original da LPU (sua fórmula) | AD1: MERCADO BRASIL (6 regiões) | AE1: Origem do de-para | AF1: Descrição completa (original da LPU)
A2: 5 | B2: MASTRO | C2: Mastro | E2: Mastro · 2m · AeV 2m² · 45m/s | F2: VB | G2: - | H2: 2 | I2: 2 | J2: 2 | K2: 45 | L2: 4 | M2: 3801.96 | N2: =IF(M2="","",ROUND(M2*PARÂMETROS!$B$4,2)) | O2: 4 | P2: 3721.96 | Q2: =IF(P2="","",ROUND(P2*PARÂMETROS!$B$4,2)) | R2: 8 | S2: 3763.92 | V2: =IF(T2="","",ROUND(T2*PARÂMETROS!$B$5,2)) | Y2: =IFERROR(ROUND(W2/T2,2),"") | Z2: =IFERROR(ROUND(N2/T2,2),"") | AA2: =IFERROR(ROUND(N2/W2,2),"") | AB2: 6.3 | AC2: 3820.06 | AD2: 3721.98 | AF2: Mastros Mastros com altura superior 2m deverão ser providos de pedaleira e cabo trava-quedas. >> 2
A3: 6 | B3: MASTRO | C3: Mastro | E3: Mastro · 3m · AeV 2m² · 45m/s | F3: VB | G3: - | H3: 2 | I3: 3 | J3: 2 | K3: 45 | L3: 4 | M3: 6071.32 | N3: =IF(M3="","",ROUND(M3*PARÂMETROS!$B$4,2)) | O3: 4 | P3: 5908.12 | Q3: =IF(P3="","",ROUND(P3*PARÂMETROS!$B$4,2)) | R3: 8 | S3: 5908.12 | V3: =IF(T3="","",ROUND(T3*PARÂMETROS!$B$5,2)) | Y3: =IFERROR(ROUND(W3/T3,2),"") | Z3: =IFERROR(ROUND(N3/T3,2),"") | AA3: =IFERROR(ROUND(N3/W3,2),"") | AB3: 5.4 | AC3: 6958.3 | AD3: 5418.52 | AF3: Mastros Mastros com altura superior 2m deverão ser providos de pedaleira e cabo trava-quedas. >> 2
A4: 7 | B4: MASTRO | C4: Mastro | E4: Mastro · 3m · AeV 3m² · 45m/s | F4: VB | G4: - | H4: 3 | I4: 3 | J4: 3 | K4: 45 | L4: 4 | M4: 6378.52 | N4: =IF(M4="","",ROUND(M4*PARÂMETROS!$B$4,2)) | O4: 4 | P4: 6202.52 | Q4: =IF(P4="","",ROUND(P4*PARÂMETROS!$B$4,2)) | R4: 8 | S4: 6202.52 | V4: =IF(T4="","",ROUND(T4*PARÂMETROS!$B$5,2)) | Y4: =IFERROR(ROUND(W4/T4,2),"") | Z4: =IFERROR(ROUND(N4/T4,2),"") | AA4: =IFERROR(ROUND(N4/W4,2),"") | AB4: 5.7 | AC4: 7277.47 | AD4: 5674.52 | AF4: Mastros Mastros com altura superior 2m deverão ser providos de pedaleira e cabo trava-quedas. >> 3
A5: 8 | B5: MASTRO | C5: Mastro | E5: Mastro · 4m · AeV 2m² · 45m/s | F5: VB | G5: - | H5: 2 | I5: 4 | J5: 2 | K5: 45 | L5: 4 | M5: 7911.45 | N5: =IF(M5="","",ROUND(M5*PARÂMETROS!$B$4,2)) | O5: 4 | P5: 7711.45 | Q5: =IF(P5="","",ROUND(P5*PARÂMETROS!$B$4,2)) | R5: 8 | S5: 7711.45 | V5: =IF(T5="","",ROUND(T5*PARÂMETROS!$B$5,2)) | Y5: =IFERROR(ROUND(W5/T5,2),"") | Z5: =IFERROR(ROUND(N5/T5,2),"") | AA5: =IFERROR(ROUND(N5/W5,2),"") | AB5: 3.5 | AC5: 8814.38 | AD5: 7111.45 | AF5: Mastros Mastros com altura superior 2m deverão ser providos de pedaleira e cabo trava-quedas. >> 2
A6: 9 | B6: MASTRO | C6: Mastro | E6: Mastro · 4m · AeV 3m² · 45m/s | F6: VB | G6: - | H6: 3 | I6: 4 | J6: 3 | K6: 45 | L6: 4 | M6: 9677.85 | N6: =IF(M6="","",ROUND(M6*PARÂMETROS!$B$4,2)) | O6: 4 | P6: 9404.25 | Q6: =IF(P6="","",ROUND(P6*PARÂMETROS!$B$4,2)) | R6: 8 | S6: 9404.25 | V6: =IF(T6="","",ROUND(T6*PARÂMETROS!$B$5,2)) | Y6: =IFERROR(ROUND(W6/T6,2),"") | Z6: =IFERROR(ROUND(N6/T6,2),"") | AA6: =IFERROR(ROUND(N6/W6,2),"") | AB6: 3.7 | AC6: 9886.65 | AD6: 8583.45 | AF6: Mastros Mastros com altura superior 2m deverão ser providos de pedaleira e cabo trava-quedas. >> 3
A7: 10 | B7: MASTRO | C7: Mastro | E7: Mastro · 6m · AeV 2m² · 45m/s | F7: VB | G7: - | H7: 2 | I7: 6 | J7: 2 | K7: 45 | L7: 4 | M7: 12883.71 | N7: =IF(M7="","",ROUND(M7*PARÂMETROS!$B$4,2)) | O7: 4 | P7: 13005.3 | Q7: =IF(P7="","",ROUND(P7*PARÂMETROS!$B$4,2)) | R7: 8 | S7: 12883.71 | V7: =IF(T7="","",ROUND(T7*PARÂMETROS!$B$5,2)) | Y7: =IFERROR(ROUND(W7/T7,2),"") | Z7: =IFERROR(ROUND(N7/T7,2),"") | AA7: =IFERROR(ROUND(N7/W7,2),"") | AB7: 3.8 | AC7: 12802.44 | AD7: 11925.19 | AF7: Mastros Mastros com altura superior 2m deverão ser providos de pedaleira e cabo trava-quedas. >> 2
A8: 11 | B8: MASTRO | C8: Mastro | E8: Mastro · 6m · AeV 3m² · 45m/s | F8: VB | G8: - | H8: 3 | I8: 6 | J8: 3 | K8: 45 | L8: 4 | M8: 15038.54 | N8: =IF(M8="","",ROUND(M8*PARÂMETROS!$B$4,2)) | O8: 4 | P8: 14096.81 | Q8: =IF(P8="","",ROUND(P8*PARÂMETROS!$B$4,2)) | R8: 8 | S8: 14096.81 | V8: =IF(T8="","",ROUND(T8*PARÂMETROS!$B$5,2)) | Y8: =IFERROR(ROUND(W8/T8,2),"") | Z8: =IFERROR(ROUND(N8/T8,2),"") | AA8: =IFERROR(ROUND(N8/W8,2),"") | AB8: 4 | AC8: 14131.97 | AD8: 13249.68 | AF8: Mastros Mastros com altura superior 2m deverão ser providos de pedaleira e cabo trava-quedas. >> 3
A9: 12 | B9: MASTRO | C9: Mastro | E9: Mastro · 8m · AeV 3m² · 45m/s | F9: VB | G9: - | H9: 3 | I9: 8 | J9: 3 | K9: 45 | L9: 4 | M9: 24845.17 | N9: =IF(M9="","",ROUND(M9*PARÂMETROS!$B$4,2)) | O9: 4 | P9: 22800.52 | Q9: =IF(P9="","",ROUND(P9*PARÂMETROS!$B$4,2)) | R9: 8 | S9: 22800.52 | V9: =IF(T9="","",ROUND(T9*PARÂMETROS!$B$5,2)) | Y9: =IFERROR(ROUND(W9/T9,2),"") | Z9: =IFERROR(ROUND(N9/T9,2),"") | AA9: =IFERROR(ROUND(N9/W9,2),"") | AB9: 5.6 | AC9: 22685.59 | AD9: 21437.41 | AF9: Mastros Mastros com altura superior 2m deverão ser providos de pedaleira e cabo trava-quedas. >> 3
A10: 13 | B10: MASTRO | C10: Mastro | E10: Mastro · 8m · AeV 4m² · 45m/s | F10: VB | G10: - | H10: 4 | I10: 8 | J10: 4 | K10: 45 | L10: 4 | M10: 25630.36 | N10: =IF(M10="","",ROUND(M10*PARÂMETROS!$B$4,2)) | O10: 4 | P10: 23550.22 | Q10: =IF(P10="","",ROUND(P10*PARÂMETROS!$B$4,2)) | R10: 8 | S10: 23550.22 | V10: =IF(T10="","",ROUND(T10*PARÂMETROS!$B$5,2)) | Y10: =IFERROR(ROUND(W10/T10,2),"") | Z10: =IFERROR(ROUND(N10/T10,2),"") | AA10: =IFERROR(ROUND(N10/W10,2),"") | AB10: 5.7 | AC10: 23319.46 | AD10: 22118.97 | AF10: Mastros Mastros com altura superior 2m deverão ser providos de pedaleira e cabo trava-quedas. >> 4
A11: 14 | B11: POSTE | C11: Poste Concreto/Fibra Simplificado | D11: Suporte RF em plataforma EV > 30m | E11: 3 | F11: VB | I11: 9 | J11: 3 | K11: 30 | L11: 1 | M11: 3375 | N11: =IF(M11="","",ROUND(M11*PARÂMETROS!$B$4,2)) | O11: 1 | P11: 3375 | Q11: =IF(P11="","",ROUND(P11*PARÂMETROS!$B$4,2)) | R11: 2 | S11: 3375 | V11: =IF(T11="","",ROUND(T11*PARÂMETROS!$B$5,2)) | Y11: =IFERROR(ROUND(W11/T11,2),"") | Z11: =IFERROR(ROUND(N11/T11,2),"") | AA11: =IFERROR(ROUND(N11/W11,2),"") | AB11: 1 | AC11: 3375 | AD11: 3375 | AF11: Poste de Concreto ou Fibra Simplificado Deflexão máxima 1◦0"00" >> Suporte RF em plataforma EV > 30m >> 3
A12: 15 | B12: POSTE | C12: Poste Concreto/Fibra Simplificado | D12: Suporte RF em plataforma EV > 30m | E12: 3 | F12: VB | I12: 9 | J12: 3 | K12: 35 | L12: 1 | M12: 3543.75 | N12: =IF(M12="","",ROUND(M12*PARÂMETROS!$B$4,2)) | O12: 1 | P12: 3543.75 | Q12: =IF(P12="","",ROUND(P12*PARÂMETROS!$B$4,2)) | R12: 2 | S12: 3543.75 | V12: =IF(T12="","",ROUND(T12*PARÂMETROS!$B$5,2)) | Y12: =IFERROR(ROUND(W12/T12,2),"") | Z12: =IFERROR(ROUND(N12/T12,2),"") | AA12: =IFERROR(ROUND(N12/W12,2),"") | AB12: 1 | AC12: 3543.75 | AD12: 3543.75 | AF12: Poste de Concreto ou Fibra Simplificado Deflexão máxima 1◦0"00" >> Suporte RF em plataforma EV > 30m >> 3
A13: 16 | B13: POSTE | C13: Poste Concreto/Fibra Simplificado | D13: Suporte TX em plataforma EV > 30m | E13: 3 | F13: VB | I13: 9 | J13: 3 | K13: 40 | L13: 1 | M13: 3720.94 | N13: =IF(M13="","",ROUND(M13*PARÂMETROS!$B$4,2)) | O13: 1 | P13: 3720.94 | Q13: =IF(P13="","",ROUND(P13*PARÂMETROS!$B$4,2)) | R13: 2 | S13: 3720.94 | V13: =IF(T13="","",ROUND(T13*PARÂMETROS!$B$5,2)) | Y13: =IFERROR(ROUND(W13/T13,2),"") | Z13: =IFERROR(ROUND(N13/T13,2),"") | AA13: =IFERROR(ROUND(N13/W13,2),"") | AB13: 1 | AC13: 3720.94 | AD13: 3720.94 | AF13: Poste de Concreto ou Fibra Simplificado Deflexão máxima 1◦0"00" >> Suporte TX em plataforma EV > 30m >> 3
A14: 17 | B14: POSTE | C14: Poste Concreto/Fibra Simplificado | D14: SPDA | E14: 3 | F14: VB | I14: 9 | J14: 3 | K14: 45 | L14: 1 | M14: 3906.98 | N14: =IF(M14="","",ROUND(M14*PARÂMETROS!$B$4,2)) | O14: 1 | P14: 3906.98 | Q14: =IF(P14="","",ROUND(P14*PARÂMETROS!$B$4,2)) | R14: 2 | S14: 3906.98 | V14: =IF(T14="","",ROUND(T14*PARÂMETROS!$B$5,2)) | Y14: =IFERROR(ROUND(W14/T14,2),"") | Z14: =IFERROR(ROUND(N14/T14,2),"") | AA14: =IFERROR(ROUND(N14/W14,2),"") | AB14: 1 | AC14: 3906.98 | AD14: 3906.98 | AF14: Poste de Concreto ou Fibra Simplificado Deflexão máxima 1◦0"00" >> SPDA >> 3
A15: 18 | B15: POSTE | C15: Poste Concreto/Fibra Simplificado | E15: Poste Concreto/Fibra Simplificado · 9m · AeV 4m² · 30m/s | F15: VB | H15: 4 | I15: 9 | J15: 4 | K15: 30 | L15: 1 | M15: 3881.25 | N15: =IF(M15="","",ROUND(M15*PARÂMETROS!$B$4,2)) | O15: 1 | P15: 3881.25 | Q15: =IF(P15="","",ROUND(P15*PARÂMETROS!$B$4,2)) | R15: 2 | S15: 3881.25 | V15: =IF(T15="","",ROUND(T15*PARÂMETROS!$B$5,2)) | Y15: =IFERROR(ROUND(W15/T15,2),"") | Z15: =IFERROR(ROUND(N15/T15,2),"") | AA15: =IFERROR(ROUND(N15/W15,2),"") | AB15: 1 | AC15: 3881.25 | AD15: 3881.25 | AF15: Poste de Concreto ou Fibra Simplificado Deflexão máxima 1◦0"00" >> 4
A16: 19 | B16: POSTE | C16: Poste Concreto/Fibra Simplificado | D16: Escada EV > 30m | E16: 4 | F16: VB | I16: 9 | J16: 4 | K16: 35 | L16: 1 | M16: 4075.31 | N16: =IF(M16="","",ROUND(M16*PARÂMETROS!$B$4,2)) | O16: 1 | P16: 4075.31 | Q16: =IF(P16="","",ROUND(P16*PARÂMETROS!$B$4,2)) | R16: 2 | S16: 4075.31 | V16: =IF(T16="","",ROUND(T16*PARÂMETROS!$B$5,2)) | Y16: =IFERROR(ROUND(W16/T16,2),"") | Z16: =IFERROR(ROUND(N16/T16,2),"") | AA16: =IFERROR(ROUND(N16/W16,2),"") | AB16: 1 | AC16: 4075.31 | AD16: 4075.31 | AF16: Poste de Concreto ou Fibra Simplificado Deflexão máxima 1◦0"00" >> Escada EV > 30m >> 4
A17: 20 | B17: POSTE | C17: Poste Concreto/Fibra Simplificado | D17: Trava quedas | E17: 4 | F17: VB | I17: 9 | J17: 4 | K17: 40 | L17: 1 | M17: 4279.08 | N17: =IF(M17="","",ROUND(M17*PARÂMETROS!$B$4,2)) | O17: 1 | P17: 4279.08 | Q17: =IF(P17="","",ROUND(P17*PARÂMETROS!$B$4,2)) | R17: 2 | S17: 4279.08 | V17: =IF(T17="","",ROUND(T17*PARÂMETROS!$B$5,2)) | Y17: =IFERROR(ROUND(W17/T17,2),"") | Z17: =IFERROR(ROUND(N17/T17,2),"") | AA17: =IFERROR(ROUND(N17/W17,2),"") | AB17: 1 | AC17: 4279.08 | AD17: 4279.08 | AF17: Poste de Concreto ou Fibra Simplificado Deflexão máxima 1◦0"00" >> Trava quedas >> 4
A18: 21 | B18: POSTE | C18: Poste Concreto/Fibra Simplificado | D18: Trava quedas | E18: 4 | F18: VB | I18: 9 | J18: 4 | K18: 45 | L18: 1 | M18: 4493.03 | N18: =IF(M18="","",ROUND(M18*PARÂMETROS!$B$4,2)) | O18: 1 | P18: 4493.03 | Q18: =IF(P18="","",ROUND(P18*PARÂMETROS!$B$4,2)) | R18: 2 | S18: 4493.03 | V18: =IF(T18="","",ROUND(T18*PARÂMETROS!$B$5,2)) | Y18: =IFERROR(ROUND(W18/T18,2),"") | Z18: =IFERROR(ROUND(N18/T18,2),"") | AA18: =IFERROR(ROUND(N18/W18,2),"") | AB18: 1 | AC18: 4493.03 | AD18: 4493.03 | AF18: Poste de Concreto ou Fibra Simplificado Deflexão máxima 1◦0"00" >> Trava quedas >> 4
A19: 22 | B19: POSTE | C19: Poste Concreto/Fibra Simplificado | D19: Esteriamento Horizontal EV > 30m | E19: 5 | F19: VB | I19: 9 | J19: 5 | K19: 30 | L19: 1 | M19: 4463.44 | N19: =IF(M19="","",ROUND(M19*PARÂMETROS!$B$4,2)) | O19: 1 | P19: 4463.44 | Q19: =IF(P19="","",ROUND(P19*PARÂMETROS!$B$4,2)) | R19: 2 | S19: 4463.44 | V19: =IF(T19="","",ROUND(T19*PARÂMETROS!$B$5,2)) | Y19: =IFERROR(ROUND(W19/T19,2),"") | Z19: =IFERROR(ROUND(N19/T19,2),"") | AA19: =IFERROR(ROUND(N19/W19,2),"") | AB19: 1 | AC19: 4463.44 | AD19: 4463.44 | AF19: Poste de Concreto ou Fibra Simplificado Deflexão máxima 1◦0"00" >> Esteriamento Horizontal EV > 30m >> 5
A20: 23 | B20: POSTE | C20: Poste Concreto/Fibra Simplificado | D20: Esteriamento Horizontal EV > 30m | E20: 5 | F20: VB | I20: 9 | J20: 5 | K20: 35 | L20: 1 | M20: 4686.61 | N20: =IF(M20="","",ROUND(M20*PARÂMETROS!$B$4,2)) | O20: 1 | P20: 4686.61 | Q20: =IF(P20="","",ROUND(P20*PARÂMETROS!$B$4,2)) | R20: 2 | S20: 4686.61 | V20: =IF(T20="","",ROUND(T20*PARÂMETROS!$B$5,2)) | Y20: =IFERROR(ROUND(W20/T20,2),"") | Z20: =IFERROR(ROUND(N20/T20,2),"") | AA20: =IFERROR(ROUND(N20/W20,2),"") | AB20: 1 | AC20: 4686.61 | AD20: 4686.61 | AF20: Poste de Concreto ou Fibra Simplificado Deflexão máxima 1◦0"00" >> Esteriamento Horizontal EV > 30m >> 5
A21: 24 | B21: POSTE | C21: Poste Concreto/Fibra Simplificado | D21: Esteriamento Horizontal EV > 30m | E21: 5 | F21: VB | I21: 9 | J21: 5 | K21: 40 | L21: 1 | M21: 4920.94 | N21: =IF(M21="","",ROUND(M21*PARÂMETROS!$B$4,2)) | O21: 1 | P21: 4920.94 | Q21: =IF(P21="","",ROUND(P21*PARÂMETROS!$B$4,2)) | R21: 2 | S21: 4920.94 | V21: =IF(T21="","",ROUND(T21*PARÂMETROS!$B$5,2)) | Y21: =IFERROR(ROUND(W21/T21,2),"") | Z21: =IFERROR(ROUND(N21/T21,2),"") | AA21: =IFERROR(ROUND(N21/W21,2),"") | AB21: 1 | AC21: 4920.94 | AD21: 4920.94 | AF21: Poste de Concreto ou Fibra Simplificado Deflexão máxima 1◦0"00" >> Esteriamento Horizontal EV > 30m >> 5
A22: 25 | B22: POSTE | C22: Poste Concreto/Fibra Simplificado | D22: Balizamento Baixa Intensidade EV até 45m | E22: 5 | F22: VB | I22: 9 | J22: 5 | K22: 45 | L22: 1 | M22: 5166.99 | N22: =IF(M22="","",ROUND(M22*PARÂMETROS!$B$4,2)) | O22: 1 | P22: 5166.99 | Q22: =IF(P22="","",ROUND(P22*PARÂMETROS!$B$4,2)) | R22: 2 | S22: 5166.99 | V22: =IF(T22="","",ROUND(T22*PARÂMETROS!$B$5,2)) | Y22: =IFERROR(ROUND(W22/T22,2),"") | Z22: =IFERROR(ROUND(N22/T22,2),"") | AA22: =IFERROR(ROUND(N22/W22,2),"") | AB22: 1 | AC22: 5166.99 | AD22: 5166.99 | AF22: Poste de Concreto ou Fibra Simplificado Deflexão máxima 1◦0"00" >> Balizamento Baixa Intensidade EV até 45m >> 5
A23: 26 | B23: POSTE | C23: Poste Metálico Simplificado | E23: Poste Metálico Simplificado · 9m · AeV 3m² · 30m/s | F23: VB | H23: 3 | I23: 9 | J23: 3 | K23: 30 | L23: 5 | M23: 8018.55 | N23: =IF(M23="","",ROUND(M23*PARÂMETROS!$B$4,2)) | O23: 5 | P23: 8018.55 | Q23: =IF(P23="","",ROUND(P23*PARÂMETROS!$B$4,2)) | R23: 10 | S23: 8018.55 | V23: =IF(T23="","",ROUND(T23*PARÂMETROS!$B$5,2)) | Y23: =IFERROR(ROUND(W23/T23,2),"") | Z23: =IFERROR(ROUND(N23/T23,2),"") | AA23: =IFERROR(ROUND(N23/W23,2),"") | AB23: 4.7 | AC23: 12075.67 | AD23: 8018.55 | AF23: Poste de Metálico Simplificado Deflexão máxima 1◦0"00" Fornecimento de Poste inclui gabaritos, peças, placa de identificação, parafusos e tudo o que for necessário para sua correta instalação, sempre galvanizado a quente (≥ 84micron, NBR 6323). >> 3
A24: 27 | B24: POSTE | C24: Poste Metálico Simplificado | E24: Poste Metálico Simplificado · 9m · AeV 3m² · 35m/s | F24: VB | H24: 3 | I24: 9 | J24: 3 | K24: 35 | L24: 5 | M24: 8018.55 | N24: =IF(M24="","",ROUND(M24*PARÂMETROS!$B$4,2)) | O24: 5 | P24: 8018.55 | Q24: =IF(P24="","",ROUND(P24*PARÂMETROS!$B$4,2)) | R24: 10 | S24: 8018.55 | V24: =IF(T24="","",ROUND(T24*PARÂMETROS!$B$5,2)) | Y24: =IFERROR(ROUND(W24/T24,2),"") | Z24: =IFERROR(ROUND(N24/T24,2),"") | AA24: =IFERROR(ROUND(N24/W24,2),"") | AB24: 4.7 | AC24: 12101.49 | AD24: 8018.55 | AF24: Poste de Metálico Simplificado Deflexão máxima 1◦0"00" Fornecimento de Poste inclui gabaritos, peças, placa de identificação, parafusos e tudo o que for necessário para sua correta instalação, sempre galvanizado a quente (≥ 84micron, NBR 6323). >> 3
A25: 28 | B25: POSTE | C25: Poste Metálico Simplificado | E25: Poste Metálico Simplificado · 9m · AeV 3m² · 40m/s | F25: VB | H25: 3 | I25: 9 | J25: 3 | K25: 40 | L25: 5 | M25: 8744.2 | N25: =IF(M25="","",ROUND(M25*PARÂMETROS!$B$4,2)) | O25: 5 | P25: 8744.2 | Q25: =IF(P25="","",ROUND(P25*PARÂMETROS!$B$4,2)) | R25: 10 | S25: 8744.2 | V25: =IF(T25="","",ROUND(T25*PARÂMETROS!$B$5,2)) | Y25: =IFERROR(ROUND(W25/T25,2),"") | Z25: =IFERROR(ROUND(N25/T25,2),"") | AA25: =IFERROR(ROUND(N25/W25,2),"") | AB25: 3.2 | AC25: 12723.31 | AD25: 8744.2 | AF25: Poste de Metálico Simplificado Deflexão máxima 1◦0"00" Fornecimento de Poste inclui gabaritos, peças, placa de identificação, parafusos e tudo o que for necessário para sua correta instalação, sempre galvanizado a quente (≥ 84micron, NBR 6323). >> 3
A26: 29 | B26: POSTE | C26: Poste Metálico Simplificado | E26: Poste Metálico Simplificado · 9m · AeV 3m² · 45m/s | F26: VB | H26: 3 | I26: 9 | J26: 3 | K26: 45 | L26: 5 | M26: 9469.87 | N26: =IF(M26="","",ROUND(M26*PARÂMETROS!$B$4,2)) | O26: 5 | P26: 9469.87 | Q26: =IF(P26="","",ROUND(P26*PARÂMETROS!$B$4,2)) | R26: 10 | S26: 9469.87 | V26: =IF(T26="","",ROUND(T26*PARÂMETROS!$B$5,2)) | Y26: =IFERROR(ROUND(W26/T26,2),"") | Z26: =IFERROR(ROUND(N26/T26,2),"") | AA26: =IFERROR(ROUND(N26/W26,2),"") | AB26: 3.1 | AC26: 12957.27 | AD26: 9469.87 | AF26: Poste de Metálico Simplificado Deflexão máxima 1◦0"00" Fornecimento de Poste inclui gabaritos, peças, placa de identificação, parafusos e tudo o que for necessário para sua correta instalação, sempre galvanizado a quente (≥ 84micron, NBR 6323). >> 3
A27: 30 | B27: POSTE | C27: Poste Metálico Simplificado | E27: Poste Metálico Simplificado · 9m · AeV 4m² · 30m/s | F27: VB | H27: 4 | I27: 9 | J27: 4 | K27: 30 | L27: 5 | M27: 8152.19 | N27: =IF(M27="","",ROUND(M27*PARÂMETROS!$B$4,2)) | O27: 5 | P27: 8152.19 | Q27: =IF(P27="","",ROUND(P27*PARÂMETROS!$B$4,2)) | R27: 10 | S27: 8152.19 | V27: =IF(T27="","",ROUND(T27*PARÂMETROS!$B$5,2)) | Y27: =IFERROR(ROUND(W27/T27,2),"") | Z27: =IFERROR(ROUND(N27/T27,2),"") | AA27: =IFERROR(ROUND(N27/W27,2),"") | AB27: 4.7 | AC27: 12503.95 | AD27: 8152.19 | AF27: Poste de Metálico Simplificado Deflexão máxima 1◦0"00" Fornecimento de Poste inclui gabaritos, peças, placa de identificação, parafusos e tudo o que for necessário para sua correta instalação, sempre galvanizado a quente (≥ 84micron, NBR 6323). >> 4
A28: 31 | B28: POSTE | C28: Poste Metálico Simplificado | E28: Poste Metálico Simplificado · 9m · AeV 4m² · 35m/s | F28: VB | H28: 4 | I28: 9 | J28: 4 | K28: 35 | L28: 5 | M28: 8559.8 | N28: =IF(M28="","",ROUND(M28*PARÂMETROS!$B$4,2)) | O28: 5 | P28: 8559.8 | Q28: =IF(P28="","",ROUND(P28*PARÂMETROS!$B$4,2)) | R28: 10 | S28: 8559.8 | V28: =IF(T28="","",ROUND(T28*PARÂMETROS!$B$5,2)) | Y28: =IFERROR(ROUND(W28/T28,2),"") | Z28: =IFERROR(ROUND(N28/T28,2),"") | AA28: =IFERROR(ROUND(N28/W28,2),"") | AB28: 4.7 | AC28: 12601.29 | AD28: 8559.8 | AF28: Poste de Metálico Simplificado Deflexão máxima 1◦0"00" Fornecimento de Poste inclui gabaritos, peças, placa de identificação, parafusos e tudo o que for necessário para sua correta instalação, sempre galvanizado a quente (≥ 84micron, NBR 6323). >> 4
A29: 32 | B29: POSTE | C29: Poste Metálico Simplificado | E29: Poste Metálico Simplificado · 9m · AeV 4m² · 40m/s | F29: VB | H29: 4 | I29: 9 | J29: 4 | K29: 40 | L29: 5 | M29: 8889.93 | N29: =IF(M29="","",ROUND(M29*PARÂMETROS!$B$4,2)) | O29: 5 | P29: 8889.93 | Q29: =IF(P29="","",ROUND(P29*PARÂMETROS!$B$4,2)) | R29: 10 | S29: 8889.93 | V29: =IF(T29="","",ROUND(T29*PARÂMETROS!$B$5,2)) | Y29: =IFERROR(ROUND(W29/T29,2),"") | Z29: =IFERROR(ROUND(N29/T29,2),"") | AA29: =IFERROR(ROUND(N29/W29,2),"") | AB29: 3.2 | AC29: 13144.01 | AD29: 8889.93 | AF29: Poste de Metálico Simplificado Deflexão máxima 1◦0"00" Fornecimento de Poste inclui gabaritos, peças, placa de identificação, parafusos e tudo o que for necessário para sua correta instalação, sempre galvanizado a quente (≥ 84micron, NBR 6323). >> 4
A30: 33 | B30: POSTE | C30: Poste Metálico Simplificado | E30: Poste Metálico Simplificado · 9m · AeV 4m² · 45m/s | F30: VB | H30: 4 | I30: 9 | J30: 4 | K30: 45 | L30: 5 | M30: 9627.7 | N30: =IF(M30="","",ROUND(M30*PARÂMETROS!$B$4,2)) | O30: 5 | P30: 9627.7 | Q30: =IF(P30="","",ROUND(P30*PARÂMETROS!$B$4,2)) | R30: 10 | S30: 9627.7 | V30: =IF(T30="","",ROUND(T30*PARÂMETROS!$B$5,2)) | Y30: =IFERROR(ROUND(W30/T30,2),"") | Z30: =IFERROR(ROUND(N30/T30,2),"") | AA30: =IFERROR(ROUND(N30/W30,2),"") | AB30: 3.1 | AC30: 13390.39 | AD30: 9627.7 | AF30: Poste de Metálico Simplificado Deflexão máxima 1◦0"00" Fornecimento de Poste inclui gabaritos, peças, placa de identificação, parafusos e tudo o que for necessário para sua correta instalação, sempre galvanizado a quente (≥ 84micron, NBR 6323). >> 4
A31: 34 | B31: POSTE | C31: Poste Metálico Simplificado | E31: Poste Metálico Simplificado · 9m · AeV 5m² · 30m/s | F31: VB | H31: 5 | I31: 9 | J31: 5 | K31: 30 | L31: 5 | M31: 8285.83 | N31: =IF(M31="","",ROUND(M31*PARÂMETROS!$B$4,2)) | O31: 5 | P31: 8285.83 | Q31: =IF(P31="","",ROUND(P31*PARÂMETROS!$B$4,2)) | R31: 10 | S31: 8285.83 | V31: =IF(T31="","",ROUND(T31*PARÂMETROS!$B$5,2)) | Y31: =IFERROR(ROUND(W31/T31,2),"") | Z31: =IFERROR(ROUND(N31/T31,2),"") | AA31: =IFERROR(ROUND(N31/W31,2),"") | AB31: 4.7 | AC31: 13314.78 | AD31: 8285.83 | AF31: Poste de Metálico Simplificado Deflexão máxima 1◦0"00" Fornecimento de Poste inclui gabaritos, peças, placa de identificação, parafusos e tudo o que for necessário para sua correta instalação, sempre galvanizado a quente (≥ 84micron, NBR 6323). >> 5
A32: 35 | B32: POSTE | C32: Poste Metálico Simplificado | E32: Poste Metálico Simplificado · 9m · AeV 5m² · 35m/s | F32: VB | H32: 5 | I32: 9 | J32: 5 | K32: 35 | L32: 5 | M32: 8700.12 | N32: =IF(M32="","",ROUND(M32*PARÂMETROS!$B$4,2)) | O32: 5 | P32: 8700.12 | Q32: =IF(P32="","",ROUND(P32*PARÂMETROS!$B$4,2)) | R32: 10 | S32: 8700.12 | V32: =IF(T32="","",ROUND(T32*PARÂMETROS!$B$5,2)) | Y32: =IFERROR(ROUND(W32/T32,2),"") | Z32: =IFERROR(ROUND(N32/T32,2),"") | AA32: =IFERROR(ROUND(N32/W32,2),"") | AB32: 4.7 | AC32: 13403.46 | AD32: 8700.12 | AF32: Poste de Metálico Simplificado Deflexão máxima 1◦0"00" Fornecimento de Poste inclui gabaritos, peças, placa de identificação, parafusos e tudo o que for necessário para sua correta instalação, sempre galvanizado a quente (≥ 84micron, NBR 6323). >> 5
A33: 36 | B33: POSTE | C33: Poste Metálico Simplificado | E33: Poste Metálico Simplificado · 9m · AeV 5m² · 40m/s | F33: VB | H33: 5 | I33: 9 | J33: 5 | K33: 40 | L33: 5 | M33: 9035.67 | N33: =IF(M33="","",ROUND(M33*PARÂMETROS!$B$4,2)) | O33: 5 | P33: 9035.67 | Q33: =IF(P33="","",ROUND(P33*PARÂMETROS!$B$4,2)) | R33: 10 | S33: 9035.67 | V33: =IF(T33="","",ROUND(T33*PARÂMETROS!$B$5,2)) | Y33: =IFERROR(ROUND(W33/T33,2),"") | Z33: =IFERROR(ROUND(N33/T33,2),"") | AA33: =IFERROR(ROUND(N33/W33,2),"") | AB33: 3.2 | AC33: 13947.27 | AD33: 9035.67 | AF33: Poste de Metálico Simplificado Deflexão máxima 1◦0"00" Fornecimento de Poste inclui gabaritos, peças, placa de identificação, parafusos e tudo o que for necessário para sua correta instalação, sempre galvanizado a quente (≥ 84micron, NBR 6323). >> 5
A34: 37 | B34: POSTE | C34: Poste Metálico Simplificado | E34: Poste Metálico Simplificado · 9m · AeV 5m² · 45m/s | F34: VB | H34: 5 | I34: 9 | J34: 5 | K34: 45 | L34: 5 | M34: 9785.53 | N34: =IF(M34="","",ROUND(M34*PARÂMETROS!$B$4,2)) | O34: 5 | P34: 9785.53 | Q34: =IF(P34="","",ROUND(P34*PARÂMETROS!$B$4,2)) | R34: 10 | S34: 9785.53 | V34: =IF(T34="","",ROUND(T34*PARÂMETROS!$B$5,2)) | Y34: =IFERROR(ROUND(W34/T34,2),"") | Z34: =IFERROR(ROUND(N34/T34,2),"") | AA34: =IFERROR(ROUND(N34/W34,2),"") | AB34: 3.1 | AC34: 14196.06 | AD34: 9785.53 | AF34: Poste de Metálico Simplificado Deflexão máxima 1◦0"00" Fornecimento de Poste inclui gabaritos, peças, placa de identificação, parafusos e tudo o que for necessário para sua correta instalação, sempre galvanizado a quente (≥ 84micron, NBR 6323). >> 5
A35: 38 | B35: POSTE | C35: Poste Metálico Simplificado | E35: Kit de ancoragem Poste 9m | F35: VB | I35: 9 | L35: 5 | M35: 1375 | N35: =IF(M35="","",ROUND(M35*PARÂMETROS!$B$4,2)) | O35: 5 | P35: 1375 | Q35: =IF(P35="","",ROUND(P35*PARÂMETROS!$B$4,2)) | R35: 10 | S35: 1375 | V35: =IF(T35="","",ROUND(T35*PARÂMETROS!$B$5,2)) | Y35: =IFERROR(ROUND(W35/T35,2),"") | Z35: =IFERROR(ROUND(N35/T35,2),"") | AA35: =IFERROR(ROUND(N35/W35,2),"") | AB35: 5.5 | AC35: 1550.57 | AD35: 1375 | AF35: Poste de Metálico Simplificado Deflexão máxima 1◦0"00" Fornecimento de Poste inclui gabaritos, peças, placa de identificação, parafusos e tudo o que for necessário para sua correta instalação, sempre galvanizado a quente (≥ 84micron, NBR 6323). >> Kit de ancoragem Poste 9m
A36: 39 | B36: POSTE | C36: Montagem Poste | E36: Montagem Poste | F36: VB | I36: 9 | L36: 5 | M36: 11631.09 | N36: =IF(M36="","",ROUND(M36*PARÂMETROS!$B$4,2)) | O36: 6 | P36: 12700.54 | Q36: =IF(P36="","",ROUND(P36*PARÂMETROS!$B$4,2)) | R36: 11 | S36: 11631.09 | V36: =IF(T36="","",ROUND(T36*PARÂMETROS!$B$5,2)) | Y36: =IFERROR(ROUND(W36/T36,2),"") | Z36: =IFERROR(ROUND(N36/T36,2),"") | AA36: =IFERROR(ROUND(N36/W36,2),"") | AB36: 5.7 | AC36: 14259.29 | AD36: 11631.09 | AF36: Montagem Poste >> Inclui mão de obra, equipamentos p/ içamento, ferramentas e o que for necessário para correta execução da montagem da EV.
A37: 40 | B37: MASTRO | C37: Mastro | E37: Mastro · 10m · AeV 3m² · 45m/s | F37: VB | G37: - | H37: 3 | I37: 10 | J37: 3 | K37: 45 | L37: 4 | M37: 33371.64 | N37: =IF(M37="","",ROUND(M37*PARÂMETROS!$B$4,2)) | O37: 4 | P37: 30427.16 | Q37: =IF(P37="","",ROUND(P37*PARÂMETROS!$B$4,2)) | R37: 8 | S37: 30427.16 | V37: =IF(T37="","",ROUND(T37*PARÂMETROS!$B$5,2)) | Y37: =IFERROR(ROUND(W37/T37,2),"") | Z37: =IFERROR(ROUND(N37/T37,2),"") | AA37: =IFERROR(ROUND(N37/W37,2),"") | AB37: 8.4 | AC37: 34744.96 | AD37: 28464.17 | AF37: Mastros Mastros com altura superior 2m deverão ser providos de pedaleira e cabo trava-quedas. >> 3
A38: 41 | B38: MASTRO | C38: Mastro | E38: Mastro · 10m · AeV 4m² · 45m/s | F38: VB | G38: - | H38: 4 | I38: 10 | J38: 4 | K38: 45 | L38: 4 | M38: 34598.51 | N38: =IF(M38="","",ROUND(M38*PARÂMETROS!$B$4,2)) | O38: 4 | P38: 31506.8 | Q38: =IF(P38="","",ROUND(P38*PARÂMETROS!$B$4,2)) | R38: 8 | S38: 31506.8 | V38: =IF(T38="","",ROUND(T38*PARÂMETROS!$B$5,2)) | Y38: =IFERROR(ROUND(W38/T38,2),"") | Z38: =IFERROR(ROUND(N38/T38,2),"") | AA38: =IFERROR(ROUND(N38/W38,2),"") | AB38: 9.8 | AC38: 37922.49 | AD38: 29445.67 | AF38: Mastros Mastros com altura superior 2m deverão ser providos de pedaleira e cabo trava-quedas. >> 4
A39: 42 | B39: POSTE | C39: Poste Concreto/Fibra Simplificado | E39: Balizamento Média Intensidade EV de 46 até 150m — 3 | F39: VB | I39: 12 | J39: 3 | K39: 30 | L39: 1 | M39: 4950 | N39: =IF(M39="","",ROUND(M39*PARÂMETROS!$B$4,2)) | O39: 1 | P39: 4950 | Q39: =IF(P39="","",ROUND(P39*PARÂMETROS!$B$4,2)) | R39: 2 | S39: 4950 | V39: =IF(T39="","",ROUND(T39*PARÂMETROS!$B$5,2)) | Y39: =IFERROR(ROUND(W39/T39,2),"") | Z39: =IFERROR(ROUND(N39/T39,2),"") | AA39: =IFERROR(ROUND(N39/W39,2),"") | AB39: 1 | AC39: 4950 | AD39: 4950 | AF39: Poste de Concreto ou Fibra Simplificado Deflexão máxima 1◦0"00" >> Balizamento Média Intensidade EV de 46 até 150m >> 3
A40: 43 | B40: POSTE | C40: Poste Concreto/Fibra Simplificado | D40: FCI | E40: 3 | F40: VB | I40: 12 | J40: 3 | K40: 35 | L40: 1 | M40: 5197.5 | N40: =IF(M40="","",ROUND(M40*PARÂMETROS!$B$4,2)) | O40: 1 | P40: 5197.5 | Q40: =IF(P40="","",ROUND(P40*PARÂMETROS!$B$4,2)) | R40: 2 | S40: 5197.5 | V40: =IF(T40="","",ROUND(T40*PARÂMETROS!$B$5,2)) | Y40: =IFERROR(ROUND(W40/T40,2),"") | Z40: =IFERROR(ROUND(N40/T40,2),"") | AA40: =IFERROR(ROUND(N40/W40,2),"") | AB40: 1 | AC40: 5197.5 | AD40: 5197.5 | AF40: Poste de Concreto ou Fibra Simplificado Deflexão máxima 1◦0"00" >> FCI >> 3
A41: 44 | B41: POSTE | C41: Poste Concreto/Fibra Simplificado | D41: Projeto | E41: 3 | F41: VB | I41: 12 | J41: 3 | K41: 40 | L41: 1 | M41: 5457.38 | N41: =IF(M41="","",ROUND(M41*PARÂMETROS!$B$4,2)) | O41: 1 | P41: 5457.38 | Q41: =IF(P41="","",ROUND(P41*PARÂMETROS!$B$4,2)) | R41: 2 | S41: 5457.38 | V41: =IF(T41="","",ROUND(T41*PARÂMETROS!$B$5,2)) | Y41: =IFERROR(ROUND(W41/T41,2),"") | Z41: =IFERROR(ROUND(N41/T41,2),"") | AA41: =IFERROR(ROUND(N41/W41,2),"") | AB41: 1 | AC41: 5457.38 | AD41: 5457.38 | AF41: Poste de Concreto ou Fibra Simplificado Deflexão máxima 1◦0"00" >> Projeto >> 3
A42: 45 | B42: POSTE | C42: Poste Concreto/Fibra Simplificado | D42: Projeto | E42: 3 | F42: VB | I42: 12 | J42: 3 | K42: 45 | L42: 1 | M42: 5730.24 | N42: =IF(M42="","",ROUND(M42*PARÂMETROS!$B$4,2)) | O42: 1 | P42: 5730.24 | Q42: =IF(P42="","",ROUND(P42*PARÂMETROS!$B$4,2)) | R42: 2 | S42: 5730.24 | V42: =IF(T42="","",ROUND(T42*PARÂMETROS!$B$5,2)) | Y42: =IFERROR(ROUND(W42/T42,2),"") | Z42: =IFERROR(ROUND(N42/T42,2),"") | AA42: =IFERROR(ROUND(N42/W42,2),"") | AB42: 1 | AC42: 5730.24 | AD42: 5730.24 | AF42: Poste de Concreto ou Fibra Simplificado Deflexão máxima 1◦0"00" >> Projeto >> 3
A43: 46 | B43: POSTE | C43: Poste Concreto/Fibra Simplificado | D43: Projeto | E43: 4 | F43: VB | I43: 12 | J43: 4 | K43: 30 | L43: 1 | M43: 5692.5 | N43: =IF(M43="","",ROUND(M43*PARÂMETROS!$B$4,2)) | O43: 1 | P43: 5692.5 | Q43: =IF(P43="","",ROUND(P43*PARÂMETROS!$B$4,2)) | R43: 2 | S43: 5692.5 | V43: =IF(T43="","",ROUND(T43*PARÂMETROS!$B$5,2)) | Y43: =IFERROR(ROUND(W43/T43,2),"") | Z43: =IFERROR(ROUND(N43/T43,2),"") | AA43: =IFERROR(ROUND(N43/W43,2),"") | AB43: 1 | AC43: 5692.5 | AD43: 5692.5 | AF43: Poste de Concreto ou Fibra Simplificado Deflexão máxima 1◦0"00" >> Projeto >> 4
A44: 47 | B44: POSTE | C44: Poste Concreto/Fibra Simplificado | E44: Mastro 1,8m e fundação em solo para instalação de antena TX (parabólica 1,8m), com eletroduto flexível (envelopado em solo), eletroduto FGF e sistema de fixação para encaminhamento de cabos. — 4 | F44: VB | I44: 12 | J44: 4 | K44: 35 | L44: 1 | M44: 5977.13 | N44: =IF(M44="","",ROUND(M44*PARÂMETROS!$B$4,2)) | O44: 1 | P44: 5977.13 | Q44: =IF(P44="","",ROUND(P44*PARÂMETROS!$B$4,2)) | R44: 2 | S44: 5977.13 | V44: =IF(T44="","",ROUND(T44*PARÂMETROS!$B$5,2)) | Y44: =IFERROR(ROUND(W44/T44,2),"") | Z44: =IFERROR(ROUND(N44/T44,2),"") | AA44: =IFERROR(ROUND(N44/W44,2),"") | AB44: 1 | AC44: 5977.13 | AD44: 5977.13 | AF44: Poste de Concreto ou Fibra Simplificado Deflexão máxima 1◦0"00" >> Mastro 1,8m e fundação em solo para instalação de antena TX (parabólica 1,8m), com eletroduto flexível (envelopado em solo), eletroduto FGF e sistema de fixação para encaminhamento de cabos. >> 4
A45: 48 | B45: POSTE | C45: Poste Concreto/Fibra Simplificado | E45: Poste Concreto/Fibra Simplificado · 12m · AeV 4m² · 40m/s | F45: VB | H45: 4 | I45: 12 | J45: 4 | K45: 40 | L45: 1 | M45: 6275.98 | N45: =IF(M45="","",ROUND(M45*PARÂMETROS!$B$4,2)) | O45: 1 | P45: 6275.98 | Q45: =IF(P45="","",ROUND(P45*PARÂMETROS!$B$4,2)) | R45: 2 | S45: 6275.98 | V45: =IF(T45="","",ROUND(T45*PARÂMETROS!$B$5,2)) | Y45: =IFERROR(ROUND(W45/T45,2),"") | Z45: =IFERROR(ROUND(N45/T45,2),"") | AA45: =IFERROR(ROUND(N45/W45,2),"") | AB45: 1 | AC45: 6275.98 | AD45: 6275.98 | AF45: Poste de Concreto ou Fibra Simplificado Deflexão máxima 1◦0"00" >> 4
A46: 49 | B46: POSTE | C46: Poste Concreto/Fibra Simplificado | E46: Poste Concreto/Fibra Simplificado · 12m · AeV 4m² · 45m/s | F46: VB | H46: 4 | I46: 12 | J46: 4 | K46: 45 | L46: 1 | M46: 6589.78 | N46: =IF(M46="","",ROUND(M46*PARÂMETROS!$B$4,2)) | O46: 1 | P46: 6589.78 | Q46: =IF(P46="","",ROUND(P46*PARÂMETROS!$B$4,2)) | R46: 2 | S46: 6589.78 | V46: =IF(T46="","",ROUND(T46*PARÂMETROS!$B$5,2)) | Y46: =IFERROR(ROUND(W46/T46,2),"") | Z46: =IFERROR(ROUND(N46/T46,2),"") | AA46: =IFERROR(ROUND(N46/W46,2),"") | AB46: 1 | AC46: 6589.78 | AD46: 6589.78 | AF46: Poste de Concreto ou Fibra Simplificado Deflexão máxima 1◦0"00" >> 4
A47: 50 | B47: POSTE | C47: Poste Concreto/Fibra Simplificado | E47: Poste Concreto/Fibra Simplificado · 12m · AeV 5m² · 30m/s | F47: VB | H47: 5 | I47: 12 | J47: 5 | K47: 30 | L47: 1 | M47: 6546.38 | N47: =IF(M47="","",ROUND(M47*PARÂMETROS!$B$4,2)) | O47: 1 | P47: 6546.38 | Q47: =IF(P47="","",ROUND(P47*PARÂMETROS!$B$4,2)) | R47: 2 | S47: 6546.38 | V47: =IF(T47="","",ROUND(T47*PARÂMETROS!$B$5,2)) | Y47: =IFERROR(ROUND(W47/T47,2),"") | Z47: =IFERROR(ROUND(N47/T47,2),"") | AA47: =IFERROR(ROUND(N47/W47,2),"") | AB47: 1 | AC47: 6546.38 | AD47: 6546.38 | AF47: Poste de Concreto ou Fibra Simplificado Deflexão máxima 1◦0"00" >> 5
A48: 51 | B48: POSTE | C48: Poste Concreto/Fibra Simplificado | E48: Poste Concreto/Fibra Simplificado · 12m · AeV 5m² · 35m/s | F48: VB | H48: 5 | I48: 12 | J48: 5 | K48: 35 | L48: 1 | M48: 6873.69 | N48: =IF(M48="","",ROUND(M48*PARÂMETROS!$B$4,2)) | O48: 1 | P48: 6873.69 | Q48: =IF(P48="","",ROUND(P48*PARÂMETROS!$B$4,2)) | R48: 2 | S48: 6873.69 | V48: =IF(T48="","",ROUND(T48*PARÂMETROS!$B$5,2)) | Y48: =IFERROR(ROUND(W48/T48,2),"") | Z48: =IFERROR(ROUND(N48/T48,2),"") | AA48: =IFERROR(ROUND(N48/W48,2),"") | AB48: 1 | AC48: 6873.69 | AD48: 6873.69 | AF48: Poste de Concreto ou Fibra Simplificado Deflexão máxima 1◦0"00" >> 5
A49: 52 | B49: POSTE | C49: Poste Concreto/Fibra Simplificado | E49: Poste Concreto/Fibra Simplificado · 12m · AeV 5m² · 40m/s | F49: VB | H49: 5 | I49: 12 | J49: 5 | K49: 40 | L49: 1 | M49: 7217.38 | N49: =IF(M49="","",ROUND(M49*PARÂMETROS!$B$4,2)) | O49: 1 | P49: 7217.38 | Q49: =IF(P49="","",ROUND(P49*PARÂMETROS!$B$4,2)) | R49: 2 | S49: 7217.38 | V49: =IF(T49="","",ROUND(T49*PARÂMETROS!$B$5,2)) | Y49: =IFERROR(ROUND(W49/T49,2),"") | Z49: =IFERROR(ROUND(N49/T49,2),"") | AA49: =IFERROR(ROUND(N49/W49,2),"") | AB49: 1 | AC49: 7217.38 | AD49: 7217.38 | AF49: Poste de Concreto ou Fibra Simplificado Deflexão máxima 1◦0"00" >> 5
A50: 53 | B50: POSTE | C50: Poste Concreto/Fibra Simplificado | E50: Poste Concreto/Fibra Simplificado · 12m · AeV 5m² · 45m/s | F50: VB | H50: 5 | I50: 12 | J50: 5 | K50: 45 | L50: 1 | M50: 7578.25 | N50: =IF(M50="","",ROUND(M50*PARÂMETROS!$B$4,2)) | O50: 1 | P50: 7578.25 | Q50: =IF(P50="","",ROUND(P50*PARÂMETROS!$B$4,2)) | R50: 2 | S50: 7578.25 | V50: =IF(T50="","",ROUND(T50*PARÂMETROS!$B$5,2)) | Y50: =IFERROR(ROUND(W50/T50,2),"") | Z50: =IFERROR(ROUND(N50/T50,2),"") | AA50: =IFERROR(ROUND(N50/W50,2),"") | AB50: 1 | AC50: 7578.25 | AD50: 7578.25 | AF50: Poste de Concreto ou Fibra Simplificado Deflexão máxima 1◦0"00" >> 5
A51: 54 | B51: POSTE | C51: Poste Metálico Simplificado | E51: Poste Metálico Simplificado · 12m · AeV 3m² · 30m/s | F51: VB | H51: 3 | I51: 12 | J51: 3 | K51: 30 | L51: 5 | M51: 11844.38 | N51: =IF(M51="","",ROUND(M51*PARÂMETROS!$B$4,2)) | O51: 5 | P51: 11844.38 | Q51: =IF(P51="","",ROUND(P51*PARÂMETROS!$B$4,2)) | R51: 10 | S51: 11844.38 | V51: =IF(T51="","",ROUND(T51*PARÂMETROS!$B$5,2)) | Y51: =IFERROR(ROUND(W51/T51,2),"") | Z51: =IFERROR(ROUND(N51/T51,2),"") | AA51: =IFERROR(ROUND(N51/W51,2),"") | AB51: 5.7 | AC51: 17515.63 | AD51: 11844.38 | AF51: Poste de Metálico Simplificado Deflexão máxima 1◦0"00" Fornecimento de Poste inclui gabaritos, peças, placa de identificação, parafusos e tudo o que for necessário para sua correta instalação, sempre galvanizado a quente (≥ 84micron, NBR 6323). >> 3
A52: 55 | B52: POSTE | C52: Poste Metálico Simplificado | E52: Poste Metálico Simplificado · 12m · AeV 3m² · 35m/s | F52: VB | H52: 3 | I52: 12 | J52: 3 | K52: 35 | L52: 5 | M52: 11882.69 | N52: =IF(M52="","",ROUND(M52*PARÂMETROS!$B$4,2)) | O52: 5 | P52: 11882.69 | Q52: =IF(P52="","",ROUND(P52*PARÂMETROS!$B$4,2)) | R52: 10 | S52: 11882.69 | V52: =IF(T52="","",ROUND(T52*PARÂMETROS!$B$5,2)) | Y52: =IFERROR(ROUND(W52/T52,2),"") | Z52: =IFERROR(ROUND(N52/T52,2),"") | AA52: =IFERROR(ROUND(N52/W52,2),"") | AB52: 5.3 | AC52: 17840.42 | AD52: 11882.69 | AF52: Poste de Metálico Simplificado Deflexão máxima 1◦0"00" Fornecimento de Poste inclui gabaritos, peças, placa de identificação, parafusos e tudo o que for necessário para sua correta instalação, sempre galvanizado a quente (≥ 84micron, NBR 6323). >> 3
A53: 56 | B53: POSTE | C53: Poste Metálico Simplificado | E53: Poste Metálico Simplificado · 12m · AeV 3m² · 40m/s | F53: VB | H53: 3 | I53: 12 | J53: 3 | K53: 40 | L53: 5 | M53: 12608.34 | N53: =IF(M53="","",ROUND(M53*PARÂMETROS!$B$4,2)) | O53: 5 | P53: 12608.34 | Q53: =IF(P53="","",ROUND(P53*PARÂMETROS!$B$4,2)) | R53: 10 | S53: 12608.34 | V53: =IF(T53="","",ROUND(T53*PARÂMETROS!$B$5,2)) | Y53: =IFERROR(ROUND(W53/T53,2),"") | Z53: =IFERROR(ROUND(N53/T53,2),"") | AA53: =IFERROR(ROUND(N53/W53,2),"") | AB53: 4.1 | AC53: 18794.91 | AD53: 12608.34 | AF53: Poste de Metálico Simplificado Deflexão máxima 1◦0"00" Fornecimento de Poste inclui gabaritos, peças, placa de identificação, parafusos e tudo o que for necessário para sua correta instalação, sempre galvanizado a quente (≥ 84micron, NBR 6323). >> 3
A54: 57 | B54: POSTE | C54: Poste Metálico Simplificado | E54: Poste Metálico Simplificado · 12m · AeV 3m² · 45m/s | F54: VB | H54: 3 | I54: 12 | J54: 3 | K54: 45 | L54: 5 | M54: 16236.64 | N54: =IF(M54="","",ROUND(M54*PARÂMETROS!$B$4,2)) | O54: 5 | P54: 16236.64 | Q54: =IF(P54="","",ROUND(P54*PARÂMETROS!$B$4,2)) | R54: 10 | S54: 16236.64 | V54: =IF(T54="","",ROUND(T54*PARÂMETROS!$B$5,2)) | Y54: =IFERROR(ROUND(W54/T54,2),"") | Z54: =IFERROR(ROUND(N54/T54,2),"") | AA54: =IFERROR(ROUND(N54/W54,2),"") | AB54: 3.6 | AC54: 19842.01 | AD54: 16236.64 | AF54: Poste de Metálico Simplificado Deflexão máxima 1◦0"00" Fornecimento de Poste inclui gabaritos, peças, placa de identificação, parafusos e tudo o que for necessário para sua correta instalação, sempre galvanizado a quente (≥ 84micron, NBR 6323). >> 3
A55: 58 | B55: POSTE | C55: Poste Metálico Simplificado | E55: Poste Metálico Simplificado · 12m · AeV 4m² · 30m/s | F55: VB | H55: 4 | I55: 12 | J55: 4 | K55: 30 | L55: 5 | M55: 11844.38 | N55: =IF(M55="","",ROUND(M55*PARÂMETROS!$B$4,2)) | O55: 5 | P55: 11844.38 | Q55: =IF(P55="","",ROUND(P55*PARÂMETROS!$B$4,2)) | R55: 10 | S55: 11844.38 | V55: =IF(T55="","",ROUND(T55*PARÂMETROS!$B$5,2)) | Y55: =IFERROR(ROUND(W55/T55,2),"") | Z55: =IFERROR(ROUND(N55/T55,2),"") | AA55: =IFERROR(ROUND(N55/W55,2),"") | AB55: 5.7 | AC55: 17707.55 | AD55: 11844.38 | AF55: Poste de Metálico Simplificado Deflexão máxima 1◦0"00" Fornecimento de Poste inclui gabaritos, peças, placa de identificação, parafusos e tudo o que for necessário para sua correta instalação, sempre galvanizado a quente (≥ 84micron, NBR 6323). >> 4
A56: 59 | B56: POSTE | C56: Poste Metálico Simplificado | E56: Poste Metálico Simplificado · 12m · AeV 4m² · 35m/s | F56: VB | H56: 4 | I56: 12 | J56: 4 | K56: 35 | L56: 5 | M56: 12120.34 | N56: =IF(M56="","",ROUND(M56*PARÂMETROS!$B$4,2)) | O56: 5 | P56: 12120.34 | Q56: =IF(P56="","",ROUND(P56*PARÂMETROS!$B$4,2)) | R56: 10 | S56: 12120.34 | V56: =IF(T56="","",ROUND(T56*PARÂMETROS!$B$5,2)) | Y56: =IFERROR(ROUND(W56/T56,2),"") | Z56: =IFERROR(ROUND(N56/T56,2),"") | AA56: =IFERROR(ROUND(N56/W56,2),"") | AB56: 5.3 | AC56: 18026.69 | AD56: 12120.34 | AF56: Poste de Metálico Simplificado Deflexão máxima 1◦0"00" Fornecimento de Poste inclui gabaritos, peças, placa de identificação, parafusos e tudo o que for necessário para sua correta instalação, sempre galvanizado a quente (≥ 84micron, NBR 6323). >> 4
... A62: 65 | B62: POSTE | C62: Poste Metálico Simplificado | E62: Poste Metálico Simplificado · 12m · AeV 5m² · 45m/s | F62: VB | H62: 5 | I62: 12 | J62: 5 | K62: 45 | L62: 5 | M62: 16777.86 | N62: =IF(M62="","",ROUND(M62*PARÂMETROS!$B$4,2)) | O62: 5 | P62: 16777.86 | Q62: =IF(P62="","",ROUND(P62*PARÂMETROS!$B$4,2)) | R62: 10 | S62: 16777.86 | V62: =IF(T62="","",ROUND(T62*PARÂMETROS!$B$5,2)) | Y62: =IFERROR(ROUND(W62/T62,2),"") | Z62: =IFERROR(ROUND(N62/T62,2),"") | AA62: =IFERROR(ROUND(N62/W62,2),"") | AB62: 3.6 | AC62: 21059 | AD62: 16777.86 | AF62: Poste de Metálico Simplificado Deflexão máxima 1◦0"00" Fornecimento de Poste inclui gabaritos, peças, placa de identificação, parafusos e tudo o que for necessário para sua correta instalação, sempre galvanizado a quente (≥ 84micron, NBR 6323). >> 5
A63: 66 | B63: POSTE | C63: Poste Metálico Simplificado | E63: Kit de ancoragem Poste 12m | F63: VB | I63: 12 | L63: 5 | M63: 1375 | N63: =IF(M63="","",ROUND(M63*PARÂMETROS!$B$4,2)) | O63: 5 | P63: 1375 | Q63: =IF(P63="","",ROUND(P63*PARÂMETROS!$B$4,2)) | R63: 10 | S63: 1375 | V63: =IF(T63="","",ROUND(T63*PARÂMETROS!$B$5,2)) | Y63: =IFERROR(ROUND(W63/T63,2),"") | Z63: =IFERROR(ROUND(N63/T63,2),"") | AA63: =IFERROR(ROUND(N63/W63,2),"") | AB63: 3.7 | AC63: 1795.89 | AD63: 1375 | AF63: Poste de Metálico Simplificado Deflexão máxima 1◦0"00" Fornecimento de Poste inclui gabaritos, peças, placa de identificação, parafusos e tudo o que for necessário para sua correta instalação, sempre galvanizado a quente (≥ 84micron, NBR 6323). >> Kit de ancoragem Poste 12m
A64: 67 | B64: POSTE | C64: Montagem Poste | E64: Montagem Poste | F64: VB | I64: 12 | L64: 5 | M64: 15599.34 | N64: =IF(M64="","",ROUND(M64*PARÂMETROS!$B$4,2)) | O64: 6 | P64: 14999.67 | Q64: =IF(P64="","",ROUND(P64*PARÂMETROS!$B$4,2)) | R64: 11 | S64: 15599.34 | V64: =IF(T64="","",ROUND(T64*PARÂMETROS!$B$5,2)) | Y64: =IFERROR(ROUND(W64/T64,2),"") | Z64: =IFERROR(ROUND(N64/T64,2),"") | AA64: =IFERROR(ROUND(N64/W64,2),"") | AB64: 3.3 | AC64: 16290.56 | AD64: 14413.9 | AF64: Montagem Poste >> Inclui mão de obra, equipamentos p/ içamento, ferramentas e o que for necessário para correta execução da montagem da EV.
A65: 68 | B65: POSTE | C65: Poste Concreto/Fibra Simplificado | E65: Poste Concreto/Fibra Simplificado · 18m · AeV 3m² · 30m/s | F65: VB | H65: 3 | I65: 18 | J65: 3 | K65: 30 | L65: 1 | M65: 21750 | N65: =IF(M65="","",ROUND(M65*PARÂMETROS!$B$4,2)) | O65: 1 | P65: 21750 | Q65: =IF(P65="","",ROUND(P65*PARÂMETROS!$B$4,2)) | R65: 2 | S65: 21750 | V65: =IF(T65="","",ROUND(T65*PARÂMETROS!$B$5,2)) | Y65: =IFERROR(ROUND(W65/T65,2),"") | Z65: =IFERROR(ROUND(N65/T65,2),"") | AA65: =IFERROR(ROUND(N65/W65,2),"") | AB65: 1 | AC65: 21750 | AD65: 21750 | AF65: Poste de Concreto ou Fibra Simplificado Deflexão máxima 1◦0"00" >> 3
A66: 69 | B66: POSTE | C66: Poste Concreto/Fibra Simplificado | E66: Poste Concreto/Fibra Simplificado · 18m · AeV 3m² · 35m/s | F66: VB | H66: 3 | I66: 18 | J66: 3 | K66: 35 | L66: 1 | M66: 22837.5 | N66: =IF(M66="","",ROUND(M66*PARÂMETROS!$B$4,2)) | O66: 1 | P66: 22837.5 | Q66: =IF(P66="","",ROUND(P66*PARÂMETROS!$B$4,2)) | R66: 2 | S66: 22837.5 | V66: =IF(T66="","",ROUND(T66*PARÂMETROS!$B$5,2)) | Y66: =IFERROR(ROUND(W66/T66,2),"") | Z66: =IFERROR(ROUND(N66/T66,2),"") | AA66: =IFERROR(ROUND(N66/W66,2),"") | AB66: 1 | AC66: 22837.5 | AD66: 22837.5 | AF66: Poste de Concreto ou Fibra Simplificado Deflexão máxima 1◦0"00" >> 3
A67: 70 | B67: POSTE | C67: Poste Concreto/Fibra Simplificado | E67: Poste Concreto/Fibra Simplificado · 18m · AeV 3m² · 40m/s | F67: VB | H67: 3 | I67: 18 | J67: 3 | K67: 40 | L67: 1 | M67: 23979.38 | N67: =IF(M67="","",ROUND(M67*PARÂMETROS!$B$4,2)) | O67: 1 | P67: 23979.38 | Q67: =IF(P67="","",ROUND(P67*PARÂMETROS!$B$4,2)) | R67: 2 | S67: 23979.38 | V67: =IF(T67="","",ROUND(T67*PARÂMETROS!$B$5,2)) | Y67: =IFERROR(ROUND(W67/T67,2),"") | Z67: =IFERROR(ROUND(N67/T67,2),"") | AA67: =IFERROR(ROUND(N67/W67,2),"") | AB67: 1 | AC67: 23979.38 | AD67: 23979.38 | AF67: Poste de Concreto ou Fibra Simplificado Deflexão máxima 1◦0"00" >> 3
A68: 71 | B68: POSTE | C68: Poste Concreto/Fibra Simplificado | E68: Poste Concreto/Fibra Simplificado · 18m · AeV 3m² · 45m/s | F68: VB | H68: 3 | I68: 18 | J68: 3 | K68: 45 | L68: 1 | M68: 25178.34 | N68: =IF(M68="","",ROUND(M68*PARÂMETROS!$B$4,2)) | O68: 1 | P68: 25178.34 | Q68: =IF(P68="","",ROUND(P68*PARÂMETROS!$B$4,2)) | R68: 2 | S68: 25178.34 | V68: =IF(T68="","",ROUND(T68*PARÂMETROS!$B$5,2)) | Y68: =IFERROR(ROUND(W68/T68,2),"") | Z68: =IFERROR(ROUND(N68/T68,2),"") | AA68: =IFERROR(ROUND(N68/W68,2),"") | AB68: 1 | AC68: 25178.34 | AD68: 25178.34 | AF68: Poste de Concreto ou Fibra Simplificado Deflexão máxima 1◦0"00" >> 3
A69: 72 | B69: POSTE | C69: Poste Concreto/Fibra Simplificado | E69: Poste Concreto/Fibra Simplificado · 18m · AeV 4m² · 30m/s | F69: VB | H69: 4 | I69: 18 | J69: 4 | K69: 30 | L69: 1 | M69: 25012.5 | N69: =IF(M69="","",ROUND(M69*PARÂMETROS!$B$4,2)) | O69: 1 | P69: 25012.5 | Q69: =IF(P69="","",ROUND(P69*PARÂMETROS!$B$4,2)) | R69: 2 | S69: 25012.5 | V69: =IF(T69="","",ROUND(T69*PARÂMETROS!$B$5,2)) | Y69: =IFERROR(ROUND(W69/T69,2),"") | Z69: =IFERROR(ROUND(N69/T69,2),"") | AA69: =IFERROR(ROUND(N69/W69,2),"") | AB69: 1 | AC69: 25012.5 | AD69: 25012.5 | AF69: Poste de Concreto ou Fibra Simplificado Deflexão máxima 1◦0"00" >> 4
A70: 73 | B70: POSTE | C70: Poste Concreto/Fibra Simplificado | E70: Poste Concreto/Fibra Simplificado · 18m · AeV 4m² · 35m/s | F70: VB | H70: 4 | I70: 18 | J70: 4 | K70: 35 | L70: 1 | M70: 26263.13 | N70: =IF(M70="","",ROUND(M70*PARÂMETROS!$B$4,2)) | O70: 1 | P70: 26263.13 | Q70: =IF(P70="","",ROUND(P70*PARÂMETROS!$B$4,2)) | R70: 2 | S70: 26263.13 | V70: =IF(T70="","",ROUND(T70*PARÂMETROS!$B$5,2)) | Y70: =IFERROR(ROUND(W70/T70,2),"") | Z70: =IFERROR(ROUND(N70/T70,2),"") | AA70: =IFERROR(ROUND(N70/W70,2),"") | AB70: 1 | AC70: 26263.13 | AD70: 26263.13 | AF70: Poste de Concreto ou Fibra Simplificado Deflexão máxima 1◦0"00" >> 4
A71: 74 | B71: POSTE | C71: Poste Concreto/Fibra Simplificado | E71: Poste Concreto/Fibra Simplificado · 18m · AeV 4m² · 40m/s | F71: VB | H71: 4 | I71: 18 | J71: 4 | K71: 40 | L71: 1 | M71: 27576.28 | N71: =IF(M71="","",ROUND(M71*PARÂMETROS!$B$4,2)) | O71: 1 | P71: 27576.28 | Q71: =IF(P71="","",ROUND(P71*PARÂMETROS!$B$4,2)) | R71: 2 | S71: 27576.28 | V71: =IF(T71="","",ROUND(T71*PARÂMETROS!$B$5,2)) | Y71: =IFERROR(ROUND(W71/T71,2),"") | Z71: =IFERROR(ROUND(N71/T71,2),"") | AA71: =IFERROR(ROUND(N71/W71,2),"") | AB71: 1 | AC71: 27576.28 | AD71: 27576.28 | AF71: Poste de Concreto ou Fibra Simplificado Deflexão máxima 1◦0"00" >> 4
A72: 75 | B72: POSTE | C72: Poste Concreto/Fibra Simplificado | E72: Poste Concreto/Fibra Simplificado · 18m · AeV 4m² · 45m/s | F72: VB | H72: 4 | I72: 18 | J72: 4 | K72: 45 | L72: 1 | M72: 28955.1 | N72: =IF(M72="","",ROUND(M72*PARÂMETROS!$B$4,2)) | O72: 1 | P72: 28955.1 | Q72: =IF(P72="","",ROUND(P72*PARÂMETROS!$B$4,2)) | R72: 2 | S72: 28955.1 | V72: =IF(T72="","",ROUND(T72*PARÂMETROS!$B$5,2)) | Y72: =IFERROR(ROUND(W72/T72,2),"") | Z72: =IFERROR(ROUND(N72/T72,2),"") | AA72: =IFERROR(ROUND(N72/W72,2),"") | AB72: 1 | AC72: 28955.1 | AD72: 28955.1 | AF72: Poste de Concreto ou Fibra Simplificado Deflexão máxima 1◦0"00" >> 4
A73: 76 | B73: POSTE | C73: Poste Concreto/Fibra Simplificado | E73: Poste Concreto/Fibra Simplificado · 18m · AeV 5m² · 30m/s | F73: VB | H73: 5 | I73: 18 | J73: 5 | K73: 30 | L73: 1 | M73: 28764.38 | N73: =IF(M73="","",ROUND(M73*PARÂMETROS!$B$4,2)) | O73: 1 | P73: 28764.38 | Q73: =IF(P73="","",ROUND(P73*PARÂMETROS!$B$4,2)) | R73: 2 | S73: 28764.38 | V73: =IF(T73="","",ROUND(T73*PARÂMETROS!$B$5,2)) | Y73: =IFERROR(ROUND(W73/T73,2),"") | Z73: =IFERROR(ROUND(N73/T73,2),"") | AA73: =IFERROR(ROUND(N73/W73,2),"") | AB73: 1 | AC73: 28764.38 | AD73: 28764.38 | AF73: Poste de Concreto ou Fibra Simplificado Deflexão máxima 1◦0"00" >> 5
A74: 77 | B74: POSTE | C74: Poste Concreto/Fibra Simplificado | E74: Poste Concreto/Fibra Simplificado · 18m · AeV 5m² · 35m/s | F74: VB | H74: 5 | I74: 18 | J74: 5 | K74: 35 | L74: 1 | M74: 30202.59 | N74: =IF(M74="","",ROUND(M74*PARÂMETROS!$B$4,2)) | O74: 1 | P74: 30202.59 | Q74: =IF(P74="","",ROUND(P74*PARÂMETROS!$B$4,2)) | R74: 2 | S74: 30202.59 | V74: =IF(T74="","",ROUND(T74*PARÂMETROS!$B$5,2)) | Y74: =IFERROR(ROUND(W74/T74,2),"") | Z74: =IFERROR(ROUND(N74/T74,2),"") | AA74: =IFERROR(ROUND(N74/W74,2),"") | AB74: 1 | AC74: 30202.59 | AD74: 30202.59 | AF74: Poste de Concreto ou Fibra Simplificado Deflexão máxima 1◦0"00" >> 5
A75: 78 | B75: POSTE | C75: Poste Concreto/Fibra Simplificado | E75: Poste Concreto/Fibra Simplificado · 18m · AeV 5m² · 40m/s | F75: VB | H75: 5 | I75: 18 | J75: 5 | K75: 40 | L75: 1 | M75: 31712.72 | N75: =IF(M75="","",ROUND(M75*PARÂMETROS!$B$4,2)) | O75: 1 | P75: 31712.72 | Q75: =IF(P75="","",ROUND(P75*PARÂMETROS!$B$4,2)) | R75: 2 | S75: 31712.72 | V75: =IF(T75="","",ROUND(T75*PARÂMETROS!$B$5,2)) | Y75: =IFERROR(ROUND(W75/T75,2),"") | Z75: =IFERROR(ROUND(N75/T75,2),"") | AA75: =IFERROR(ROUND(N75/W75,2),"") | AB75: 1 | AC75: 31712.72 | AD75: 31712.72 | AF75: Poste de Concreto ou Fibra Simplificado Deflexão máxima 1◦0"00" >> 5
A76: 79 | B76: POSTE | C76: Poste Concreto/Fibra Simplificado | E76: Poste Concreto/Fibra Simplificado · 18m · AeV 5m² · 45m/s | F76: VB | H76: 5 | I76: 18 | J76: 5 | K76: 45 | L76: 1 | M76: 33298.36 | N76: =IF(M76="","",ROUND(M76*PARÂMETROS!$B$4,2)) | O76: 1 | P76: 33298.36 | Q76: =IF(P76="","",ROUND(P76*PARÂMETROS!$B$4,2)) | R76: 2 | S76: 33298.36 | V76: =IF(T76="","",ROUND(T76*PARÂMETROS!$B$5,2)) | Y76: =IFERROR(ROUND(W76/T76,2),"") | Z76: =IFERROR(ROUND(N76/T76,2),"") | AA76: =IFERROR(ROUND(N76/W76,2),"") | AB76: 1 | AC76: 33298.36 | AD76: 33298.36 | AF76: Poste de Concreto ou Fibra Simplificado Deflexão máxima 1◦0"00" >> 5
... A88: 91 | B88: POSTE | C88: Poste Metálico Simplificado | E88: Poste Metálico Simplificado · 18m · AeV 5m² · 45m/s | F88: VB | H88: 5 | I88: 18 | J88: 5 | K88: 45 | L88: 5 | M88: 33252.15 | N88: =IF(M88="","",ROUND(M88*PARÂMETROS!$B$4,2)) | O88: 5 | P88: 33252.15 | Q88: =IF(P88="","",ROUND(P88*PARÂMETROS!$B$4,2)) | R88: 10 | S88: 33252.15 | V88: =IF(T88="","",ROUND(T88*PARÂMETROS!$B$5,2)) | Y88: =IFERROR(ROUND(W88/T88,2),"") | Z88: =IFERROR(ROUND(N88/T88,2),"") | AA88: =IFERROR(ROUND(N88/W88,2),"") | AB88: 2 | AC88: 29635.09 | AD88: 33252.15 | AF88: Poste de Metálico Simplificado Deflexão máxima 1◦0"00" Fornecimento de Poste inclui gabaritos, peças, placa de identificação, parafusos e tudo o que for necessário para sua correta instalação, sempre galvanizado a quente (≥ 84micron, NBR 6323). >> 5
A89: 92 | B89: POSTE | C89: Poste Metálico Simplificado | E89: Kit de ancoragem Poste 18m | F89: VB | I89: 18 | L89: 5 | M89: 2391.26 | N89: =IF(M89="","",ROUND(M89*PARÂMETROS!$B$4,2)) | O89: 5 | P89: 2391.26 | Q89: =IF(P89="","",ROUND(P89*PARÂMETROS!$B$4,2)) | R89: 10 | S89: 2391.26 | V89: =IF(T89="","",ROUND(T89*PARÂMETROS!$B$5,2)) | Y89: =IFERROR(ROUND(W89/T89,2),"") | Z89: =IFERROR(ROUND(N89/T89,2),"") | AA89: =IFERROR(ROUND(N89/W89,2),"") | AB89: 2.5 | AC89: 2251.2 | AD89: 2391.26 | AF89: Poste de Metálico Simplificado Deflexão máxima 1◦0"00" Fornecimento de Poste inclui gabaritos, peças, placa de identificação, parafusos e tudo o que for necessário para sua correta instalação, sempre galvanizado a quente (≥ 84micron, NBR 6323). >> Kit de ancoragem Poste 18m
A90: 93 | B90: POSTE | C90: Montagem Poste | E90: Montagem Poste | F90: VB | I90: 18 | L90: 5 | M90: 17104.54 | N90: =IF(M90="","",ROUND(M90*PARÂMETROS!$B$4,2)) | O90: 6 | P90: 17552.27 | Q90: =IF(P90="","",ROUND(P90*PARÂMETROS!$B$4,2)) | R90: 11 | S90: 17104.54 | V90: =IF(T90="","",ROUND(T90*PARÂMETROS!$B$5,2)) | Y90: =IFERROR(ROUND(W90/T90,2),"") | Z90: =IFERROR(ROUND(N90/T90,2),"") | AA90: =IFERROR(ROUND(N90/W90,2),"") | AB90: 2.7 | AC90: 18801.79 | AD90: 17104.54 | AF90: Montagem Poste >> Inclui mão de obra, equipamentos p/ içamento, ferramentas e o que for necessário para correta execução da montagem da EV.
A91: 94 | B91: POSTE | C91: Poste Metálico Autoportante | E91: Poste Metálico Autoportante · 30m · AeV 3m² · 30m/s | F91: VB | H91: 3 | I91: 30 | J91: 3 | K91: 30 | L91: 5 | M91: 70000 | N91: =IF(M91="","",ROUND(M91*PARÂMETROS!$B$4,2)) | O91: 6 | P91: 67633.56 | Q91: =IF(P91="","",ROUND(P91*PARÂMETROS!$B$4,2)) | R91: 11 | S91: 70000 | V91: =IF(T91="","",ROUND(T91*PARÂMETROS!$B$5,2)) | Y91: =IFERROR(ROUND(W91/T91,2),"") | Z91: =IFERROR(ROUND(N91/T91,2),"") | AA91: =IFERROR(ROUND(N91/W91,2),"") | AB91: 1.7 | AC91: 71630.6 | AD91: 70000 | AF91: Poste Metálico Autoportante >> 3
A92: 95 | B92: POSTE | C92: Poste Metálico Autoportante | E92: Poste Metálico Autoportante · 30m · AeV 3m² · 35m/s | F92: VB | H92: 3 | I92: 30 | J92: 3 | K92: 35 | L92: 5 | M92: 72000 | N92: =IF(M92="","",ROUND(M92*PARÂMETROS!$B$4,2)) | O92: 6 | P92: 69301.07 | Q92: =IF(P92="","",ROUND(P92*PARÂMETROS!$B$4,2)) | R92: 11 | S92: 72000 | V92: =IF(T92="","",ROUND(T92*PARÂMETROS!$B$5,2)) | Y92: =IFERROR(ROUND(W92/T92,2),"") | Z92: =IFERROR(ROUND(N92/T92,2),"") | AA92: =IFERROR(ROUND(N92/W92,2),"") | AB92: 1.7 | AC92: 73943.63 | AD92: 72000 | AF92: Poste Metálico Autoportante >> 3
A93: 96 | B93: POSTE | C93: Poste Metálico Autoportante | E93: Poste Metálico Autoportante · 30m · AeV 3m² · 40m/s | F93: VB | H93: 3 | I93: 30 | J93: 3 | K93: 40 | L93: 5 | M93: 84000 | N93: =IF(M93="","",ROUND(M93*PARÂMETROS!$B$4,2)) | O93: 6 | P93: 78189.06 | Q93: =IF(P93="","",ROUND(P93*PARÂMETROS!$B$4,2)) | R93: 11 | S93: 84000 | V93: =IF(T93="","",ROUND(T93*PARÂMETROS!$B$5,2)) | Y93: =IFERROR(ROUND(W93/T93,2),"") | Z93: =IFERROR(ROUND(N93/T93,2),"") | AA93: =IFERROR(ROUND(N93/W93,2),"") | AB93: 2.9 | AC93: 92300.56 | AD93: 84000 | AF93: Poste Metálico Autoportante >> 3
A94: 97 | B94: POSTE | C94: Poste Metálico Autoportante | E94: Poste Metálico Autoportante · 30m · AeV 3m² · 45m/s | F94: VB | H94: 3 | I94: 30 | J94: 3 | K94: 45 | L94: 5 | M94: 88200 | N94: =IF(M94="","",ROUND(M94*PARÂMETROS!$B$4,2)) | O94: 6 | P94: 82945.47 | Q94: =IF(P94="","",ROUND(P94*PARÂMETROS!$B$4,2)) | R94: 11 | S94: 88200 | V94: =IF(T94="","",ROUND(T94*PARÂMETROS!$B$5,2)) | Y94: =IFERROR(ROUND(W94/T94,2),"") | Z94: =IFERROR(ROUND(N94/T94,2),"") | AA94: =IFERROR(ROUND(N94/W94,2),"") | AB94: 2.9 | AC94: 98731.18 | AD94: 88200 | AF94: Poste Metálico Autoportante >> 3
A95: 98 | B95: POSTE | C95: Poste Metálico Autoportante | E95: Poste Metálico Autoportante · 30m · AeV 6m² · 30m/s | F95: VB | H95: 6 | I95: 30 | J95: 6 | K95: 30 | L95: 5 | M95: 73500 | N95: =IF(M95="","",ROUND(M95*PARÂMETROS!$B$4,2)) | O95: 6 | P95: 69383.56 | Q95: =IF(P95="","",ROUND(P95*PARÂMETROS!$B$4,2)) | R95: 11 | S95: 73500 | V95: =IF(T95="","",ROUND(T95*PARÂMETROS!$B$5,2)) | Y95: =IFERROR(ROUND(W95/T95,2),"") | Z95: =IFERROR(ROUND(N95/T95,2),"") | AA95: =IFERROR(ROUND(N95/W95,2),"") | AB95: 1.7 | AC95: 74087.39 | AD95: 73500 | AF95: Poste Metálico Autoportante >> 6
A96: 99 | B96: POSTE | C96: Poste Metálico Autoportante | E96: Poste Metálico Autoportante · 30m · AeV 6m² · 35m/s | F96: VB | H96: 6 | I96: 30 | J96: 6 | K96: 35 | L96: 5 | M96: 75600 | N96: =IF(M96="","",ROUND(M96*PARÂMETROS!$B$4,2)) | O96: 6 | P96: 73989.06 | Q96: =IF(P96="","",ROUND(P96*PARÂMETROS!$B$4,2)) | R96: 11 | S96: 75600 | V96: =IF(T96="","",ROUND(T96*PARÂMETROS!$B$5,2)) | Y96: =IFERROR(ROUND(W96/T96,2),"") | Z96: =IFERROR(ROUND(N96/T96,2),"") | AA96: =IFERROR(ROUND(N96/W96,2),"") | AB96: 1.7 | AC96: 76975.62 | AD96: 75600 | AF96: Poste Metálico Autoportante >> 6
A97: 100 | B97: POSTE | C97: Poste Metálico Autoportante | E97: Poste Metálico Autoportante · 30m · AeV 6m² · 40m/s | F97: VB | H97: 6 | I97: 30 | J97: 6 | K97: 40 | L97: 5 | M97: 88200 | N97: =IF(M97="","",ROUND(M97*PARÂMETROS!$B$4,2)) | O97: 6 | P97: 85383.92 | Q97: =IF(P97="","",ROUND(P97*PARÂMETROS!$B$4,2)) | R97: 11 | S97: 88200 | V97: =IF(T97="","",ROUND(T97*PARÂMETROS!$B$5,2)) | Y97: =IFERROR(ROUND(W97/T97,2),"") | Z97: =IFERROR(ROUND(N97/T97,2),"") | AA97: =IFERROR(ROUND(N97/W97,2),"") | AB97: 2.6 | AC97: 97315.29 | AD97: 88200 | AF97: Poste Metálico Autoportante >> 6
A98: 101 | B98: POSTE | C98: Poste Metálico Autoportante | E98: Poste Metálico Autoportante · 30m · AeV 6m² · 45m/s | F98: VB | H98: 6 | I98: 30 | J98: 6 | K98: 45 | L98: 5 | M98: 92610 | N98: =IF(M98="","",ROUND(M98*PARÂMETROS!$B$4,2)) | O98: 6 | P98: 87588.92 | Q98: =IF(P98="","",ROUND(P98*PARÂMETROS!$B$4,2)) | R98: 11 | S98: 92610 | V98: =IF(T98="","",ROUND(T98*PARÂMETROS!$B$5,2)) | Y98: =IFERROR(ROUND(W98/T98,2),"") | Z98: =IFERROR(ROUND(N98/T98,2),"") | AA98: =IFERROR(ROUND(N98/W98,2),"") | AB98: 2.3 | AC98: 105401.6 | AD98: 92610 | AF98: Poste Metálico Autoportante >> 6
A99: 102 | B99: POSTE | C99: Poste Metálico Autoportante | E99: Poste Metálico Autoportante · 30m · AeV 9m² · 30m/s | F99: VB | H99: 9 | I99: 30 | J99: 9 | K99: 30 | L99: 5 | M99: 77175 | N99: =IF(M99="","",ROUND(M99*PARÂMETROS!$B$4,2)) | O99: 6 | P99: 74776.56 | Q99: =IF(P99="","",ROUND(P99*PARÂMETROS!$B$4,2)) | R99: 11 | S99: 77175 | V99: =IF(T99="","",ROUND(T99*PARÂMETROS!$B$5,2)) | Y99: =IFERROR(ROUND(W99/T99,2),"") | Z99: =IFERROR(ROUND(N99/T99,2),"") | AA99: =IFERROR(ROUND(N99/W99,2),"") | AB99: 1.7 | AC99: 76740.54 | AD99: 77175 | AF99: Poste Metálico Autoportante >> 9
A100: 103 | B100: POSTE | C100: Poste Metálico Autoportante | E100: Poste Metálico Autoportante · 30m · AeV 9m² · 35m/s | F100: VB | H100: 9 | I100: 30 | J100: 9 | K100: 35 | L100: 5 | M100: 79380 | N100: =IF(M100="","",ROUND(M100*PARÂMETROS!$B$4,2)) | O100: 6 | P100: 78535.47 | Q100: =IF(P100="","",ROUND(P100*PARÂMETROS!$B$4,2)) | R100: 11 | S100: 79380 | V100: =IF(T100="","",ROUND(T100*PARÂMETROS!$B$5,2)) | Y100: =IFERROR(ROUND(W100/T100,2),"") | Z100: =IFERROR(ROUND(N100/T100,2),"") | AA100: =IFERROR(ROUND(N100/W100,2),"") | AB100: 1.9 | AC100: 80948.11 | AD100: 79380 | AF100: Poste Metálico Autoportante >> 9
A101: 104 | B101: POSTE | C101: Poste Metálico Autoportante | E101: Poste Metálico Autoportante · 30m · AeV 9m² · 40m/s | F101: VB | H101: 9 | I101: 30 | J101: 9 | K101: 40 | L101: 5 | M101: 92610 | N101: =IF(M101="","",ROUND(M101*PARÂMETROS!$B$4,2)) | O101: 6 | P101: 89795.79 | Q101: =IF(P101="","",ROUND(P101*PARÂMETROS!$B$4,2)) | R101: 11 | S101: 92610 | V101: =IF(T101="","",ROUND(T101*PARÂMETROS!$B$5,2)) | Y101: =IFERROR(ROUND(W101/T101,2),"") | Z101: =IFERROR(ROUND(N101/T101,2),"") | AA101: =IFERROR(ROUND(N101/W101,2),"") | AB101: 2.3 | AC101: 107897.13 | AD101: 92610 | AF101: Poste Metálico Autoportante >> 9
A102: 105 | B102: POSTE | C102: Poste Metálico Autoportante | E102: Poste Metálico Autoportante · 30m · AeV 9m² · 45m/s | F102: VB | H102: 9 | I102: 30 | J102: 9 | K102: 45 | L102: 5 | M102: 97240.5 | N102: =IF(M102="","",ROUND(M102*PARÂMETROS!$B$4,2)) | O102: 6 | P102: 95680.16 | Q102: =IF(P102="","",ROUND(P102*PARÂMETROS!$B$4,2)) | R102: 11 | S102: 97240.5 | V102: =IF(T102="","",ROUND(T102*PARÂMETROS!$B$5,2)) | Y102: =IFERROR(ROUND(W102/T102,2),"") | Z102: =IFERROR(ROUND(N102/T102,2),"") | AA102: =IFERROR(ROUND(N102/W102,2),"") | AB102: 2.4 | AC102: 114675.51 | AD102: 97240.5 | AF102: Poste Metálico Autoportante >> 9
... A106: 109 | B106: POSTE | C106: Poste Metálico Autoportante | E106: Poste Metálico Autoportante · 30m · AeV 12m² · 45m/s | F106: VB | H106: 12 | I106: 30 | J106: 12 | K106: 45 | L106: 5 | M106: 103410.45 | N106: =IF(M106="","",ROUND(M106*PARÂMETROS!$B$4,2)) | O106: 6 | P106: 102756.49 | Q106: =IF(P106="","",ROUND(P106*PARÂMETROS!$B$4,2)) | R106: 11 | S106: 103410.45 | V106: =IF(T106="","",ROUND(T106*PARÂMETROS!$B$5,2)) | Y106: =IFERROR(ROUND(W106/T106,2),"") | Z106: =IFERROR(ROUND(N106/T106,2),"") | AA106: =IFERROR(ROUND(N106/W106,2),"") | AB106: 2.3 | AC106: 123964.29 | AD106: 103410.45 | AF106: Poste Metálico Autoportante >> 12
A107: 110 | B107: POSTE | C107: Poste Metálico Autoportante | E107: Kit de ancoragem Poste 30m | F107: PÇ | I107: 30 | L107: 5 | M107: 4345.31 | N107: =IF(M107="","",ROUND(M107*PARÂMETROS!$B$4,2)) | O107: 6 | P107: 4222.24 | Q107: =IF(P107="","",ROUND(P107*PARÂMETROS!$B$4,2)) | R107: 11 | S107: 4345.31 | V107: =IF(T107="","",ROUND(T107*PARÂMETROS!$B$5,2)) | Y107: =IFERROR(ROUND(W107/T107,2),"") | Z107: =IFERROR(ROUND(N107/T107,2),"") | AA107: =IFERROR(ROUND(N107/W107,2),"") | AB107: 1.9 | AC107: 4567.84 | AD107: 4345.31 | AF107: Poste Metálico Autoportante >> Kit de ancoragem Poste 30m
A108: 111 | B108: TORRE | C108: Torre Metálica Autoportante | E108: Torre Metálica Autoportante · 30m · AeV 3m² · 30m/s | F108: VB | H108: 3 | I108: 30 | J108: 3 | K108: 30 | L108: 6 | M108: 62500.89 | N108: =IF(M108="","",ROUND(M108*PARÂMETROS!$B$4,2)) | O108: 7 | P108: 66686.35 | Q108: =IF(P108="","",ROUND(P108*PARÂMETROS!$B$4,2)) | R108: 13 | S108: 66686.35 | V108: =IF(T108="","",ROUND(T108*PARÂMETROS!$B$5,2)) | Y108: =IFERROR(ROUND(W108/T108,2),"") | Z108: =IFERROR(ROUND(N108/T108,2),"") | AA108: =IFERROR(ROUND(N108/W108,2),"") | AB108: 2.1 | AC108: 61412.8 | AD108: 66686.35 | AF108: Torre Metálica Autoportante >> 3
A109: 112 | B109: TORRE | C109: Torre Metálica Autoportante | E109: Torre Metálica Autoportante · 30m · AeV 3m² · 35m/s | F109: VB | H109: 3 | I109: 30 | J109: 3 | K109: 35 | L109: 6 | M109: 69143.17 | N109: =IF(M109="","",ROUND(M109*PARÂMETROS!$B$4,2)) | O109: 7 | P109: 70331.99 | Q109: =IF(P109="","",ROUND(P109*PARÂMETROS!$B$4,2)) | R109: 13 | S109: 70331.99 | V109: =IF(T109="","",ROUND(T109*PARÂMETROS!$B$5,2)) | Y109: =IFERROR(ROUND(W109/T109,2),"") | Z109: =IFERROR(ROUND(N109/T109,2),"") | AA109: =IFERROR(ROUND(N109/W109,2),"") | AB109: 1.8 | AC109: 65386.6 | AD109: 70331.99 | AF109: Torre Metálica Autoportante >> 3
A110: 113 | B110: TORRE | C110: Torre Metálica Autoportante | E110: Torre Metálica Autoportante · 30m · AeV 3m² · 40m/s | F110: VB | H110: 3 | I110: 30 | J110: 3 | K110: 40 | L110: 6 | M110: 75904.3 | N110: =IF(M110="","",ROUND(M110*PARÂMETROS!$B$4,2)) | O110: 7 | P110: 77320.07 | Q110: =IF(P110="","",ROUND(P110*PARÂMETROS!$B$4,2)) | R110: 13 | S110: 77320.07 | V110: =IF(T110="","",ROUND(T110*PARÂMETROS!$B$5,2)) | Y110: =IFERROR(ROUND(W110/T110,2),"") | Z110: =IFERROR(ROUND(N110/T110,2),"") | AA110: =IFERROR(ROUND(N110/W110,2),"") | AB110: 1.6 | AC110: 70867.47 | AD110: 77320.07 | AF110: Torre Metálica Autoportante >> 3
A111: 114 | B111: TORRE | C111: Torre Metálica Autoportante | E111: Torre Metálica Autoportante · 30m · AeV 3m² · 45m/s | F111: VB | H111: 3 | I111: 30 | J111: 3 | K111: 45 | L111: 6 | M111: 80707.16 | N111: =IF(M111="","",ROUND(M111*PARÂMETROS!$B$4,2)) | O111: 7 | P111: 83341.16 | Q111: =IF(P111="","",ROUND(P111*PARÂMETROS!$B$4,2)) | R111: 13 | S111: 83341.16 | V111: =IF(T111="","",ROUND(T111*PARÂMETROS!$B$5,2)) | Y111: =IFERROR(ROUND(W111/T111,2),"") | Z111: =IFERROR(ROUND(N111/T111,2),"") | AA111: =IFERROR(ROUND(N111/W111,2),"") | AB111: 1.5 | AC111: 75539.4 | AD111: 83341.16 | AF111: Torre Metálica Autoportante >> 3
A112: 115 | B112: TORRE | C112: Torre Metálica Autoportante | E112: Torre Metálica Autoportante · 30m · AeV 6m² · 30m/s | F112: VB | H112: 6 | I112: 30 | J112: 6 | K112: 30 | L112: 6 | M112: 64538.21 | N112: =IF(M112="","",ROUND(M112*PARÂMETROS!$B$4,2)) | O112: 7 | P112: 66686.35 | Q112: =IF(P112="","",ROUND(P112*PARÂMETROS!$B$4,2)) | R112: 13 | S112: 66686.35 | V112: =IF(T112="","",ROUND(T112*PARÂMETROS!$B$5,2)) | Y112: =IFERROR(ROUND(W112/T112,2),"") | Z112: =IFERROR(ROUND(N112/T112,2),"") | AA112: =IFERROR(ROUND(N112/W112,2),"") | AB112: 2.1 | AC112: 63883.77 | AD112: 66686.35 | AF112: Torre Metálica Autoportante >> 6
A113: 116 | B113: TORRE | C113: Torre Metálica Autoportante | E113: Torre Metálica Autoportante · 30m · AeV 6m² · 35m/s | F113: VB | H113: 6 | I113: 30 | J113: 6 | K113: 35 | L113: 6 | M113: 70617.95 | N113: =IF(M113="","",ROUND(M113*PARÂMETROS!$B$4,2)) | O113: 7 | P113: 70903.92 | Q113: =IF(P113="","",ROUND(P113*PARÂMETROS!$B$4,2)) | R113: 13 | S113: 70903.92 | V113: =IF(T113="","",ROUND(T113*PARÂMETROS!$B$5,2)) | Y113: =IFERROR(ROUND(W113/T113,2),"") | Z113: =IFERROR(ROUND(N113/T113,2),"") | AA113: =IFERROR(ROUND(N113/W113,2),"") | AB113: 1.9 | AC113: 68225.04 | AD113: 70903.92 | AF113: Torre Metálica Autoportante >> 6
A114: 117 | B114: TORRE | C114: Torre Metálica Autoportante | E114: Torre Metálica Autoportante · 30m · AeV 6m² · 40m/s | F114: VB | H114: 6 | I114: 30 | J114: 6 | K114: 40 | L114: 6 | M114: 74047.4 | N114: =IF(M114="","",ROUND(M114*PARÂMETROS!$B$4,2)) | O114: 7 | P114: 74488.54 | Q114: =IF(P114="","",ROUND(P114*PARÂMETROS!$B$4,2)) | R114: 13 | S114: 74488.54 | V114: =IF(T114="","",ROUND(T114*PARÂMETROS!$B$5,2)) | Y114: =IFERROR(ROUND(W114/T114,2),"") | Z114: =IFERROR(ROUND(N114/T114,2),"") | AA114: =IFERROR(ROUND(N114/W114,2),"") | AB114: 1.6 | AC114: 71853.79 | AD114: 74488.54 | AF114: Torre Metálica Autoportante >> 6
A115: 118 | B115: TORRE | C115: Torre Metálica Autoportante | E115: Torre Metálica Autoportante · 30m · AeV 6m² · 45m/s | F115: VB | H115: 6 | I115: 30 | J115: 6 | K115: 45 | L115: 6 | M115: 82831.23 | N115: =IF(M115="","",ROUND(M115*PARÂMETROS!$B$4,2)) | O115: 7 | P115: 83341.16 | Q115: =IF(P115="","",ROUND(P115*PARÂMETROS!$B$4,2)) | R115: 13 | S115: 83341.16 | V115: =IF(T115="","",ROUND(T115*PARÂMETROS!$B$5,2)) | Y115: =IFERROR(ROUND(W115/T115,2),"") | Z115: =IFERROR(ROUND(N115/T115,2),"") | AA115: =IFERROR(ROUND(N115/W115,2),"") | AB115: 1.3 | AC115: 78236.15 | AD115: 83341.16 | AF115: Torre Metálica Autoportante >> 6
A116: 119 | B116: TORRE | C116: Torre Metálica Autoportante | E116: Torre Metálica Autoportante · 30m · AeV 9m² · 30m/s | F116: VB | H116: 9 | I116: 30 | J116: 9 | K116: 30 | L116: 6 | M116: 69737.98 | N116: =IF(M116="","",ROUND(M116*PARÂMETROS!$B$4,2)) | O116: 7 | P116: 68572.04 | Q116: =IF(P116="","",ROUND(P116*PARÂMETROS!$B$4,2)) | R116: 13 | S116: 68572.04 | V116: =IF(T116="","",ROUND(T116*PARÂMETROS!$B$5,2)) | Y116: =IFERROR(ROUND(W116/T116,2),"") | Z116: =IFERROR(ROUND(N116/T116,2),"") | AA116: =IFERROR(ROUND(N116/W116,2),"") | AB116: 2.2 | AC116: 67598.16 | AD116: 68572.04 | AF116: Torre Metálica Autoportante >> 9
A117: 120 | B117: TORRE | C117: Torre Metálica Autoportante | E117: Torre Metálica Autoportante · 30m · AeV 9m² · 35m/s | F117: VB | H117: 9 | I117: 30 | J117: 9 | K117: 35 | L117: 6 | M117: 75830.17 | N117: =IF(M117="","",ROUND(M117*PARÂMETROS!$B$4,2)) | O117: 7 | P117: 75707.32 | Q117: =IF(P117="","",ROUND(P117*PARÂMETROS!$B$4,2)) | R117: 13 | S117: 75707.32 | V117: =IF(T117="","",ROUND(T117*PARÂMETROS!$B$5,2)) | Y117: =IFERROR(ROUND(W117/T117,2),"") | Z117: =IFERROR(ROUND(N117/T117,2),"") | AA117: =IFERROR(ROUND(N117/W117,2),"") | AB117: 1.9 | AC117: 72726.1 | AD117: 75707.32 | AF117: Torre Metálica Autoportante >> 9
A118: 121 | B118: TORRE | C118: Torre Metálica Autoportante | E118: Torre Metálica Autoportante · 30m · AeV 9m² · 40m/s | F118: VB | H118: 9 | I118: 30 | J118: 9 | K118: 40 | L118: 6 | M118: 79981.89 | N118: =IF(M118="","",ROUND(M118*PARÂMETROS!$B$4,2)) | O118: 7 | P118: 80213.1 | Q118: =IF(P118="","",ROUND(P118*PARÂMETROS!$B$4,2)) | R118: 13 | S118: 80213.1 | V118: =IF(T118="","",ROUND(T118*PARÂMETROS!$B$5,2)) | Y118: =IFERROR(ROUND(W118/T118,2),"") | Z118: =IFERROR(ROUND(N118/T118,2),"") | AA118: =IFERROR(ROUND(N118/W118,2),"") | AB118: 1.7 | AC118: 77971.6 | AD118: 80213.1 | AF118: Torre Metálica Autoportante >> 9
A119: 122 | B119: TORRE | C119: Torre Metálica Autoportante | E119: Torre Metálica Autoportante · 30m · AeV 9m² · 45m/s | F119: VB | H119: 9 | I119: 30 | J119: 9 | K119: 45 | L119: 6 | M119: 86577.05 | N119: =IF(M119="","",ROUND(M119*PARÂMETROS!$B$4,2)) | O119: 7 | P119: 86300 | Q119: =IF(P119="","",ROUND(P119*PARÂMETROS!$B$4,2)) | R119: 13 | S119: 86300 | V119: =IF(T119="","",ROUND(T119*PARÂMETROS!$B$5,2)) | Y119: =IFERROR(ROUND(W119/T119,2),"") | Z119: =IFERROR(ROUND(N119/T119,2),"") | AA119: =IFERROR(ROUND(N119/W119,2),"") | AB119: 1.6 | AC119: 86359.26 | AD119: 86300 | AF119: Torre Metálica Autoportante >> 9
...

Sheet ABERTURA DE MERCADO
A1: Linha LPU | B1: Família | C1: Grupo | D1: Subgrupo | E1: Item | F1: Un. | G1: Região | H1: Fornecedor | I1: Valor unitário cotado (R$) | J1: Entra na mediana N+NE?
A2: 5 | B2: MASTRO | C2: Mastro | E2: Mastro · 2m · AeV 2m² · 45m/s | F2: VB | G2: NORTE | H2: METALALFA (NEGOCIADO) | I2: 1055.67 | J2: SIM
A3: 5 | B3: MASTRO | C3: Mastro | E3: Mastro · 2m · AeV 2m² · 45m/s | F3: VB | G3: NORTE | H3: BRASILSAT | I3: 3763.92 | J3: SIM
A4: 5 | B4: MASTRO | C4: Mastro | E4: Mastro · 2m · AeV 2m² · 45m/s | F4: VB | G4: NORTE | H4: CLEMAR (NEGOCIADO) | I4: 3840 | J4: SIM
A5: 5 | B5: MASTRO | C5: Mastro | E5: Mastro · 2m · AeV 2m² · 45m/s | F5: VB | G5: NORTE | H5: ZOPONE (NEGOCIADO) | I5: 6620.64 | J5: SIM
A6: 5 | B6: MASTRO | C6: Mastro | E6: Mastro · 2m · AeV 2m² · 45m/s | F6: VB | G6: NORDESTE | H6: METALALFA (NEGOCIADO) | I6: 1055.67 | J6: SIM
A7: 5 | B7: MASTRO | C7: Mastro | E7: Mastro · 2m · AeV 2m² · 45m/s | F7: VB | G7: NORDESTE | H7: CLEMAR (NEGOCIADO) | I7: 3680 | J7: SIM
A8: 5 | B8: MASTRO | C8: Mastro | E8: Mastro · 2m · AeV 2m² · 45m/s | F8: VB | G8: NORDESTE | H8: BRASILSAT | I8: 3763.92 | J8: SIM
A9: 5 | B9: MASTRO | C9: Mastro | E9: Mastro · 2m · AeV 2m² · 45m/s | F9: VB | G9: NORDESTE | H9: ZOPONE (NEGOCIADO) | I9: 5826.16 | J9: SIM
A10: 5 | B10: MASTRO | C10: Mastro | E10: Mastro · 2m · AeV 2m² · 45m/s | F10: VB | G10: C OESTE | H10: METALALFA (NEGOCIADO) | I10: 1055.67 | J10: não
A11: 5 | B11: MASTRO | C11: Mastro | E11: Mastro · 2m · AeV 2m² · 45m/s | F11: VB | G11: C OESTE | H11: CLEMAR (NEGOCIADO) | I11: 3680 | J11: não
A12: 5 | B12: MASTRO | C12: Mastro | E12: Mastro · 2m · AeV 2m² · 45m/s | F12: VB | G12: C OESTE | H12: BRASILSAT | I12: 3680.03 | J12: não
A13: 5 | B13: MASTRO | C13: Mastro | E13: Mastro · 2m · AeV 2m² · 45m/s | F13: VB | G13: C OESTE | H13: ZOPONE (NEGOCIADO) | I13: 6090.98 | J13: não
... A217: 13 | B217: MASTRO | C217: Mastro | E217: Mastro · 8m · AeV 4m² · 45m/s | F217: VB | G217: SUL | H217: CLEMAR (NEGOCIADO) | I217: 29706.6 | J217: não
A218: 14 | B218: POSTE | C218: Poste Concreto/Fibra Simplificado | D218: Suporte RF em plataforma EV > 30m | E218: 3 | F218: VB | G218: NORTE | H218: ZOPONE (NEGOCIADO) | I218: 3375 | J218: SIM
A219: 14 | B219: POSTE | C219: Poste Concreto/Fibra Simplificado | D219: Suporte RF em plataforma EV > 30m | E219: 3 | F219: VB | G219: NORDESTE | H219: ZOPONE (NEGOCIADO) | I219: 3375 | J219: SIM
A220: 14 | B220: POSTE | C220: Poste Concreto/Fibra Simplificado | D220: Suporte RF em plataforma EV > 30m | E220: 3 | F220: VB | G220: C OESTE | H220: ZOPONE (NEGOCIADO) | I220: 3375 | J220: não
A221: 14 | B221: POSTE | C221: Poste Concreto/Fibra Simplificado | D221: Suporte RF em plataforma EV > 30m | E221: 3 | F221: VB | G221: SÃO PAULO | H221: ZOPONE (NEGOCIADO) | I221: 3375 | J221: não
A222: 14 | B222: POSTE | C222: Poste Concreto/Fibra Simplificado | D222: Suporte RF em plataforma EV > 30m | E222: 3 | F222: VB | G222: LESTE | H222: ZOPONE (NEGOCIADO) | I222: 3375 | J222: não
A223: 14 | B223: POSTE | C223: Poste Concreto/Fibra Simplificado | D223: Suporte RF em plataforma EV > 30m | E223: 3 | F223: VB | G223: SUL | H223: ZOPONE (NEGOCIADO) | I223: 3375 | J223: não
A224: 15 | B224: POSTE | C224: Poste Concreto/Fibra Simplificado | D224: Suporte RF em plataforma EV > 30m | E224: 3 | F224: VB | G224: NORTE | H224: ZOPONE (NEGOCIADO) | I224: 3543.75 | J224: SIM
A225: 15 | B225: POSTE | C225: Poste Concreto/Fibra Simplificado | D225: Suporte RF em plataforma EV > 30m | E225: 3 | F225: VB | G225: NORDESTE | H225: ZOPONE (NEGOCIADO) | I225: 3543.75 | J225: SIM
A226: 15 | B226: POSTE | C226: Poste Concreto/Fibra Simplificado | D226: Suporte RF em plataforma EV > 30m | E226: 3 | F226: VB | G226: C OESTE | H226: ZOPONE (NEGOCIADO) | I226: 3543.75 | J226: não
A227: 15 | B227: POSTE | C227: Poste Concreto/Fibra Simplificado | D227: Suporte RF em plataforma EV > 30m | E227: 3 | F227: VB | G227: SÃO PAULO | H227: ZOPONE (NEGOCIADO) | I227: 3543.75 | J227: não
A228: 15 | B228: POSTE | C228: Poste Concreto/Fibra Simplificado | D228: Suporte RF em plataforma EV > 30m | E228: 3 | F228: VB | G228: LESTE | H228: ZOPONE (NEGOCIADO) | I228: 3543.75 | J228: não
A229: 15 | B229: POSTE | C229: Poste Concreto/Fibra Simplificado | D229: Suporte RF em plataforma EV > 30m | E229: 3 | F229: VB | G229: SUL | H229: ZOPONE (NEGOCIADO) | I229: 3543.75 | J229: não
... A241: 17 | B241: POSTE | C241: Poste Concreto/Fibra Simplificado | D241: SPDA | E241: 3 | F241: VB | G241: SUL | H241: ZOPONE (NEGOCIADO) | I241: 3906.98 | J241: não
A242: 18 | B242: POSTE | C242: Poste Concreto/Fibra Simplificado | E242: Poste Concreto/Fibra Simplificado · 9m · AeV 4m² · 30m/s | F242: VB | G242: NORTE | H242: ZOPONE (NEGOCIADO) | I242: 3881.25 | J242: SIM
A243: 18 | B243: POSTE | C243: Poste Concreto/Fibra Simplificado | E243: Poste Concreto/Fibra Simplificado · 9m · AeV 4m² · 30m/s | F243: VB | G243: NORDESTE | H243: ZOPONE (NEGOCIADO) | I243: 3881.25 | J243: SIM
A244: 18 | B244: POSTE | C244: Poste Concreto/Fibra Simplificado | E244: Poste Concreto/Fibra Simplificado · 9m · AeV 4m² · 30m/s | F244: VB | G244: C OESTE | H244: ZOPONE (NEGOCIADO) | I244: 3881.25 | J244: não
A245: 18 | B245: POSTE | C245: Poste Concreto/Fibra Simplificado | E245: Poste Concreto/Fibra Simplificado · 9m · AeV 4m² · 30m/s | F245: VB | G245: SÃO PAULO | H245: ZOPONE (NEGOCIADO) | I245: 3881.25 | J245: não
A246: 18 | B246: POSTE | C246: Poste Concreto/Fibra Simplificado | E246: Poste Concreto/Fibra Simplificado · 9m · AeV 4m² · 30m/s | F246: VB | G246: LESTE | H246: ZOPONE (NEGOCIADO) | I246: 3881.25 | J246: não
A247: 18 | B247: POSTE | C247: Poste Concreto/Fibra Simplificado | E247: Poste Concreto/Fibra Simplificado · 9m · AeV 4m² · 30m/s | F247: VB | G247: SUL | H247: ZOPONE (NEGOCIADO) | I247: 3881.25 | J247: não
A248: 19 | B248: POSTE | C248: Poste Concreto/Fibra Simplificado | D248: Escada EV > 30m | E248: 4 | F248: VB | G248: NORTE | H248: ZOPONE (NEGOCIADO) | I248: 4075.31 | J248: SIM
A249: 19 | B249: POSTE | C249: Poste Concreto/Fibra Simplificado | D249: Escada EV > 30m | E249: 4 | F249: VB | G249: NORDESTE | H249: ZOPONE (NEGOCIADO) | I249: 4075.31 | J249: SIM
A250: 19 | B250: POSTE | C250: Poste Concreto/Fibra Simplificado | D250: Escada EV > 30m | E250: 4 | F250: VB | G250: C OESTE | H250: ZOPONE (NEGOCIADO) | I250: 4075.31 | J250: não
A251: 19 | B251: POSTE | C251: Poste Concreto/Fibra Simplificado | D251: Escada EV > 30m | E251: 4 | F251: VB | G251: SÃO PAULO | H251: ZOPONE (NEGOCIADO) | I251: 4075.31 | J251: não
A252: 19 | B252: POSTE | C252: Poste Concreto/Fibra Simplificado | D252: Escada EV > 30m | E252: 4 | F252: VB | G252: LESTE | H252: ZOPONE (NEGOCIADO) | I252: 4075.31 | J252: não
A253: 19 | B253: POSTE | C253: Poste Concreto/Fibra Simplificado | D253: Escada EV > 30m | E253: 4 | F253: VB | G253: SUL | H253: ZOPONE (NEGOCIADO) | I253: 4075.31 | J253: não
A254: 20 | B254: POSTE | C254: Poste Concreto/Fibra Simplificado | D254: Trava quedas | E254: 4 | F254: VB | G254: NORTE | H254: ZOPONE (NEGOCIADO) | I254: 4279.08 | J254: SIM
A255: 20 | B255: POSTE | C255: Poste Concreto/Fibra Simplificado | D255: Trava quedas | E255: 4 | F255: VB | G255: NORDESTE | H255: ZOPONE (NEGOCIADO) | I255: 4279.08 | J255: SIM
A256: 20 | B256: POSTE | C256: Poste Concreto/Fibra Simplificado | D256: Trava quedas | E256: 4 | F256: VB | G256: C OESTE | H256: ZOPONE (NEGOCIADO) | I256: 4279.08 | J256: não
A257: 20 | B257: POSTE | C257: Poste Concreto/Fibra Simplificado | D257: Trava quedas | E257: 4 | F257: VB | G257: SÃO PAULO | H257: ZOPONE (NEGOCIADO) | I257: 4279.08 | J257: não
A258: 20 | B258: POSTE | C258: Poste Concreto/Fibra Simplificado | D258: Trava quedas | E258: 4 | F258: VB | G258: LESTE | H258: ZOPONE (NEGOCIADO) | I258: 4279.08 | J258: não
A259: 20 | B259: POSTE | C259: Poste Concreto/Fibra Simplificado | D259: Trava quedas | E259: 4 | F259: VB | G259: SUL | H259: ZOPONE (NEGOCIADO) | I259: 4279.08 | J259: não
... A289: 25 | B289: POSTE | C289: Poste Concreto/Fibra Simplificado | D289: Balizamento Baixa Intensidade EV até 45m | E289: 5 | F289: VB | G289: SUL | H289: ZOPONE (NEGOCIADO) | I289: 5166.99 | J289: não
A290: 26 | B290: POSTE | C290: Poste Metálico Simplificado | E290: Poste Metálico Simplificado · 9m · AeV 3m² · 30m/s | F290: VB | G290: NORTE | H290: CLEMAR (NEGOCIADO) | I290: 4927.99 | J290: SIM
A291: 26 | B291: POSTE | C291: Poste Metálico Simplificado | E291: Poste Metálico Simplificado · 9m · AeV 3m² · 30m/s | F291: VB | G291: NORTE | H291: METALALFA (NEGOCIADO) | I291: 7925.44 | J291: SIM
A292: 26 | B292: POSTE | C292: Poste Metálico Simplificado | E292: Poste Metálico Simplificado · 9m · AeV 3m² · 30m/s | F292: VB | G292: NORTE | H292: ZOPONE (NEGOCIADO) | I292: 8018.55 | J292: SIM
A293: 26 | B293: POSTE | C293: Poste Metálico Simplificado | E293: Poste Metálico Simplificado · 9m · AeV 3m² · 30m/s | F293: VB | G293: NORTE | H293: BRASILSAT | I293: 16506.35 | J293: SIM
A294: 26 | B294: POSTE | C294: Poste Metálico Simplificado | E294: Poste Metálico Simplificado · 9m · AeV 3m² · 30m/s | F294: VB | G294: NORTE | H294: CAW (NEGOCIADO) | I294: 23000 | J294: SIM
A295: 26 | B295: POSTE | C295: Poste Metálico Simplificado | E295: Poste Metálico Simplificado · 9m · AeV 3m² · 30m/s | F295: VB | G295: NORDESTE | H295: CLEMAR (NEGOCIADO) | I295: 4927.99 | J295: SIM
A296: 26 | B296: POSTE | C296: Poste Metálico Simplificado | E296: Poste Metálico Simplificado · 9m · AeV 3m² · 30m/s | F296: VB | G296: NORDESTE | H296: METALALFA (NEGOCIADO) | I296: 7925.44 | J296: SIM
A297: 26 | B297: POSTE | C297: Poste Metálico Simplificado | E297: Poste Metálico Simplificado · 9m · AeV 3m² · 30m/s | F297: VB | G297: NORDESTE | H297: ZOPONE (NEGOCIADO) | I297: 8018.55 | J297: SIM
A298: 26 | B298: POSTE | C298: Poste Metálico Simplificado | E298: Poste Metálico Simplificado · 9m · AeV 3m² · 30m/s | F298: VB | G298: NORDESTE | H298: BRASILSAT | I298: 16506.35 | J298: SIM
A299: 26 | B299: POSTE | C299: Poste Metálico Simplificado | E299: Poste Metálico Simplificado · 9m · AeV 3m² · 30m/s | F299: VB | G299: NORDESTE | H299: CAW (NEGOCIADO) | I299: 23000 | J299: SIM
A300: 26 | B300: POSTE | C300: Poste Metálico Simplificado | E300: Poste Metálico Simplificado · 9m · AeV 3m² · 30m/s | F300: VB | G300: C OESTE | H300: CLEMAR (NEGOCIADO) | I300: 4927.99 | J300: não
A301: 26 | B301: POSTE | C301: Poste Metálico Simplificado | E301: Poste Metálico Simplificado · 9m · AeV 3m² · 30m/s | F301: VB | G301: C OESTE | H301: METALALFA (NEGOCIADO) | I301: 7925.44 | J301: não
... A767: 42 | B767: POSTE | C767: Poste Concreto/Fibra Simplificado | E767: Balizamento Média Intensidade EV de 46 até 150m — 3 | F767: VB | G767: SUL | H767: ZOPONE (NEGOCIADO) | I767: 4950 | J767: não
A768: 43 | B768: POSTE | C768: Poste Concreto/Fibra Simplificado | D768: FCI | E768: 3 | F768: VB | G768: NORTE | H768: ZOPONE (NEGOCIADO) | I768: 5197.5 | J768: SIM
A769: 43 | B769: POSTE | C769: Poste Concreto/Fibra Simplificado | D769: FCI | E769: 3 | F769: VB | G769: NORDESTE | H769: ZOPONE (NEGOCIADO) | I769: 5197.5 | J769: SIM
A770: 43 | B770: POSTE | C770: Poste Concreto/Fibra Simplificado | D770: FCI | E770: 3 | F770: VB | G770: C OESTE | H770: ZOPONE (NEGOCIADO) | I770: 5197.5 | J770: não
A771: 43 | B771: POSTE | C771: Poste Concreto/Fibra Simplificado | D771: FCI | E771: 3 | F771: VB | G771: SÃO PAULO | H771: ZOPONE (NEGOCIADO) | I771: 5197.5 | J771: não
A772: 43 | B772: POSTE | C772: Poste Concreto/Fibra Simplificado | D772: FCI | E772: 3 | F772: VB | G772: LESTE | H772: ZOPONE (NEGOCIADO) | I772: 5197.5 | J772: não
A773: 43 | B773: POSTE | C773: Poste Concreto/Fibra Simplificado | D773: FCI | E773: 3 | F773: VB | G773: SUL | H773: ZOPONE (NEGOCIADO) | I773: 5197.5 | J773: não
A774: 44 | B774: POSTE | C774: Poste Concreto/Fibra Simplificado | D774: Projeto | E774: 3 | F774: VB | G774: NORTE | H774: ZOPONE (NEGOCIADO) | I774: 5457.38 | J774: SIM
A775: 44 | B775: POSTE | C775: Poste Concreto/Fibra Simplificado | D775: Projeto | E775: 3 | F775: VB | G775: NORDESTE | H775: ZOPONE (NEGOCIADO) | I775: 5457.38 | J775: SIM
A776: 44 | B776: POSTE | C776: Poste Concreto/Fibra Simplificado | D776: Projeto | E776: 3 | F776: VB | G776: C OESTE | H776: ZOPONE (NEGOCIADO) | I776: 5457.38 | J776: não
A777: 44 | B777: POSTE | C777: Poste Concreto/Fibra Simplificado | D777: Projeto | E777: 3 | F777: VB | G777: SÃO PAULO | H777: ZOPONE (NEGOCIADO) | I777: 5457.38 | J777: não
A778: 44 | B778: POSTE | C778: Poste Concreto/Fibra Simplificado | D778: Projeto | E778: 3 | F778: VB | G778: LESTE | H778: ZOPONE (NEGOCIADO) | I778: 5457.38 | J778: não
A779: 44 | B779: POSTE | C779: Poste Concreto/Fibra Simplificado | D779: Projeto | E779: 3 | F779: VB | G779: SUL | H779: ZOPONE (NEGOCIADO) | I779: 5457.38 | J779: não
... A791: 46 | B791: POSTE | C791: Poste Concreto/Fibra Simplificado | D791: Projeto | E791: 4 | F791: VB | G791: SUL | H791: ZOPONE (NEGOCIADO) | I791: 5692.5 | J791: não
A792: 47 | B792: POSTE | C792: Poste Concreto/Fibra Simplificado | E792: Mastro 1,8m e fundação em solo para instalação de antena TX (parabólica 1,8m), com eletroduto flexível (envelopado em solo), eletroduto FGF e sistema de fixação para encaminhamento de cabos. — 4 | F792: VB | G792: NORTE | H792: ZOPONE (NEGOCIADO) | I792: 5977.13 | J792: SIM
A793: 47 | B793: POSTE | C793: Poste Concreto/Fibra Simplificado | E793: Mastro 1,8m e fundação em solo para instalação de antena TX (parabólica 1,8m), com eletroduto flexível (envelopado em solo), eletroduto FGF e sistema de fixação para encaminhamento de cabos. — 4 | F793: VB | G793: NORDESTE | H793: ZOPONE (NEGOCIADO) | I793: 5977.13 | J793: SIM
A794: 47 | B794: POSTE | C794: Poste Concreto/Fibra Simplificado | E794: Mastro 1,8m e fundação em solo para instalação de antena TX (parabólica 1,8m), com eletroduto flexível (envelopado em solo), eletroduto FGF e sistema de fixação para encaminhamento de cabos. — 4 | F794: VB | G794: C OESTE | H794: ZOPONE (NEGOCIADO) | I794: 5977.13 | J794: não
A795: 47 | B795: POSTE | C795: Poste Concreto/Fibra Simplificado | E795: Mastro 1,8m e fundação em solo para instalação de antena TX (parabólica 1,8m), com eletroduto flexível (envelopado em solo), eletroduto FGF e sistema de fixação para encaminhamento de cabos. — 4 | F795: VB | G795: SÃO PAULO | H795: ZOPONE (NEGOCIADO) | I795: 5977.13 | J795: não
A796: 47 | B796: POSTE | C796: Poste Concreto/Fibra Simplificado | E796: Mastro 1,8m e fundação em solo para instalação de antena TX (parabólica 1,8m), com eletroduto flexível (envelopado em solo), eletroduto FGF e sistema de fixação para encaminhamento de cabos. — 4 | F796: VB | G796: LESTE | H796: ZOPONE (NEGOCIADO) | I796: 5977.13 | J796: não
A797: 47 | B797: POSTE | C797: Poste Concreto/Fibra Simplificado | E797: Mastro 1,8m e fundação em solo para instalação de antena TX (parabólica 1,8m), com eletroduto flexível (envelopado em solo), eletroduto FGF e sistema de fixação para encaminhamento de cabos. — 4 | F797: VB | G797: SUL | H797: ZOPONE (NEGOCIADO) | I797: 5977.13 | J797: não
A798: 48 | B798: POSTE | C798: Poste Concreto/Fibra Simplificado | E798: Poste Concreto/Fibra Simplificado · 12m · AeV 4m² · 40m/s | F798: VB | G798: NORTE | H798: ZOPONE (NEGOCIADO) | I798: 6275.98 | J798: SIM
A799: 48 | B799: POSTE | C799: Poste Concreto/Fibra Simplificado | E799: Poste Concreto/Fibra Simplificado · 12m · AeV 4m² · 40m/s | F799: VB | G799: NORDESTE | H799: ZOPONE (NEGOCIADO) | I799: 6275.98 | J799: SIM
A800: 48 | B800: POSTE | C800: Poste Concreto/Fibra Simplificado | E800: Poste Concreto/Fibra Simplificado · 12m · AeV 4m² · 40m/s | F800: VB | G800: C OESTE | H800: ZOPONE (NEGOCIADO) | I800: 6275.98 | J800: não
A801: 48 | B801: POSTE | C801: Poste Concreto/Fibra Simplificado | E801: Poste Concreto/Fibra Simplificado · 12m · AeV 4m² · 40m/s | F801: VB | G801: SÃO PAULO | H801: ZOPONE (NEGOCIADO) | I801: 6275.98 | J801: não
A802: 48 | B802: POSTE | C802: Poste Concreto/Fibra Simplificado | E802: Poste Concreto/Fibra Simplificado · 12m · AeV 4m² · 40m/s | F802: VB | G802: LESTE | H802: ZOPONE (NEGOCIADO) | I802: 6275.98 | J802: não
A803: 48 | B803: POSTE | C803: Poste Concreto/Fibra Simplificado | E803: Poste Concreto/Fibra Simplificado · 12m · AeV 4m² · 40m/s | F803: VB | G803: SUL | H803: ZOPONE (NEGOCIADO) | I803: 6275.98 | J803: não
... A4419: 164 | B4419: MONTAGEM | C4419: Montagem Torre | E4419: Montagem Torre | F4419: VB | G4419: SUL | H4419: NOVA CORRENTE | I4419: 31500 | J4419: não
A4420: 165 | B4420: INFRA | C4420: Padrão de Entrada | D4420: 2a. Abordagem FO | E4420: Instalação de Poste de Aço ou Concreto p/ 2a. abordagem fibra óptica | F4420: VB | G4420: NORTE | H4420: CAW (NEGOCIADO) | I4420: 2300 | J4420: SIM
A4421: 165 | B4421: INFRA | C4421: Padrão de Entrada | D4421: 2a. Abordagem FO | E4421: Instalação de Poste de Aço ou Concreto p/ 2a. abordagem fibra óptica | F4421: VB | G4421: NORTE | H4421: BRASILSAT | I4421: 2660.1 | J4421: SIM
A4422: 165 | B4422: INFRA | C4422: Padrão de Entrada | D4422: 2a. Abordagem FO | E4422: Instalação de Poste de Aço ou Concreto p/ 2a. abordagem fibra óptica | F4422: VB | G4422: NORTE | H4422: CAW ESTRUTURA + AGEPLAN OBRA | I4422: 3024 | J4422: SIM
A4423: 165 | B4423: INFRA | C4423: Padrão de Entrada | D4423: 2a. Abordagem FO | E4423: Instalação de Poste de Aço ou Concreto p/ 2a. abordagem fibra óptica | F4423: VB | G4423: NORTE | H4423: INFRASITE + SECCIONAL | I4423: 3800 | J4423: SIM
A4424: 165 | B4424: INFRA | C4424: Padrão de Entrada | D4424: 2a. Abordagem FO | E4424: Instalação de Poste de Aço ou Concreto p/ 2a. abordagem fibra óptica | F4424: VB | G4424: NORTE | H4424: METALALFA (NEGOCIADO) | I4424: 4092 | J4424: SIM
A4425: 165 | B4425: INFRA | C4425: Padrão de Entrada | D4425: 2a. Abordagem FO | E4425: Instalação de Poste de Aço ou Concreto p/ 2a. abordagem fibra óptica | F4425: VB | G4425: NORTE | H4425: CLEMAR (NEGOCIADO) | I4425: 4554 | J4425: SIM
A4426: 165 | B4426: INFRA | C4426: Padrão de Entrada | D4426: 2a. Abordagem FO | E4426: Instalação de Poste de Aço ou Concreto p/ 2a. abordagem fibra óptica | F4426: VB | G4426: NORTE | H4426: ZOPONE (NEGOCIADO) | I4426: 4557.11 | J4426: SIM
A4427: 165 | B4427: INFRA | C4427: Padrão de Entrada | D4427: 2a. Abordagem FO | E4427: Instalação de Poste de Aço ou Concreto p/ 2a. abordagem fibra óptica | F4427: VB | G4427: NORDESTE | H4427: NOVA CORRENTE | I4427: 1500 | J4427: SIM
A4428: 165 | B4428: INFRA | C4428: Padrão de Entrada | D4428: 2a. Abordagem FO | E4428: Instalação de Poste de Aço ou Concreto p/ 2a. abordagem fibra óptica | F4428: VB | G4428: NORDESTE | H4428: CAW (NEGOCIADO) | I4428: 2300 | J4428: SIM
A4429: 165 | B4429: INFRA | C4429: Padrão de Entrada | D4429: 2a. Abordagem FO | E4429: Instalação de Poste de Aço ou Concreto p/ 2a. abordagem fibra óptica | F4429: VB | G4429: NORDESTE | H4429: METALALFA (NEGOCIADO) | I4429: 2557.5 | J4429: SIM
A4430: 165 | B4430: INFRA | C4430: Padrão de Entrada | D4430: 2a. Abordagem FO | E4430: Instalação de Poste de Aço ou Concreto p/ 2a. abordagem fibra óptica | F4430: VB | G4430: NORDESTE | H4430: BRASILSAT | I4430: 2660.1 | J4430: SIM
A4431: 165 | B4431: INFRA | C4431: Padrão de Entrada | D4431: 2a. Abordagem FO | E4431: Instalação de Poste de Aço ou Concreto p/ 2a. abordagem fibra óptica | F4431: VB | G4431: NORDESTE | H4431: CAW ESTRUTURA + AGEPLAN OBRA | I4431: 2916 | J4431: SIM
... A4833: 174 | B4833: MASTRO | C4833: Acessórios — Mastro/Poste/Torre | D4833: Balizamento Baixa Intensidade EV até 45m | E4833: Balizamento solar de Baixa Intensidade, portaria COMAR 1424 GC3- -ICA 11-408 de 14/12/2020, inclui suporte, painel, armário com controlador e bateria. | F4833: Kit | G4833: SUL | H4833: ZOPONE (NEGOCIADO) | I4833: 4156.59 | J4833: não
A4834: 175 | B4834: MASTRO | C4834: Acessórios — Mastro/Poste/Torre | E4834: Balizamento Média Intensidade EV de 46 até 150m — Balizamento solar de Média Intensidade, portaria COMAR 1424 GC3- -ICA 11-408 de 14/12/2020, inclui suporte, painel, armário com controlador e bateria. | F4834: Kit | G4834: NORTE | H4834: INFRASITE + SECCIONAL | I4834: 1300 | J4834: SIM
A4835: 175 | B4835: MASTRO | C4835: Acessórios — Mastro/Poste/Torre | E4835: Balizamento Média Intensidade EV de 46 até 150m — Balizamento solar de Média Intensidade, portaria COMAR 1424 GC3- -ICA 11-408 de 14/12/2020, inclui suporte, painel, armário com controlador e bateria. | F4835: Kit | G4835: NORTE | H4835: CAW (NEGOCIADO) | I4835: 2430 | J4835: SIM
...

Sheet LPU ADEQUAÇÃO
K1: C OESTE | Z1: NORDESTE | AU1: N O R T E | BN1: SÃO PAULO | CF1: LESTE (ES, MG E RJ) | CX1: SUL
K2: CLEMAR (NEGOCIADO) | M2: ZOPONE (NEGOCIADO) | O2: METALALFA (NEGOCIADO) | Q2: CAW (NEGOCIADO) | S2: BRASILSAT | U2: INFRASITE + SECCIONAL | W2: CAW ESTRUTURA + AGEPLAN OBRA | Z2: CLEMAR (NEGOCIADO) | AB2: NOVA CORRENTE | AD2: ZOPONE (NEGOCIADO) | AF2: METALALFA (NEGOCIADO) | AH2: CAW (NEGOCIADO) | AJ2: BRASILSAT | AL2: INFRASITE + SECCIONAL | AN2: CAW ESTRUTURA + AGEPLAN OBRA | AU2: VALOR MERCADO | AV2: MÉDIA | AX2: LS OFFICE | AZ2: CLEMAR (NEGOCIADO) | BB2: ZOPONE (NEGOCIADO) | BD2: METALALFA (NEGOCIADO) | BF2: CAW (NEGOCIADO) | BH2: BRASILSAT | BJ2: INFRASITE + SECCIONAL | BL2: CAW ESTRUTURA + AGEPLAN OBRA | BN2: CLEMAR (NEGOCIADO) | BP2: NOVA CORRENTE | BR2: ZOPONE (NEGOCIADO) | BT2: METALALFA (NEGOCIADO) | BV2: CAW (NEGOCIADO) | BX2: BRASILSAT | BZ2: INFRASITE + SECCIONAL | CB2: CAW ESTRUTURA + AGEPLAN OBRA | CF2: CLEMAR (NEGOCIADO) | CH2: NOVA CORRENTE | CJ2: ZOPONE (NEGOCIADO) | CL2: METALALFA (NEGOCIADO) | CN2: CAW (NEGOCIADO) | CP2: BRASILSAT | CR2: INFRASITE + SECCIONAL | CT2: CAW ESTRUTURA + AGEPLAN OBRA | CX2: CLEMAR (NEGOCIADO) | CZ2: NOVA CORRENTE | DB2: ZOPONE (NEGOCIADO) | DD2: METALALFA (NEGOCIADO) | DF2: CAW (NEGOCIADO) | DH2: BRASILSAT | DJ2: INFRASITE + SECCIONAL | DL2: CAW ESTRUTURA + AGEPLAN OBRA
B4: RESUMO | C4: SOLUÇÃO | D4: SIMPLES | E4: MACRO | F4: Altura (m) | G4: AeV c/ CA Nominal EV (m²) | H4: S1xV0 (m/s) | I4: Unid. | J4: QTDE | K4: Unitário | L4: Total | M4: Unitário2 | N4: Total3 | O4: Unitário4 | P4: Total5 | Q4: Unitário6 | R4: Total7 | S4: Unitário8 | T4: Total9 | U4: Unitário10 | V4: Total11 | W4: Unitário12 | X4: Total13 | Y4: 0 | Z4: Unitário14 | AA4: Total15 | AB4: Unitário16 | AC4: Total17 | AD4: Unitário18 | AE4: Total19 | AF4: Unitário20 | AG4: Total21 | AH4: Unitário22 | AI4: Total23 | AJ4: Unitário24 | AK4: Total25 | AL4: Unitário26 | AM4: Total27 | AN4: Unitário28 | AO4: Total29 | AP4: 1 | AQ4: 2 | AR4: 3 | AS4: 4 | AT4: 5 | AU4: VALOR MERCADO | AV4: VL UNIT MÉDIA | AW4: TOTAL MÉDIA | AX4: VL UNITÁRIO LS | AY4: TOTAL LS | AZ4: VL UNITÁRIO CLEMAR | BA4: TOTAL CLEMAR | BB4: Unitário32 | BC4: Total33 | BD4: Unitário34 | BE4: Total35 | BF4: Unitário36 | BG4: Total37 | BH4: Unitário38 | BI4: Total39 | BJ4: Unitário40 | BK4: Total41 | BL4: Unitário42 | BM4: Total43 | BN4: Unitário44 | BO4: Total45 | BP4: Unitário46 | BQ4: Total47 | BR4: Unitário48 | BS4: Total49 | BT4: Unitário50 | BU4: Total51 | BV4: Unitário52 | BW4: Total53 | BX4: Unitário54 | BY4: Total55 | BZ4: Unitário56 | CA4: Total57 | CB4: Unitário58 | CC4: Total59 | CD4: Minimo | CF4: Unitário | CG4: Total | CH4: Unitário | CI4: Total | CJ4: Unitário | CK4: Total | CL4: Unitário | CM4: Total | CN4: Unitário | CO4: Total | CP4: Unitário | CQ4: Total | CR4: Unitário | CS4: Total | CT4: Unitário | CU4: Total | CV4: Minimo | CX4: Unitário | CY4: Total | CZ4: Unitário | DA4: Total | DB4: Unitário | DC4: Total | DD4: Unitário | DE4: Total | DF4: Unitário | DG4: Total | DH4: Unitário | DI4: Total | DJ4: Unitário | DK4: Total | DL4: Unitário | DM4: Total | DN4: Minimo | DO4: Minimo
B5: MASTRO | C5: Mastros Mastros com altura superior 2m deverão ser providos de pedaleira e cabo trava-quedas. | D5: - | E5: 2 | F5: 2 | G5: 2 | H5: 45 | I5: VB | K5: 3680 | L5: =IF(ISTEXT(K5),K5,$J5*K5) | M5: 6090.98 | N5: =IF(ISTEXT(M5),M5,$J5*M5) | O5: 1055.6704 | P5: =IF(ISTEXT(O5),O5,$J5*O5) | Q5: n/a | R5: =IF(ISTEXT(Q5),Q5,$J5*Q5) | S5: 3680.0304 | T5: =IF(ISTEXT(S5),S5,$J5*S5) | U5: N/A | V5: =IF(ISTEXT(U5),U5,$J5*U5) | W5: N/A | X5: =IF(ISTEXT(W5),W5,$J5*W5) | Z5: 3680 | AA5: =IF(ISTEXT(Z5),Z5,$J5*Z5) | AB5: NA | AC5: =IF(ISTEXT(AB5),AB5,$J5*AB5) | AD5: 5826.16 | AE5: =IF(ISTEXT(AD5),AD5,$J5*AD5) | AF5: 1055.6704 | AG5: =IF(ISTEXT(AF5),AF5,$J5*AF5) | AH5: n/a | AI5: =IF(ISTEXT(AH5),AH5,$J5*AH5) | AJ5: 3763.9222 | AK5: =IF(ISTEXT(AJ5),AJ5,$J5*AJ5) | AL5: N/A | AM5: =IF(ISTEXT(AL5),AL5,$J5*AL5) | AN5: N/A | AO5: =IF(ISTEXT(AN5),AN5,$J5*AN5) | AU5: 3801.96 | AV5: =AVERAGE(AZ5,BB5,BD5,BF5,BH5,BJ5,BL5) | AW5: =BASEDADOS[[#This Row],[VL UNIT MÉDIA]]*BASEDADOS[[#This Row],[QTDE]] | AX5: =ROUND(AU5*PARÂMETROS!$B$4,2) | AZ5: 3840 | BA5: =IF(ISTEXT(AZ5),AZ5,$J5*AZ5) | BB5: 6620.64 | BC5: =IF(ISTEXT(BB5),BB5,$J5*BB5) | BD5: 1055.6704 | BE5: =IF(ISTEXT(BD5),BD5,$J5*BD5) | BF5: n/a | BG5: =IF(ISTEXT(BF5),BF5,$J5*BF5) | BH5: 3763.9222 | BI5: =IF(ISTEXT(BH5),BH5,$J5*BH5) | BJ5: N/A | BK5: =IF(ISTEXT(BJ5),BJ5,$J5*BJ5) | BL5: N/A | BM5: =IF(ISTEXT(BL5),BL5,$J5*BL5) | BN5: 3520 | BO5: =IF(ISTEXT(BN5),BN5,$J5*BN5) | BP5: NA | BQ5: =IF(ISTEXT(BP5),BP5,$J5*BP5) | BR5: 5296.51 | BS5: =IF(ISTEXT(BR5),BR5,$J5*BR5) | BT5: 1055.6704 | BU5: =IF(ISTEXT(BT5),BT5,$J5*BT5) | BV5: n/a | BW5: =IF(ISTEXT(BV5),BV5,$J5*BV5) | BX5: 3763.9222 | BY5: =IF(ISTEXT(BX5),BX5,$J5*BX5) | BZ5: N/A | CA5: =IF(ISTEXT(BZ5),BZ5,$J5*BZ5) | CB5: N/A | CC5: =IF(ISTEXT(CB5),CB5,$J5*CB5) | CD5: =IF($J5="",0,IF($J5=1,_xlfn.MINIFS(BN5:CC5,BN5:CC5,">"&0),_xlfn.MINIFS(BN5:CC5,BN5:CC5,">"&0,BN5:CC5,"<>"&BN5,BN5:CC5,"<>"&BP5,BN5:CC5,"<>"&BR5,BN5:CC5,"<>"&BT5,BN5:CC5,"<>"&BV5,BN5:CC5,"<>"&BX5,BN5:CC5,"<>"&BZ5,BN5:CC5,"<>"&CB5,BN5:CC5,"<>"&#REF!,BN5:CC5,"<>"&#REF!,BN5:CC5,"<>"&#REF!,BN5:CC5,"<>"&#REF!,BN5:CC5,"<>"&#REF!,BN5:CC5,"<>"&#REF!,BN5:CC5,"<>"&#REF!,BN5:CC5,"<>"&#REF!,BN5:CC5,"<>"&#REF!,BN5:CC5,"<>"&#REF!,BN5:CC5,"<>"&#REF!,BN5:CC5,"<>"&#REF!,BN5:CC5,"<>"&#REF!,BN5:CC5,"<>"&#REF!,BN5:CC5,"<>"&#REF!,BN5:CC5,"<>"&#REF!,BN5:CC5,"<>"&#REF!,BN5:CC5,"<>"&#REF!,BN5:CC5,"<>"&#REF!,BN5:CC5,"<>"&#REF!,BN5:CC5,"<>"&#REF!,BN5:CC5,"<>"&#REF!))) | CF5: 3360 | CG5: =IF(ISTEXT(CF5),CF5,$J5*CF5) | CH5: NA | CI5: =IF(ISTEXT(CH5),CH5,$J5*CH5) | CJ5: 5296.51 | CK5: =IF(ISTEXT(CJ5),CJ5,$J5*CJ5) | CL5: 1055.6704 | CM5: =IF(ISTEXT(CL5),CL5,$J5*CL5) | CN5: n/a | CO5: =IF(ISTEXT(CN5),CN5,$J5*CN5) | CP5: 3763.9222 | CQ5: =IF(ISTEXT(CP5),CP5,$J5*CP5) | CR5: N/A | CS5: =IF(ISTEXT(CR5),CR5,$J5*CR5) | CT5: N/A | CU5: =IF(ISTEXT(CT5),CT5,$J5*CT5) | CV5: =IF($J5="",0,IF($J5=1,_xlfn.MINIFS(CF5:CU5,CF5:CU5,">"&0),_xlfn.MINIFS(CF5:CU5,CF5:CU5,">"&0,CF5:CU5,"<>"&CF5,CF5:CU5,"<>"&CH5,CF5:CU5,"<>"&CJ5,CF5:CU5,"<>"&CL5,CF5:CU5,"<>"&CN5,CF5:CU5,"<>"&CP5,CF5:CU5,"<>"&CR5,CF5:CU5,"<>"&CT5,CF5:CU5,"<>"&#REF!,CF5:CU5,"<>"&#REF!,CF5:CU5,"<>"&#REF!,CF5:CU5,"<>"&#REF!,CF5:CU5,"<>"&#REF!,CF5:CU5,"<>"&#REF!,CF5:CU5,"<>"&#REF!,CF5:CU5,"<>"&#REF!,CF5:CU5,"<>"&#REF!,CF5:CU5,"<>"&#REF!,CF5:CU5,"<>"&#REF!,CF5:CU5,"<>"&#REF!,CF5:CU5,"<>"&#REF!,CF5:CU5,"<>"&#REF!,CF5:CU5,"<>"&#REF!,CF5:CU5,"<>"&#REF!,CF5:CU5,"<>"&#REF!,CF5:CU5,"<>"&#REF!,CF5:CU5,"<>"&#REF!,CF5:CU5,"<>"&#REF!,CF5:CU5,"<>"&#REF!,CF5:CU5,"<>"&#REF!))) | CX5: 3200 | CY5: =IF(ISTEXT(CX5),CX5,$J5*CX5) | CZ5: NA | DA5: =IF(ISTEXT(CZ5),CZ5,$J5*CZ5) | DB5: 5296.51 | DC5: =IF(ISTEXT(DB5),DB5,$J5*DB5) | DD5: 1055.6704 | DE5: =IF(ISTEXT(DD5),DD5,$J5*DD5) | DF5: n/a | DG5: =IF(ISTEXT(DF5),DF5,$J5*DF5) | DH5: 3763.9222 | DI5: =IF(ISTEXT(DH5),DH5,$J5*DH5) | DJ5: N/A | DK5: =IF(ISTEXT(DJ5),DJ5,$J5*DJ5) | DL5: N/A | DM5: =IF(ISTEXT(DL5),DL5,$J5*DL5) | DN5: =IF($J5="",0,IF($J5=1,_xlfn.MINIFS(CX5:DM5,CX5:DM5,">"&0),_xlfn.MINIFS(CX5:DM5,CX5:DM5,">"&0,CX5:DM5,"<>"&CX5,CX5:DM5,"<>"&CZ5,CX5:DM5,"<>"&DB5,CX5:DM5,"<>"&DD5,CX5:DM5,"<>"&DF5,CX5:DM5,"<>"&DH5,CX5:DM5,"<>"&DJ5,CX5:DM5,"<>"&DL5,CX5:DM5,"<>"&#REF!,CX5:DM5,"<>"&#REF!,CX5:DM5,"<>"&#REF!,CX5:DM5,"<>"&#REF!,CX5:DM5,"<>"&#REF!,CX5:DM5,"<>"&#REF!,CX5:DM5,"<>"&#REF!,CX5:DM5,"<>"&#REF!,CX5:DM5,"<>"&#REF!,CX5:DM5,"<>"&#REF!,CX5:DM5,"<>"&#REF!,CX5:DM5,"<>"&#REF!,CX5:DM5,"<>"&#REF!,CX5:DM5,"<>"&#REF!,CX5:DM5,"<>"&#REF!,CX5:DM5,"<>"&#REF!,CX5:DM5,"<>"&#REF!,CX5:DM5,"<>"&#REF!,CX5:DM5,"<>"&#REF!,CX5:DM5,"<>"&#REF!,CX5:DM5,"<>"&#REF!,CX5:DM5,"<>"&#REF!))) | DO5: =IF($J5="",0,IF($J5=1,_xlfn.MINIFS(#REF!,#REF!,">"&0),_xlfn.MINIFS(#REF!,#REF!,">"&0,#REF!,"<>"&#REF!,#REF!,"<>"&#REF!,#REF!,"<>"&#REF!,#REF!,"<>"&#REF!,#REF!,"<>"&#REF!,#REF!,"<>"&#REF!,#REF!,"<>"&#REF!,#REF!,"<>"&#REF!,#REF!,"<>"&#REF!,#REF!,"<>"&#REF!,#REF!,"<>"&#REF!,#REF!,"<>"&#REF!,#REF!,"<>"&#REF!,#REF!,"<>"&#REF!,#REF!,"<>"&#REF!,#REF!,"<>"&#REF!,#REF!,"<>"&#REF!,#REF!,"<>"&#REF!,#REF!,"<>"&#REF!,#REF!,"<>"&#REF!,#REF!,"<>"&#REF!,#REF!,"<>"&#REF!,#REF!,"<>"&#REF!,#REF!,"<>"&#REF!,#REF!,"<>"&#REF!,#REF!,"<>"&#REF!,#REF!,"<>"&#REF!,#REF!,"<>"&#REF!,#REF!,"<>"&#REF!,#REF!,"<>"&#REF!)))
B6: MASTRO | C6: Mastros Mastros com altura superior 2m deverão ser providos de pedaleira e cabo trava-quedas. | D6: - | E6: 2 | F6: 3 | G6: 2 | H6: 45 | I6: VB | K6: 7507.2 | L6: =IF(ISTEXT(K6),K6,$J6*K6) | M6: 12186.17 | N6: =IF(ISTEXT(M6),M6,$J6*M6) | O6: 2444.7104 | P6: =IF(ISTEXT(O6),O6,$J6*O6) | Q6: n/a | R6: =IF(ISTEXT(Q6),Q6,$J6*Q6) | S6: 4212.9948 | T6: =IF(ISTEXT(S6),S6,$J6*S6) | U6: N/A | V6: =IF(ISTEXT(U6),U6,$J6*U6) | W6: N/A | X6: =IF(ISTEXT(W6),W6,$J6*W6) | Z6: 7507.2 | AA6: =IF(ISTEXT(Z6),Z6,$J6*Z6) | AB6: NA | AC6: =IF(ISTEXT(AB6),AB6,$J6*AB6) | AD6: 11656.34 | AE6: =IF(ISTEXT(AD6),AD6,$J6*AD6) | AF6: 2444.7104 | AG6: =IF(ISTEXT(AF6),AF6,$J6*AF6) | AH6: n/a | AI6: =IF(ISTEXT(AH6),AH6,$J6*AH6) | AJ6: 4309.0363 | AK6: =IF(ISTEXT(AJ6),AJ6,$J6*AJ6) | AL6: N/A | AM6: =IF(ISTEXT(AL6),AL6,$J6*AL6) | AN6: N/A | AO6: =IF(ISTEXT(AN6),AN6,$J6*AN6) | AU6: 6071.32 | AV6: =AVERAGE(AZ6,BB6,BD6,BF6,BH6,BJ6,BL6) | AW6: =BASEDADOS[[#This Row],[VL UNIT MÉDIA]]*BASEDADOS[[#This Row],[QTDE]] | AX6: =ROUND(AU6*PARÂMETROS!$B$4,2) | AZ6: 7833.6 | BA6: =IF(ISTEXT(AZ6),AZ6,$J6*AZ6) | BB6: 13245.84 | BC6: =IF(ISTEXT(BB6),BB6,$J6*BB6) | BD6: 2444.7104 | BE6: =IF(ISTEXT(BD6),BD6,$J6*BD6) | BF6: n/a | BG6: =IF(ISTEXT(BF6),BF6,$J6*BF6) | BH6: 4309.0363 | BI6: =IF(ISTEXT(BH6),BH6,$J6*BH6) | BJ6: N/A | BK6: =IF(ISTEXT(BJ6),BJ6,$J6*BJ6) | BL6: N/A | BM6: =IF(ISTEXT(BL6),BL6,$J6*BL6) | BN6: 7180.8 | BO6: =IF(ISTEXT(BN6),BN6,$J6*BN6) | BP6: NA | BQ6: =IF(ISTEXT(BP6),BP6,$J6*BP6) | BR6: 10596.67 | BS6: =IF(ISTEXT(BR6),BR6,$J6*BR6) | BT6: 2444.7104 | BU6: =IF(ISTEXT(BT6),BT6,$J6*BT6) | BV6: n/a | BW6: =IF(ISTEXT(BV6),BV6,$J6*BV6) | BX6: 4309.0363 | BY6: =IF(ISTEXT(BX6),BX6,$J6*BX6) | BZ6: N/A | CA6: =IF(ISTEXT(BZ6),BZ6,$J6*BZ6) | CB6: N/A | CC6: =IF(ISTEXT(CB6),CB6,$J6*CB6) | CD6: =IF($J6="",0,IF($J6=1,_xlfn.MINIFS(BN6:CC6,BN6:CC6,">"&0),_xlfn.MINIFS(BN6:CC6,BN6:CC6,">"&0,BN6:CC6,"<>"&BN6,BN6:CC6,"<>"&BP6,BN6:CC6,"<>"&BR6,BN6:CC6,"<>"&BT6,BN6:CC6,"<>"&BV6,BN6:CC6,"<>"&BX6,BN6:CC6,"<>"&BZ6,BN6:CC6,"<>"&CB6,BN6:CC6,"<>"&#REF!,BN6:CC6,"<>"&#REF!,BN6:CC6,"<>"&#REF!,BN6:CC6,"<>"&#REF!,BN6:CC6,"<>"&#REF!,BN6:CC6,"<>"&#REF!,BN6:CC6,"<>"&#REF!,BN6:CC6,"<>"&#REF!,BN6:CC6,"<>"&#REF!,BN6:CC6,"<>"&#REF!,BN6:CC6,"<>"&#REF!,BN6:CC6,"<>"&#REF!,BN6:CC6,"<>"&#REF!,BN6:CC6,"<>"&#REF!,BN6:CC6,"<>"&#REF!,BN6:CC6,"<>"&#REF!,BN6:CC6,"<>"&#REF!,BN6:CC6,"<>"&#REF!,BN6:CC6,"<>"&#REF!,BN6:CC6,"<>"&#REF!,BN6:CC6,"<>"&#REF!,BN6:CC6,"<>"&#REF!))) | CF6: 6854.4 | CG6: =IF(ISTEXT(CF6),CF6,$J6*CF6) | CH6: NA | CI6: =IF(ISTEXT(CH6),CH6,$J6*CH6) | CJ6: 10596.67 | CK6: =IF(ISTEXT(CJ6),CJ6,$J6*CJ6) | CL6: 2444.7104 | CM6: =IF(ISTEXT(CL6),CL6,$J6*CL6) | CN6: n/a | CO6: =IF(ISTEXT(CN6),CN6,$J6*CN6) | CP6: 4309.0363 | CQ6: =IF(ISTEXT(CP6),CP6,$J6*CP6) | CR6: N/A | CS6: =IF(ISTEXT(CR6),CR6,$J6*CR6) | CT6: N/A | CU6: =IF(ISTEXT(CT6),CT6,$J6*CT6) | CV6: =IF($J6="",0,IF($J6=1,_xlfn.MINIFS(CF6:CU6,CF6:CU6,">"&0),_xlfn.MINIFS(CF6:CU6,CF6:CU6,">"&0,CF6:CU6,"<>"&CF6,CF6:CU6,"<>"&CH6,CF6:CU6,"<>"&CJ6,CF6:CU6,"<>"&CL6,CF6:CU6,"<>"&CN6,CF6:CU6,"<>"&CP6,CF6:CU6,"<>"&CR6,CF6:CU6,"<>"&CT6,CF6:CU6,"<>"&#REF!,CF6:CU6,"<>"&#REF!,CF6:CU6,"<>"&#REF!,CF6:CU6,"<>"&#REF!,CF6:CU6,"<>"&#REF!,CF6:CU6,"<>"&#REF!,CF6:CU6,"<>"&#REF!,CF6:CU6,"<>"&#REF!,CF6:CU6,"<>"&#REF!,CF6:CU6,"<>"&#REF!,CF6:CU6,"<>"&#REF!,CF6:CU6,"<>"&#REF!,CF6:CU6,"<>"&#REF!,CF6:CU6,"<>"&#REF!,CF6:CU6,"<>"&#REF!,CF6:CU6,"<>"&#REF!,CF6:CU6,"<>"&#REF!,CF6:CU6,"<>"&#REF!,CF6:CU6,"<>"&#REF!,CF6:CU6,"<>"&#REF!,CF6:CU6,"<>"&#REF!,CF6:CU6,"<>"&#REF!))) | CX6: 6528 | CY6: =IF(ISTEXT(CX6),CX6,$J6*CX6) | CZ6: NA | DA6: =IF(ISTEXT(CZ6),CZ6,$J6*CZ6) | DB6: 10596.67 | DC6: =IF(ISTEXT(DB6),DB6,$J6*DB6) | DD6: 2444.7104 | DE6: =IF(ISTEXT(DD6),DD6,$J6*DD6) | DF6: n/a | DG6: =IF(ISTEXT(DF6),DF6,$J6*DF6) | DH6: 4309.0363 | DI6: =IF(ISTEXT(DH6),DH6,$J6*DH6) | DJ6: N/A | DK6: =IF(ISTEXT(DJ6),DJ6,$J6*DJ6) | DL6: N/A | DM6: =IF(ISTEXT(DL6),DL6,$J6*DL6) | DN6: =IF($J6="",0,IF($J6=1,_xlfn.MINIFS(CX6:DM6,CX6:DM6,">"&0),_xlfn.MINIFS(CX6:DM6,CX6:DM6,">"&0,CX6:DM6,"<>"&CX6,CX6:DM6,"<>"&CZ6,CX6:DM6,"<>"&DB6,CX6:DM6,"<>"&DD6,CX6:DM6,"<>"&DF6,CX6:DM6,"<>"&DH6,CX6:DM6,"<>"&DJ6,CX6:DM6,"<>"&DL6,CX6:DM6,"<>"&#REF!,CX6:DM6,"<>"&#REF!,CX6:DM6,"<>"&#REF!,CX6:DM6,"<>"&#REF!,CX6:DM6,"<>"&#REF!,CX6:DM6,"<>"&#REF!,CX6:DM6,"<>"&#REF!,CX6:DM6,"<>"&#REF!,CX6:DM6,"<>"&#REF!,CX6:DM6,"<>"&#REF!,CX6:DM6,"<>"&#REF!,CX6:DM6,"<>"&#REF!,CX6:DM6,"<>"&#REF!,CX6:DM6,"<>"&#REF!,CX6:DM6,"<>"&#REF!,CX6:DM6,"<>"&#REF!,CX6:DM6,"<>"&#REF!,CX6:DM6,"<>"&#REF!,CX6:DM6,"<>"&#REF!,CX6:DM6,"<>"&#REF!,CX6:DM6,"<>"&#REF!,CX6:DM6,"<>"&#REF!))) | DO6: =IF($J6="",0,IF($J6=1,_xlfn.MINIFS(#REF!,#REF!,">"&0),_xlfn.MINIFS(#REF!,#REF!,">"&0,#REF!,"<>"&#REF!,#REF!,"<>"&#REF!,#REF!,"<>"&#REF!,#REF!,"<>"&#REF!,#REF!,"<>"&#REF!,#REF!,"<>"&#REF!,#REF!,"<>"&#REF!,#REF!,"<>"&#REF!,#REF!,"<>"&#REF!,#REF!,"<>"&#REF!,#REF!,"<>"&#REF!,#REF!,"<>"&#REF!,#REF!,"<>"&#REF!,#REF!,"<>"&#REF!,#REF!,"<>"&#REF!,#REF!,"<>"&#REF!,#REF!,"<>"&#REF!,#REF!,"<>"&#REF!,#REF!,"<>"&#REF!,#REF!,"<>"&#REF!,#REF!,"<>"&#REF!,#REF!,"<>"&#REF!,#REF!,"<>"&#REF!,#REF!,"<>"&#REF!,#REF!,"<>"&#REF!,#REF!,"<>"&#REF!,#REF!,"<>"&#REF!,#REF!,"<>"&#REF!,#REF!,"<>"&#REF!,#REF!,"<>"&#REF!)))
B7: MASTRO | C7: Mastros Mastros com altura superior 2m deverão ser providos de pedaleira e cabo trava-quedas. | D7: - | E7: 3 | F7: 3 | G7: 3 | H7: 45 | I7: VB | K7: 8096 | L7: =IF(ISTEXT(K7),K7,$J7*K7) | M7: 12795.48 | N7: =IF(ISTEXT(M7),M7,$J7*M7) | O7: 2444.7104 | P7: =IF(ISTEXT(O7),O7,$J7*O7) | Q7: n/a | R7: =IF(ISTEXT(Q7),Q7,$J7*Q7) | S7: 4212.9948 | T7: =IF(ISTEXT(S7),S7,$J7*S7) | U7: N/A | V7: =IF(ISTEXT(U7),U7,$J7*U7) | W7: N/A | X7: =IF(ISTEXT(W7),W7,$J7*W7) | Z7: 8096 | AA7: =IF(ISTEXT(Z7),Z7,$J7*Z7) | AB7: NA | AC7: =IF(ISTEXT(AB7),AB7,$J7*AB7) | AD7: 12239.15 | AE7: =IF(ISTEXT(AD7),AD7,$J7*AD7) | AF7: 2444.7104 | AG7: =IF(ISTEXT(AF7),AF7,$J7*AF7) | AH7: n/a | AI7: =IF(ISTEXT(AH7),AH7,$J7*AH7) | AJ7: 4309.0363 | AK7: =IF(ISTEXT(AJ7),AJ7,$J7*AJ7) | AL7: N/A | AM7: =IF(ISTEXT(AL7),AL7,$J7*AL7) | AN7: N/A | AO7: =IF(ISTEXT(AN7),AN7,$J7*AN7) | AU7: 6378.52 | AV7: =AVERAGE(AZ7,BB7,BD7,BF7,BH7,BJ7,BL7) | AW7: =BASEDADOS[[#This Row],[VL UNIT MÉDIA]]*BASEDADOS[[#This Row],[QTDE]] | AX7: =ROUND(AU7*PARÂMETROS!$B$4,2) | AZ7: 8448 | BA7: =IF(ISTEXT(AZ7),AZ7,$J7*AZ7) | BB7: 13908.13 | BC7: =IF(ISTEXT(BB7),BB7,$J7*BB7) | BD7: 2444.7104 | BE7: =IF(ISTEXT(BD7),BD7,$J7*BD7) | BF7: n/a | BG7: =IF(ISTEXT(BF7),BF7,$J7*BF7) | BH7: 4309.0363 | BI7: =IF(ISTEXT(BH7),BH7,$J7*BH7) | BJ7: N/A | BK7: =IF(ISTEXT(BJ7),BJ7,$J7*BJ7) | BL7: N/A | BM7: =IF(ISTEXT(BL7),BL7,$J7*BL7) | BN7: 7744 | BO7: =IF(ISTEXT(BN7),BN7,$J7*BN7) | BP7: NA | BQ7: =IF(ISTEXT(BP7),BP7,$J7*BP7) | BR7: 11126.5 | BS7: =IF(ISTEXT(BR7),BR7,$J7*BR7) | BT7: 2444.7104 | BU7: =IF(ISTEXT(BT7),BT7,$J7*BT7) | BV7: n/a | BW7: =IF(ISTEXT(BV7),BV7,$J7*BV7) | BX7: 4309.0363 | BY7: =IF(ISTEXT(BX7),BX7,$J7*BX7) | BZ7: N/A | CA7: =IF(ISTEXT(BZ7),BZ7,$J7*BZ7) | CB7: N/A | CC7: =IF(ISTEXT(CB7),CB7,$J7*CB7) | CD7: =IF($J7="",0,IF($J7=1,_xlfn.MINIFS(BN7:CC7,BN7:CC7,">"&0),_xlfn.MINIFS(BN7:CC7,BN7:CC7,">"&0,BN7:CC7,"<>"&BN7,BN7:CC7,"<>"&BP7,BN7:CC7,"<>"&BR7,BN7:CC7,"<>"&BT7,BN7:CC7,"<>"&BV7,BN7:CC7,"<>"&BX7,BN7:CC7,"<>"&BZ7,BN7:CC7,"<>"&CB7,BN7:CC7,"<>"&#REF!,BN7:CC7,"<>"&#REF!,BN7:CC7,"<>"&#REF!,BN7:CC7,"<>"&#REF!,BN7:CC7,"<>"&#REF!,BN7:CC7,"<>"&#REF!,BN7:CC7,"<>"&#REF!,BN7:CC7,"<>"&#REF!,BN7:CC7,"<>"&#REF!,BN7:CC7,"<>"&#REF!,BN7:CC7,"<>"&#REF!,BN7:CC7,"<>"&#REF!,BN7:CC7,"<>"&#REF!,BN7:CC7,"<>"&#REF!,BN7:CC7,"<>"&#REF!,BN7:CC7,"<>"&#REF!,BN7:CC7,"<>"&#REF!,BN7:CC7,"<>"&#REF!,BN7:CC7,"<>"&#REF!,BN7:CC7,"<>"&#REF!,BN7:CC7,"<>"&#REF!,BN7:CC7,"<>"&#REF!))) | CF7: 7392 | CG7: =IF(ISTEXT(CF7),CF7,$J7*CF7) | CH7: NA | CI7: =IF(ISTEXT(CH7),CH7,$J7*CH7) | CJ7: 11126.5 | CK7: =IF(ISTEXT(CJ7),CJ7,$J7*CJ7) | CL7: 2444.7104 | CM7: =IF(ISTEXT(CL7),CL7,$J7*CL7) | CN7: n/a | CO7: =IF(ISTEXT(CN7),CN7,$J7*CN7) | CP7: 4309.0363 | CQ7: =IF(ISTEXT(CP7),CP7,$J7*CP7) | CR7: N/A | CS7: =IF(ISTEXT(CR7),CR7,$J7*CR7) | CT7: N/A | CU7: =IF(ISTEXT(CT7),CT7,$J7*CT7) | CV7: =IF($J7="",0,IF($J7=1,_xlfn.MINIFS(CF7:CU7,CF7:CU7,">"&0),_xlfn.MINIFS(CF7:CU7,CF7:CU7,">"&0,CF7:CU7,"<>"&CF7,CF7:CU7,"<>"&CH7,CF7:CU7,"<>"&CJ7,CF7:CU7,"<>"&CL7,CF7:CU7,"<>"&CN7,CF7:CU7,"<>"&CP7,CF7:CU7,"<>"&CR7,CF7:CU7,"<>"&CT7,CF7:CU7,"<>"&#REF!,CF7:CU7,"<>"&#REF!,CF7:CU7,"<>"&#REF!,CF7:CU7,"<>"&#REF!,CF7:CU7,"<>"&#REF!,CF7:CU7,"<>"&#REF!,CF7:CU7,"<>"&#REF!,CF7:CU7,"<>"&#REF!,CF7:CU7,"<>"&#REF!,CF7:CU7,"<>"&#REF!,CF7:CU7,"<>"&#REF!,CF7:CU7,"<>"&#REF!,CF7:CU7,"<>"&#REF!,CF7:CU7,"<>"&#REF!,CF7:CU7,"<>"&#REF!,CF7:CU7,"<>"&#REF!,CF7:CU7,"<>"&#REF!,CF7:CU7,"<>"&#REF!,CF7:CU7,"<>"&#REF!,CF7:CU7,"<>"&#REF!,CF7:CU7,"<>"&#REF!,CF7:CU7,"<>"&#REF!))) | CX7: 7040 | CY7: =IF(ISTEXT(CX7),CX7,$J7*CX7) | CZ7: NA | DA7: =IF(ISTEXT(CZ7),CZ7,$J7*CZ7) | DB7: 11126.5 | DC7: =IF(ISTEXT(DB7),DB7,$J7*DB7) | DD7: 2444.7104 | DE7: =IF(ISTEXT(DD7),DD7,$J7*DD7) | DF7: n/a | DG7: =IF(ISTEXT(DF7),DF7,$J7*DF7) | DH7: 4309.0363 | DI7: =IF(ISTEXT(DH7),DH7,$J7*DH7) | DJ7: N/A | DK7: =IF(ISTEXT(DJ7),DJ7,$J7*DJ7) | DL7: N/A | DM7: =IF(ISTEXT(DL7),DL7,$J7*DL7) | DN7: =IF($J7="",0,IF($J7=1,_xlfn.MINIFS(CX7:DM7,CX7:DM7,">"&0),_xlfn.MINIFS(CX7:DM7,CX7:DM7,">"&0,CX7:DM7,"<>"&CX7,CX7:DM7,"<>"&CZ7,CX7:DM7,"<>"&DB7,CX7:DM7,"<>"&DD7,CX7:DM7,"<>"&DF7,CX7:DM7,"<>"&DH7,CX7:DM7,"<>"&DJ7,CX7:DM7,"<>"&DL7,CX7:DM7,"<>"&#REF!,CX7:DM7,"<>"&#REF!,CX7:DM7,"<>"&#REF!,CX7:DM7,"<>"&#REF!,CX7:DM7,"<>"&#REF!,CX7:DM7,"<>"&#REF!,CX7:DM7,"<>"&#REF!,CX7:DM7,"<>"&#REF!,CX7:DM7,"<>"&#REF!,CX7:DM7,"<>"&#REF!,CX7:DM7,"<>"&#REF!,CX7:DM7,"<>"&#REF!,CX7:DM7,"<>"&#REF!,CX7:DM7,"<>"&#REF!,CX7:DM7,"<>"&#REF!,CX7:DM7,"<>"&#REF!,CX7:DM7,"<>"&#REF!,CX7:DM7,"<>"&#REF!,CX7:DM7,"<>"&#REF!,CX7:DM7,"<>"&#REF!,CX7:DM7,"<>"&#REF!,CX7:DM7,"<>"&#REF!))) | DO7: =IF($J7="",0,IF($J7=1,_xlfn.MINIFS(#REF!,#REF!,">"&0),_xlfn.MINIFS(#REF!,#REF!,">"&0,#REF!,"<>"&#REF!,#REF!,"<>"&#REF!,#REF!,"<>"&#REF!,#REF!,"<>"&#REF!,#REF!,"<>"&#REF!,#REF!,"<>"&#REF!,#REF!,"<>"&#REF!,#REF!,"<>"&#REF!,#REF!,"<>"&#REF!,#REF!,"<>"&#REF!,#REF!,"<>"&#REF!,#REF!,"<>"&#REF!,#REF!,"<>"&#REF!,#REF!,"<>"&#REF!,#REF!,"<>"&#REF!,#REF!,"<>"&#REF!,#REF!,"<>"&#REF!,#REF!,"<>"&#REF!,#REF!,"<>"&#REF!,#REF!,"<>"&#REF!,#REF!,"<>"&#REF!,#REF!,"<>"&#REF!,#REF!,"<>"&#REF!,#REF!,"<>"&#REF!,#REF!,"<>"&#REF!,#REF!,"<>"&#REF!,#REF!,"<>"&#REF!,#REF!,"<>"&#REF!,#REF!,"<>"&#REF!,#REF!,"<>"&#REF!)))
B8: MASTRO | C8: Mastros Mastros com altura superior 2m deverão ser providos de pedaleira e cabo trava-quedas. | D8: - | E8: 2 | F8: 4 | G8: 2 | H8: 45 | I8: VB | K8: 9200 | L8: =IF(ISTEXT(K8),K8,$J8*K8) | M8: 13915.53 | N8: =IF(ISTEXT(M8),M8,$J8*M8) | O8: 6222.8992 | P8: =IF(ISTEXT(O8),O8,$J8*O8) | Q8: n/a | R8: =IF(ISTEXT(Q8),Q8,$J8*Q8) | S8: 4212.9948 | T8: =IF(ISTEXT(S8),S8,$J8*S8) | U8: N/A | V8: =IF(ISTEXT(U8),U8,$J8*U8) | W8: N/A | X8: =IF(ISTEXT(W8),W8,$J8*W8) | Z8: 9200 | AA8: =IF(ISTEXT(Z8),Z8,$J8*Z8) | AB8: NA | AC8: =IF(ISTEXT(AB8),AB8,$J8*AB8) | AD8: 13310.51 | AE8: =IF(ISTEXT(AD8),AD8,$J8*AD8) | AF8: 6222.8992 | AG8: =IF(ISTEXT(AF8),AF8,$J8*AF8) | AH8: n/a | AI8: =IF(ISTEXT(AH8),AH8,$J8*AH8) | AJ8: 4309.0363 | AK8: =IF(ISTEXT(AJ8),AJ8,$J8*AJ8) | AL8: N/A | AM8: =IF(ISTEXT(AL8),AL8,$J8*AL8) | AN8: N/A | AO8: =IF(ISTEXT(AN8),AN8,$J8*AN8) | AU8: 7911.45 | AV8: =AVERAGE(AZ8,BB8,BD8,BF8,BH8,BJ8,BL8) | AW8: =BASEDADOS[[#This Row],[VL UNIT MÉDIA]]*BASEDADOS[[#This Row],[QTDE]] | AX8: =ROUND(AU8*PARÂMETROS!$B$4,2) | AZ8: 9600 | BA8: =IF(ISTEXT(AZ8),AZ8,$J8*AZ8) | BB8: 15125.58 | BC8: =IF(ISTEXT(BB8),BB8,$J8*BB8) | BD8: 6222.8992 | BE8: =IF(ISTEXT(BD8),BD8,$J8*BD8) | BF8: n/a | BG8: =IF(ISTEXT(BF8),BF8,$J8*BF8) | BH8: 4309.0363 | BI8: =IF(ISTEXT(BH8),BH8,$J8*BH8) | BJ8: N/A | BK8: =IF(ISTEXT(BJ8),BJ8,$J8*BJ8) | BL8: N/A | BM8: =IF(ISTEXT(BL8),BL8,$J8*BL8) | BN8: 8800 | BO8: =IF(ISTEXT(BN8),BN8,$J8*BN8) | BP8: NA | BQ8: =IF(ISTEXT(BP8),BP8,$J8*BP8) | BR8: 12100.46 | BS8: =IF(ISTEXT(BR8),BR8,$J8*BR8) | BT8: 6222.8992 | BU8: =IF(ISTEXT(BT8),BT8,$J8*BT8) | BV8: n/a | BW8: =IF(ISTEXT(BV8),BV8,$J8*BV8) | BX8: 4309.0363 | BY8: =IF(ISTEXT(BX8),BX8,$J8*BX8) | BZ8: N/A | CA8: =IF(ISTEXT(BZ8),BZ8,$J8*BZ8) | CB8: N/A | CC8: =IF(ISTEXT(CB8),CB8,$J8*CB8) | CD8: =IF($J8="",0,IF($J8=1,_xlfn.MINIFS(BN8:CC8,BN8:CC8,">"&0),_xlfn.MINIFS(BN8:CC8,BN8:CC8,">"&0,BN8:CC8,"<>"&BN8,BN8:CC8,"<>"&BP8,BN8:CC8,"<>"&BR8,BN8:CC8,"<>"&BT8,BN8:CC8,"<>"&BV8,BN8:CC8,"<>"&BX8,BN8:CC8,"<>"&BZ8,BN8:CC8,"<>"&CB8,BN8:CC8,"<>"&#REF!,BN8:CC8,"<>"&#REF!,BN8:CC8,"<>"&#REF!,BN8:CC8,"<>"&#REF!,BN8:CC8,"<>"&#REF!,BN8:CC8,"<>"&#REF!,BN8:CC8,"<>"&#REF!,BN8:CC8,"<>"&#REF!,BN8:CC8,"<>"&#REF!,BN8:CC8,"<>"&#REF!,BN8:CC8,"<>"&#REF!,BN8:CC8,"<>"&#REF!,BN8:CC8,"<>"&#REF!,BN8:CC8,"<>"&#REF!,BN8:CC8,"<>"&#REF!,BN8:CC8,"<>"&#REF!,BN8:CC8,"<>"&#REF!,BN8:CC8,"<>"&#REF!,BN8:CC8,"<>"&#REF!,BN8:CC8,"<>"&#REF!,BN8:CC8,"<>"&#REF!,BN8:CC8,"<>"&#REF!))) | CF8: 8400 | CG8: =IF(ISTEXT(CF8),CF8,$J8*CF8) | CH8: NA | CI8: =IF(ISTEXT(CH8),CH8,$J8*CH8) | CJ8: 12100.46 | CK8: =IF(ISTEXT(CJ8),CJ8,$J8*CJ8) | CL8: 6222.8992 | CM8: =IF(ISTEXT(CL8),CL8,$J8*CL8) | CN8: n/a | CO8: =IF(ISTEXT(CN8),CN8,$J8*CN8) | CP8: 4309.0363 | CQ8: =IF(ISTEXT(CP8),CP8,$J8*CP8) | CR8: N/A | CS8: =IF(ISTEXT(CR8),CR8,$J8*CR8) | CT8: N/A | CU8: =IF(ISTEXT(CT8),CT8,$J8*CT8) | CV8: =IF($J8="",0,IF($J8=1,_xlfn.MINIFS(CF8:CU8,CF8:CU8,">"&0),_xlfn.MINIFS(CF8:CU8,CF8:CU8,">"&0,CF8:CU8,"<>"&CF8,CF8:CU8,"<>"&CH8,CF8:CU8,"<>"&CJ8,CF8:CU8,"<>"&CL8,CF8:CU8,"<>"&CN8,CF8:CU8,"<>"&CP8,CF8:CU8,"<>"&CR8,CF8:CU8,"<>"&CT8,CF8:CU8,"<>"&#REF!,CF8:CU8,"<>"&#REF!,CF8:CU8,"<>"&#REF!,CF8:CU8,"<>"&#REF!,CF8:CU8,"<>"&#REF!,CF8:CU8,"<>"&#REF!,CF8:CU8,"<>"&#REF!,CF8:CU8,"<>"&#REF!,CF8:CU8,"<>"&#REF!,CF8:CU8,"<>"&#REF!,CF8:CU8,"<>"&#REF!,CF8:CU8,"<>"&#REF!,CF8:CU8,"<>"&#REF!,CF8:CU8,"<>"&#REF!,CF8:CU8,"<>"&#REF!,CF8:CU8,"<>"&#REF!,CF8:CU8,"<>"&#REF!,CF8:CU8,"<>"&#REF!,CF8:CU8,"<>"&#REF!,CF8:CU8,"<>"&#REF!,CF8:CU8,"<>"&#REF!,CF8:CU8,"<>"&#REF!))) | CX8: 8000 | CY8: =IF(ISTEXT(CX8),CX8,$J8*CX8) | CZ8: NA | DA8: =IF(ISTEXT(CZ8),CZ8,$J8*CZ8) | DB8: 12100.46 | DC8: =IF(ISTEXT(DB8),DB8,$J8*DB8) | DD8: 6222.8992 | DE8: =IF(ISTEXT(DD8),DD8,$J8*DD8) | DF8: n/a | DG8: =IF(ISTEXT(DF8),DF8,$J8*DF8) | DH8: 4309.0363 | DI8: =IF(ISTEXT(DH8),DH8,$J8*DH8) | DJ8: N/A | DK8: =IF(ISTEXT(DJ8),DJ8,$J8*DJ8) | DL8: N/A | DM8: =IF(ISTEXT(DL8),DL8,$J8*DL8) | DN8: =IF($J8="",0,IF($J8=1,_xlfn.MINIFS(CX8:DM8,CX8:DM8,">"&0),_xlfn.MINIFS(CX8:DM8,CX8:DM8,">"&0,CX8:DM8,"<>"&CX8,CX8:DM8,"<>"&CZ8,CX8:DM8,"<>"&DB8,CX8:DM8,"<>"&DD8,CX8:DM8,"<>"&DF8,CX8:DM8,"<>"&DH8,CX8:DM8,"<>"&DJ8,CX8:DM8,"<>"&DL8,CX8:DM8,"<>"&#REF!,CX8:DM8,"<>"&#REF!,CX8:DM8,"<>"&#REF!,CX8:DM8,"<>"&#REF!,CX8:DM8,"<>"&#REF!,CX8:DM8,"<>"&#REF!,CX8:DM8,"<>"&#REF!,CX8:DM8,"<>"&#REF!,CX8:DM8,"<>"&#REF!,CX8:DM8,"<>"&#REF!,CX8:DM8,"<>"&#REF!,CX8:DM8,"<>"&#REF!,CX8:DM8,"<>"&#REF!,CX8:DM8,"<>"&#REF!,CX8:DM8,"<>"&#REF!,CX8:DM8,"<>"&#REF!,CX8:DM8,"<>"&#REF!,CX8:DM8,"<>"&#REF!,CX8:DM8,"<>"&#REF!,CX8:DM8,"<>"&#REF!,CX8:DM8,"<>"&#REF!,CX8:DM8,"<>"&#REF!))) | DO8: =IF($J8="",0,IF($J8=1,_xlfn.MINIFS(#REF!,#REF!,">"&0),_xlfn.MINIFS(#REF!,#REF!,">"&0,#REF!,"<>"&#REF!,#REF!,"<>"&#REF!,#REF!,"<>"&#REF!,#REF!,"<>"&#REF!,#REF!,"<>"&#REF!,#REF!,"<>"&#REF!,#REF!,"<>"&#REF!,#REF!,"<>"&#REF!,#REF!,"<>"&#REF!,#REF!,"<>"&#REF!,#REF!,"<>"&#REF!,#REF!,"<>"&#REF!,#REF!,"<>"&#REF!,#REF!,"<>"&#REF!,#REF!,"<>"&#REF!,#REF!,"<>"&#REF!,#REF!,"<>"&#REF!,#REF!,"<>"&#REF!,#REF!,"<>"&#REF!,#REF!,"<>"&#REF!,#REF!,"<>"&#REF!,#REF!,"<>"&#REF!,#REF!,"<>"&#REF!,#REF!,"<>"&#REF!,#REF!,"<>"&#REF!,#REF!,"<>"&#REF!,#REF!,"<>"&#REF!,#REF!,"<>"&#REF!,#REF!,"<>"&#REF!,#REF!,"<>"&#REF!)))
B9: MASTRO | C9: Mastros Mastros com altura superior 2m deverão ser providos de pedaleira e cabo trava-quedas. | D9: - | E9: 3 | F9: 4 | G9: 3 | H9: 45 | I9: VB | K9: 12585.6 | L9: =IF(ISTEXT(K9),K9,$J9*K9) | M9: 14611.31 | N9: =IF(ISTEXT(M9),M9,$J9*M9) | O9: 6222.8992 | P9: =IF(ISTEXT(O9),O9,$J9*O9) | Q9: n/a | R9: =IF(ISTEXT(Q9),Q9,$J9*Q9) | S9: 4212.9948 | T9: =IF(ISTEXT(S9),S9,$J9*S9) | U9: N/A | V9: =IF(ISTEXT(U9),U9,$J9*U9) | W9: N/A | X9: =IF(ISTEXT(W9),W9,$J9*W9) | Z9: 12585.6 | AA9: =IF(ISTEXT(Z9),Z9,$J9*Z9) | AB9: NA | AC9: =IF(ISTEXT(AB9),AB9,$J9*AB9) | AD9: 13976.04 | AE9: =IF(ISTEXT(AD9),AD9,$J9*AD9) | AF9: 6222.8992 | AG9: =IF(ISTEXT(AF9),AF9,$J9*AF9) | AH9: n/a | AI9: =IF(ISTEXT(AH9),AH9,$J9*AH9) | AJ9: 4309.0363 | AK9: =IF(ISTEXT(AJ9),AJ9,$J9*AJ9) | AL9: N/A | AM9: =IF(ISTEXT(AL9),AL9,$J9*AL9) | AN9: N/A | AO9: =IF(ISTEXT(AN9),AN9,$J9*AN9) | AU9: 9677.85 | AV9: =AVERAGE(AZ9,BB9,BD9,BF9,BH9,BJ9,BL9) | AW9: =BASEDADOS[[#This Row],[VL UNIT MÉDIA]]*BASEDADOS[[#This Row],[QTDE]] | AX9: =ROUND(AU9*PARÂMETROS!$B$4,2) | AZ9: 13132.8 | BA9: =IF(ISTEXT(AZ9),AZ9,$J9*AZ9) | BB9: 15881.86 | BC9: =IF(ISTEXT(BB9),BB9,$J9*BB9) | BD9: 6222.8992 | BE9: =IF(ISTEXT(BD9),BD9,$J9*BD9) | BF9: n/a | BG9: =IF(ISTEXT(BF9),BF9,$J9*BF9) | BH9: 4309.0363 | BI9: =IF(ISTEXT(BH9),BH9,$J9*BH9) | BJ9: N/A | BK9: =IF(ISTEXT(BJ9),BJ9,$J9*BJ9) | BL9: N/A | BM9: =IF(ISTEXT(BL9),BL9,$J9*BL9) | BN9: 12038.4 | BO9: =IF(ISTEXT(BN9),BN9,$J9*BN9) | BP9: NA | BQ9: =IF(ISTEXT(BP9),BP9,$J9*BP9) | BR9: 12705.49 | BS9: =IF(ISTEXT(BR9),BR9,$J9*BR9) | BT9: 6222.8992 | BU9: =IF(ISTEXT(BT9),BT9,$J9*BT9) | BV9: n/a | BW9: =IF(ISTEXT(BV9),BV9,$J9*BV9) | BX9: 4309.0363 | BY9: =IF(ISTEXT(BX9),BX9,$J9*BX9) | BZ9: N/A | CA9: =IF(ISTEXT(BZ9),BZ9,$J9*BZ9) | CB9: N/A | CC9: =IF(ISTEXT(CB9),CB9,$J9*CB9) | CD9: =IF($J9="",0,IF($J9=1,_xlfn.MINIFS(BN9:CC9,BN9:CC9,">"&0),_xlfn.MINIFS(BN9:CC9,BN9:CC9,">"&0,BN9:CC9,"<>"&BN9,BN9:CC9,"<>"&BP9,BN9:CC9,"<>"&BR9,BN9:CC9,"<>"&BT9,BN9:CC9,"<>"&BV9,BN9:CC9,"<>"&BX9,BN9:CC9,"<>"&BZ9,BN9:CC9,"<>"&CB9,BN9:CC9,"<>"&#REF!,BN9:CC9,"<>"&#REF!,BN9:CC9,"<>"&#REF!,BN9:CC9,"<>"&#REF!,BN9:CC9,"<>"&#REF!,BN9:CC9,"<>"&#REF!,BN9:CC9,"<>"&#REF!,BN9:CC9,"<>"&#REF!,BN9:CC9,"<>"&#REF!,BN9:CC9,"<>"&#REF!,BN9:CC9,"<>"&#REF!,BN9:CC9,"<>"&#REF!,BN9:CC9,"<>"&#REF!,BN9:CC9,"<>"&#REF!,BN9:CC9,"<>"&#REF!,BN9:CC9,"<>"&#REF!,BN9:CC9,"<>"&#REF!,BN9:CC9,"<>"&#REF!,BN9:CC9,"<>"&#REF!,BN9:CC9,"<>"&#REF!,BN9:CC9,"<>"&#REF!,BN9:CC9,"<>"&#REF!))) | CF9: 11491.2 | CG9: =IF(ISTEXT(CF9),CF9,$J9*CF9) | CH9: NA | CI9: =IF(ISTEXT(CH9),CH9,$J9*CH9) | CJ9: 12705.49 | CK9: =IF(ISTEXT(CJ9),CJ9,$J9*CJ9) | CL9: 6222.8992 | CM9: =IF(ISTEXT(CL9),CL9,$J9*CL9) | CN9: n/a | CO9: =IF(ISTEXT(CN9),CN9,$J9*CN9) | CP9: 4309.0363 | CQ9: =IF(ISTEXT(CP9),CP9,$J9*CP9) | CR9: N/A | CS9: =IF(ISTEXT(CR9),CR9,$J9*CR9) | CT9: N/A | CU9: =IF(ISTEXT(CT9),CT9,$J9*CT9) | CV9: =IF($J9="",0,IF($J9=1,_xlfn.MINIFS(CF9:CU9,CF9:CU9,">"&0),_xlfn.MINIFS(CF9:CU9,CF9:CU9,">"&0,CF9:CU9,"<>"&CF9,CF9:CU9,"<>"&CH9,CF9:CU9,"<>"&CJ9,CF9:CU9,"<>"&CL9,CF9:CU9,"<>"&CN9,CF9:CU9,"<>"&CP9,CF9:CU9,"<>"&CR9,CF9:CU9,"<>"&CT9,CF9:CU9,"<>"&#REF!,CF9:CU9,"<>"&#REF!,CF9:CU9,"<>"&#REF!,CF9:CU9,"<>"&#REF!,CF9:CU9,"<>"&#REF!,CF9:CU9,"<>"&#REF!,CF9:CU9,"<>"&#REF!,CF9:CU9,"<>"&#REF!,CF9:CU9,"<>"&#REF!,CF9:CU9,"<>"&#REF!,CF9:CU9,"<>"&#REF!,CF9:CU9,"<>"&#REF!,CF9:CU9,"<>"&#REF!,CF9:CU9,"<>"&#REF!,CF9:CU9,"<>"&#REF!,CF9:CU9,"<>"&#REF!,CF9:CU9,"<>"&#REF!,CF9:CU9,"<>"&#REF!,CF9:CU9,"<>"&#REF!,CF9:CU9,"<>"&#REF!,CF9:CU9,"<>"&#REF!,CF9:CU9,"<>"&#REF!))) | CX9: 10944 | CY9: =IF(ISTEXT(CX9),CX9,$J9*CX9) | CZ9: NA | DA9: =IF(ISTEXT(CZ9),CZ9,$J9*CZ9) | DB9: 12705.49 | DC9: =IF(ISTEXT(DB9),DB9,$J9*DB9) | DD9: 6222.8992 | DE9: =IF(ISTEXT(DD9),DD9,$J9*DD9) | DF9: n/a | DG9: =IF(ISTEXT(DF9),DF9,$J9*DF9) | DH9: 4309.0363 | DI9: =IF(ISTEXT(DH9),DH9,$J9*DH9) | DJ9: N/A | DK9: =IF(ISTEXT(DJ9),DJ9,$J9*DJ9) | DL9: N/A | DM9: =IF(ISTEXT(DL9),DL9,$J9*DL9) | DN9: =IF($J9="",0,IF($J9=1,_xlfn.MINIFS(CX9:DM9,CX9:DM9,">"&0),_xlfn.MINIFS(CX9:DM9,CX9:DM9,">"&0,CX9:DM9,"<>"&CX9,CX9:DM9,"<>"&CZ9,CX9:DM9,"<>"&DB9,CX9:DM9,"<>"&DD9,CX9:DM9,"<>"&DF9,CX9:DM9,"<>"&DH9,CX9:DM9,"<>"&DJ9,CX9:DM9,"<>"&DL9,CX9:DM9,"<>"&#REF!,CX9:DM9,"<>"&#REF!,CX9:DM9,"<>"&#REF!,CX9:DM9,"<>"&#REF!,CX9:DM9,"<>"&#REF!,CX9:DM9,"<>"&#REF!,CX9:DM9,"<>"&#REF!,CX9:DM9,"<>"&#REF!,CX9:DM9,"<>"&#REF!,CX9:DM9,"<>"&#REF!,CX9:DM9,"<>"&#REF!,CX9:DM9,"<>"&#REF!,CX9:DM9,"<>"&#REF!,CX9:DM9,"<>"&#REF!,CX9:DM9,"<>"&#REF!,CX9:DM9,"<>"&#REF!,CX9:DM9,"<>"&#REF!,CX9:DM9,"<>"&#REF!,CX9:DM9,"<>"&#REF!,CX9:DM9,"<>"&#REF!,CX9:DM9,"<>"&#REF!,CX9:DM9,"<>"&#REF!))) | DO9: =IF($J9="",0,IF($J9=1,_xlfn.MINIFS(#REF!,#REF!,">"&0),_xlfn.MINIFS(#REF!,#REF!,">"&0,#REF!,"<>"&#REF!,#REF!,"<>"&#REF!,#REF!,"<>"&#REF!,#REF!,"<>"&#REF!,#REF!,"<>"&#REF!,#REF!,"<>"&#REF!,#REF!,"<>"&#REF!,#REF!,"<>"&#REF!,#REF!,"<>"&#REF!,#REF!,"<>"&#REF!,#REF!,"<>"&#REF!,#REF!,"<>"&#REF!,#REF!,"<>"&#REF!,#REF!,"<>"&#REF!,#REF!,"<>"&#REF!,#REF!,"<>"&#REF!,#REF!,"<>"&#REF!,#REF!,"<>"&#REF!,#REF!,"<>"&#REF!,#REF!,"<>"&#REF!,#REF!,"<>"&#REF!,#REF!,"<>"&#REF!,#REF!,"<>"&#REF!,#REF!,"<>"&#REF!,#REF!,"<>"&#REF!,#REF!,"<>"&#REF!,#REF!,"<>"&#REF!,#REF!,"<>"&#REF!,#REF!,"<>"&#REF!,#REF!,"<>"&#REF!)))
B10: MASTRO | C10: Mastros Mastros com altura superior 2m deverão ser providos de pedaleira e cabo trava-quedas. | D10: - | E10: 2 | F10: 6 | G10: 2 | H10: 45 | I10: VB | K10: 16048.724 | L10: =IF(ISTEXT(K10),K10,$J10*K10) | M10: 18556.35 | N10: =IF(ISTEXT(M10),M10,$J10*M10) | O10: 9556.5952 | P10: =IF(ISTEXT(O10),O10,$J10*O10) | Q10: n/a | R10: =IF(ISTEXT(Q10),Q10,$J10*Q10) | S10: 5154.8514 | T10: =IF(ISTEXT(S10),S10,$J10*S10) | U10: N/A | V10: =IF(ISTEXT(U10),U10,$J10*U10) | W10: N/A | X10: =IF(ISTEXT(W10),W10,$J10*W10) | Z10: 16453.995 | AA10: =IF(ISTEXT(Z10),Z10,$J10*Z10) | AB10: NA | AC10: =IF(ISTEXT(AB10),AB10,$J10*AB10) | AD10: 17749.55 | AE10: =IF(ISTEXT(AD10),AD10,$J10*AD10) | AF10: 9556.5952 | AG10: =IF(ISTEXT(AF10),AF10,$J10*AF10) | AH10: n/a | AI10: =IF(ISTEXT(AH10),AH10,$J10*AH10) | AJ10: 5272.364 | AK10: =IF(ISTEXT(AJ10),AJ10,$J10*AJ10) | AL10: N/A | AM10: =IF(ISTEXT(AL10),AL10,$J10*AL10) | AN10: N/A | AO10: =IF(ISTEXT(AN10),AN10,$J10*AN10) | AU10: 12883.71 | AV10: =AVERAGE(AZ10,BB10,BD10,BF10,BH10,BJ10,BL10) | AW10: =BASEDADOS[[#This Row],[VL UNIT MÉDIA]]*BASEDADOS[[#This Row],[QTDE]] | AX10: =ROUND(AU10*PARÂMETROS!$B$4,2) | AZ10: 16210.832 | BA10: =IF(ISTEXT(AZ10),AZ10,$J10*AZ10) | BB10: 20169.95 | BC10: =IF(ISTEXT(BB10),BB10,$J10*BB10) | BD10: 9556.5952 | BE10: =IF(ISTEXT(BD10),BD10,$J10*BD10) | BF10: n/a | BG10: =IF(ISTEXT(BF10),BF10,$J10*BF10) | BH10: 5272.364 | BI10: =IF(ISTEXT(BH10),BH10,$J10*BH10) | BJ10: N/A | BK10: =IF(ISTEXT(BJ10),BJ10,$J10*BJ10) | BL10: N/A | BM10: =IF(ISTEXT(BL10),BL10,$J10*BL10) | BN10: 15723.16 | BO10: =IF(ISTEXT(BN10),BN10,$J10*BN10) | BP10: NA | BQ10: =IF(ISTEXT(BP10),BP10,$J10*BP10) | BR10: 16135.96 | BS10: =IF(ISTEXT(BR10),BR10,$J10*BR10) | BT10: 9556.5952 | BU10: =IF(ISTEXT(BT10),BT10,$J10*BT10) | BV10: n/a | BW10: =IF(ISTEXT(BV10),BV10,$J10*BV10) | BX10: 5272.364 | BY10: =IF(ISTEXT(BX10),BX10,$J10*BX10) | BZ10: N/A | CA10: =IF(ISTEXT(BZ10),BZ10,$J10*BZ10) | CB10: N/A | CC10: =IF(ISTEXT(CB10),CB10,$J10*CB10) | CD10: =IF($J10="",0,IF($J10=1,_xlfn.MINIFS(BN10:CC10,BN10:CC10,">"&0),_xlfn.MINIFS(BN10:CC10,BN10:CC10,">"&0,BN10:CC10,"<>"&BN10,BN10:CC10,"<>"&BP10,BN10:CC10,"<>"&BR10,BN10:CC10,"<>"&BT10,BN10:CC10,"<>"&BV10,BN10:CC10,"<>"&BX10,BN10:CC10,"<>"&BZ10,BN10:CC10,"<>"&CB10,BN10:CC10,"<>"&#REF!,BN10:CC10,"<>"&#REF!,BN10:CC10,"<>"&#REF!,BN10:CC10,"<>"&#REF!,BN10:CC10,"<>"&#REF!,BN10:CC10,"<>"&#REF!,BN10:CC10,"<>"&#REF!,BN10:CC10,"<>"&#REF!,BN10:CC10,"<>"&#REF!,BN10:CC10,"<>"&#REF!,BN10:CC10,"<>"&#REF!,BN10:CC10,"<>"&#REF!,BN10:CC10,"<>"&#REF!,BN10:CC10,"<>"&#REF!,BN10:CC10,"<>"&#REF!,BN10:CC10,"<>"&#REF!,BN10:CC10,"<>"&#REF!,BN10:CC10,"<>"&#REF!,BN10:CC10,"<>"&#REF!,BN10:CC10,"<>"&#REF!,BN10:CC10,"<>"&#REF!,BN10:CC10,"<>"&#REF!))) | CF10: 15008.471 | CG10: =IF(ISTEXT(CF10),CF10,$J10*CF10) | CH10: NA | CI10: =IF(ISTEXT(CH10),CH10,$J10*CH10) | CJ10: 16135.96 | CK10: =IF(ISTEXT(CJ10),CJ10,$J10*CJ10) | CL10: 9556.5952 | CM10: =IF(ISTEXT(CL10),CL10,$J10*CL10) | CN10: n/a | CO10: =IF(ISTEXT(CN10),CN10,$J10*CN10) | CP10: 5272.364 | CQ10: =IF(ISTEXT(CP10),CP10,$J10*CP10) | CR10: N/A | CS10: =IF(ISTEXT(CR10),CR10,$J10*CR10) | CT10: N/A | CU10: =IF(ISTEXT(CT10),CT10,$J10*CT10) | CV10: =IF($J10="",0,IF($J10=1,_xlfn.MINIFS(CF10:CU10,CF10:CU10,">"&0),_xlfn.MINIFS(CF10:CU10,CF10:CU10,">"&0,CF10:CU10,"<>"&CF10,CF10:CU10,"<>"&CH10,CF10:CU10,"<>"&CJ10,CF10:CU10,"<>"&CL10,CF10:CU10,"<>"&CN10,CF10:CU10,"<>"&CP10,CF10:CU10,"<>"&CR10,CF10:CU10,"<>"&CT10,CF10:CU10,"<>"&#REF!,CF10:CU10,"<>"&#REF!,CF10:CU10,"<>"&#REF!,CF10:CU10,"<>"&#REF!,CF10:CU10,"<>"&#REF!,CF10:CU10,"<>"&#REF!,CF10:CU10,"<>"&#REF!,CF10:CU10,"<>"&#REF!,CF10:CU10,"<>"&#REF!,CF10:CU10,"<>"&#REF!,CF10:CU10,"<>"&#REF!,CF10:CU10,"<>"&#REF!,CF10:CU10,"<>"&#REF!,CF10:CU10,"<>"&#REF!,CF10:CU10,"<>"&#REF!,CF10:CU10,"<>"&#REF!,CF10:CU10,"<>"&#REF!,CF10:CU10,"<>"&#REF!,CF10:CU10,"<>"&#REF!,CF10:CU10,"<>"&#REF!,CF10:CU10,"<>"&#REF!,CF10:CU10,"<>"&#REF!))) | CX10: 14293.782 | CY10: =IF(ISTEXT(CX10),CX10,$J10*CX10) | CZ10: NA | DA10: =IF(ISTEXT(CZ10),CZ10,$J10*CZ10) | DB10: 16135.96 | DC10: =IF(ISTEXT(DB10),DB10,$J10*DB10) | DD10: 9556.5952 | DE10: =IF(ISTEXT(DD10),DD10,$J10*DD10) | DF10: n/a | DG10: =IF(ISTEXT(DF10),DF10,$J10*DF10) | DH10: 5272.364 | DI10: =IF(ISTEXT(DH10),DH10,$J10*DH10) | DJ10: N/A | DK10: =IF(ISTEXT(DJ10),DJ10,$J10*DJ10) | DL10: N/A | DM10: =IF(ISTEXT(DL10),DL10,$J10*DL10) | DN10: =IF($J10="",0,IF($J10=1,_xlfn.MINIFS(CX10:DM10,CX10:DM10,">"&0),_xlfn.MINIFS(CX10:DM10,CX10:DM10,">"&0,CX10:DM10,"<>"&CX10,CX10:DM10,"<>"&CZ10,CX10:DM10,"<>"&DB10,CX10:DM10,"<>"&DD10,CX10:DM10,"<>"&DF10,CX10:DM10,"<>"&DH10,CX10:DM10,"<>"&DJ10,CX10:DM10,"<>"&DL10,CX10:DM10,"<>"&#REF!,CX10:DM10,"<>"&#REF!,CX10:DM10,"<>"&#REF!,CX10:DM10,"<>"&#REF!,CX10:DM10,"<>"&#REF!,CX10:DM10,"<>"&#REF!,CX10:DM10,"<>"&#REF!,CX10:DM10,"<>"&#REF!,CX10:DM10,"<>"&#REF!,CX10:DM10,"<>"&#REF!,CX10:DM10,"<>"&#REF!,CX10:DM10,"<>"&#REF!,CX10:DM10,"<>"&#REF!,CX10:DM10,"<>"&#REF!,CX10:DM10,"<>"&#REF!,CX10:DM10,"<>"&#REF!,CX10:DM10,"<>"&#REF!,CX10:DM10,"<>"&#REF!,CX10:DM10,"<>"&#REF!,CX10:DM10,"<>"&#REF!,CX10:DM10,"<>"&#REF!,CX10:DM10,"<>"&#REF!))) | DO10: =IF($J10="",0,IF($J10=1,_xlfn.MINIFS(#REF!,#REF!,">"&0),_xlfn.MINIFS(#REF!,#REF!,">"&0,#REF!,"<>"&#REF!,#REF!,"<>"&#REF!,#REF!,"<>"&#REF!,#REF!,"<>"&#REF!,#REF!,"<>"&#REF!,#REF!,"<>"&#REF!,#REF!,"<>"&#REF!,#REF!,"<>"&#REF!,#REF!,"<>"&#REF!,#REF!,"<>"&#REF!,#REF!,"<>"&#REF!,#REF!,"<>"&#REF!,#REF!,"<>"&#REF!,#REF!,"<>"&#REF!,#REF!,"<>"&#REF!,#REF!,"<>"&#REF!,#REF!,"<>"&#REF!,#REF!,"<>"&#REF!,#REF!,"<>"&#REF!,#REF!,"<>"&#REF!,#REF!,"<>"&#REF!,#REF!,"<>"&#REF!,#REF!,"<>"&#REF!,#REF!,"<>"&#REF!,#REF!,"<>"&#REF!,#REF!,"<>"&#REF!,#REF!,"<>"&#REF!,#REF!,"<>"&#REF!,#REF!,"<>"&#REF!,#REF!,"<>"&#REF!)))
B11: MASTRO | C11: Mastros Mastros com altura superior 2m deverão ser providos de pedaleira e cabo trava-quedas. | D11: - | E11: 3 | F11: 6 | G11: 3 | H11: 45 | I11: VB | K11: 17955.421 | L11: =IF(ISTEXT(K11),K11,$J11*K11) | M11: 19484.17 | N11: =IF(ISTEXT(M11),M11,$J11*M11) | O11: 9556.5952 | P11: =IF(ISTEXT(O11),O11,$J11*O11) | Q11: n/a | R11: =IF(ISTEXT(Q11),Q11,$J11*Q11) | S11: 5154.8514 | T11: =IF(ISTEXT(S11),S11,$J11*S11) | U11: N/A | V11: =IF(ISTEXT(U11),U11,$J11*U11) | W11: N/A | X11: =IF(ISTEXT(W11),W11,$J11*W11) | Z11: 18810.442 | AA11: =IF(ISTEXT(Z11),Z11,$J11*Z11) | AB11: NA | AC11: =IF(ISTEXT(AB11),AB11,$J11*AB11) | AD11: 18637.03 | AE11: =IF(ISTEXT(AD11),AD11,$J11*AD11) | AF11: 9556.5952 | AG11: =IF(ISTEXT(AF11),AF11,$J11*AF11) | AH11: n/a | AI11: =IF(ISTEXT(AH11),AH11,$J11*AH11) | AJ11: 5272.364 | AK11: =IF(ISTEXT(AJ11),AJ11,$J11*AJ11) | AL11: N/A | AM11: =IF(ISTEXT(AL11),AL11,$J11*AL11) | AN11: N/A | AO11: =IF(ISTEXT(AN11),AN11,$J11*AN11) | AU11: 15038.54 | AV11: =AVERAGE(AZ11,BB11,BD11,BF11,BH11,BJ11,BL11) | AW11: =BASEDADOS[[#This Row],[VL UNIT MÉDIA]]*BASEDADOS[[#This Row],[QTDE]] | AX11: =ROUND(AU11*PARÂMETROS!$B$4,2) | AZ11: 20520.482 | BA11: =IF(ISTEXT(AZ11),AZ11,$J11*AZ11) | BB11: 21178.45 | BC11: =IF(ISTEXT(BB11),BB11,$J11*BB11) | BD11: 9556.5952 | BE11: =IF(ISTEXT(BD11),BD11,$J11*BD11) | BF11: n/a | BG11: =IF(ISTEXT(BF11),BF11,$J11*BF11) | BH11: 5272.364 | BI11: =IF(ISTEXT(BH11),BH11,$J11*BH11) | BJ11: N/A | BK11: =IF(ISTEXT(BJ11),BJ11,$J11*BJ11) | BL11: N/A | BM11: =IF(ISTEXT(BL11),BL11,$J11*BL11) | BN11: 17100.401 | BO11: =IF(ISTEXT(BN11),BN11,$J11*BN11) | BP11: NA | BQ11: =IF(ISTEXT(BP11),BP11,$J11*BP11) | BR11: 16942.76 | BS11: =IF(ISTEXT(BR11),BR11,$J11*BR11) | BT11: 9556.5952 | BU11: =IF(ISTEXT(BT11),BT11,$J11*BT11) | BV11: n/a | BW11: =IF(ISTEXT(BV11),BV11,$J11*BV11) | BX11: 5272.364 | BY11: =IF(ISTEXT(BX11),BX11,$J11*BX11) | BZ11: N/A | CA11: =IF(ISTEXT(BZ11),BZ11,$J11*BZ11) | CB11: N/A | CC11: =IF(ISTEXT(CB11),CB11,$J11*CB11) | CD11: =IF($J11="",0,IF($J11=1,_xlfn.MINIFS(BN11:CC11,BN11:CC11,">"&0),_xlfn.MINIFS(BN11:CC11,BN11:CC11,">"&0,BN11:CC11,"<>"&BN11,BN11:CC11,"<>"&BP11,BN11:CC11,"<>"&BR11,BN11:CC11,"<>"&BT11,BN11:CC11,"<>"&BV11,BN11:CC11,"<>"&BX11,BN11:CC11,"<>"&BZ11,BN11:CC11,"<>"&CB11,BN11:CC11,"<>"&#REF!,BN11:CC11,"<>"&#REF!,BN11:CC11,"<>"&#REF!,BN11:CC11,"<>"&#REF!,BN11:CC11,"<>"&#REF!,BN11:CC11,"<>"&#REF!,BN11:CC11,"<>"&#REF!,BN11:CC11,"<>"&#REF!,BN11:CC11,"<>"&#REF!,BN11:CC11,"<>"&#REF!,BN11:CC11,"<>"&#REF!,BN11:CC11,"<>"&#REF!,BN11:CC11,"<>"&#REF!,BN11:CC11,"<>"&#REF!,BN11:CC11,"<>"&#REF!,BN11:CC11,"<>"&#REF!,BN11:CC11,"<>"&#REF!,BN11:CC11,"<>"&#REF!,BN11:CC11,"<>"&#REF!,BN11:CC11,"<>"&#REF!,BN11:CC11,"<>"&#REF!,BN11:CC11,"<>"&#REF!))) | CF11: 17100.401 | CG11: =IF(ISTEXT(CF11),CF11,$J11*CF11) | CH11: NA | CI11: =IF(ISTEXT(CH11),CH11,$J11*CH11) | CJ11: 16942.76 | CK11: =IF(ISTEXT(CJ11),CJ11,$J11*CJ11) | CL11: 9556.5952 | CM11: =IF(ISTEXT(CL11),CL11,$J11*CL11) | CN11: n/a | CO11: =IF(ISTEXT(CN11),CN11,$J11*CN11) | CP11: 5272.364 | CQ11: =IF(ISTEXT(CP11),CP11,$J11*CP11) | CR11: N/A | CS11: =IF(ISTEXT(CR11),CR11,$J11*CR11) | CT11: N/A | CU11: =IF(ISTEXT(CT11),CT11,$J11*CT11) | CV11: =IF($J11="",0,IF($J11=1,_xlfn.MINIFS(CF11:CU11,CF11:CU11,">"&0),_xlfn.MINIFS(CF11:CU11,CF11:CU11,">"&0,CF11:CU11,"<>"&CF11,CF11:CU11,"<>"&CH11,CF11:CU11,"<>"&CJ11,CF11:CU11,"<>"&CL11,CF11:CU11,"<>"&CN11,CF11:CU11,"<>"&CP11,CF11:CU11,"<>"&CR11,CF11:CU11,"<>"&CT11,CF11:CU11,"<>"&#REF!,CF11:CU11,"<>"&#REF!,CF11:CU11,"<>"&#REF!,CF11:CU11,"<>"&#REF!,CF11:CU11,"<>"&#REF!,CF11:CU11,"<>"&#REF!,CF11:CU11,"<>"&#REF!,CF11:CU11,"<>"&#REF!,CF11:CU11,"<>"&#REF!,CF11:CU11,"<>"&#REF!,CF11:CU11,"<>"&#REF!,CF11:CU11,"<>"&#REF!,CF11:CU11,"<>"&#REF!,CF11:CU11,"<>"&#REF!,CF11:CU11,"<>"&#REF!,CF11:CU11,"<>"&#REF!,CF11:CU11,"<>"&#REF!,CF11:CU11,"<>"&#REF!,CF11:CU11,"<>"&#REF!,CF11:CU11,"<>"&#REF!,CF11:CU11,"<>"&#REF!,CF11:CU11,"<>"&#REF!))) | CX11: 17100.401 | CY11: =IF(ISTEXT(CX11),CX11,$J11*CX11) | CZ11: NA | DA11: =IF(ISTEXT(CZ11),CZ11,$J11*CZ11) | DB11: 16942.76 | DC11: =IF(ISTEXT(DB11),DB11,$J11*DB11) | DD11: 9556.5952 | DE11: =IF(ISTEXT(DD11),DD11,$J11*DD11) | DF11: n/a | DG11: =IF(ISTEXT(DF11),DF11,$J11*DF11) | DH11: 5272.364 | DI11: =IF(ISTEXT(DH11),DH11,$J11*DH11) | DJ11: N/A | DK11: =IF(ISTEXT(DJ11),DJ11,$J11*DJ11) | DL11: N/A | DM11: =IF(ISTEXT(DL11),DL11,$J11*DL11) | DN11: =IF($J11="",0,IF($J11=1,_xlfn.MINIFS(CX11:DM11,CX11:DM11,">"&0),_xlfn.MINIFS(CX11:DM11,CX11:DM11,">"&0,CX11:DM11,"<>"&CX11,CX11:DM11,"<>"&CZ11,CX11:DM11,"<>"&DB11,CX11:DM11,"<>"&DD11,CX11:DM11,"<>"&DF11,CX11:DM11,"<>"&DH11,CX11:DM11,"<>"&DJ11,CX11:DM11,"<>"&DL11,CX11:DM11,"<>"&#REF!,CX11:DM11,"<>"&#REF!,CX11:DM11,"<>"&#REF!,CX11:DM11,"<>"&#REF!,CX11:DM11,"<>"&#REF!,CX11:DM11,"<>"&#REF!,CX11:DM11,"<>"&#REF!,CX11:DM11,"<>"&#REF!,CX11:DM11,"<>"&#REF!,CX11:DM11,"<>"&#REF!,CX11:DM11,"<>"&#REF!,CX11:DM11,"<>"&#REF!,CX11:DM11,"<>"&#REF!,CX11:DM11,"<>"&#REF!,CX11:DM11,"<>"&#REF!,CX11:DM11,"<>"&#REF!,CX11:DM11,"<>"&#REF!,CX11:DM11,"<>"&#REF!,CX11:DM11,"<>"&#REF!,CX11:DM11,"<>"&#REF!,CX11:DM11,"<>"&#REF!,CX11:DM11,"<>"&#REF!))) | DO11: =IF($J11="",0,IF($J11=1,_xlfn.MINIFS(#REF!,#REF!,">"&0),_xlfn.MINIFS(#REF!,#REF!,">"&0,#REF!,"<>"&#REF!,#REF!,"<>"&#REF!,#REF!,"<>"&#REF!,#REF!,"<>"&#REF!,#REF!,"<>"&#REF!,#REF!,"<>"&#REF!,#REF!,"<>"&#REF!,#REF!,"<>"&#REF!,#REF!,"<>"&#REF!,#REF!,"<>"&#REF!,#REF!,"<>"&#REF!,#REF!,"<>"&#REF!,#REF!,"<>"&#REF!,#REF!,"<>"&#REF!,#REF!,"<>"&#REF!,#REF!,"<>"&#REF!,#REF!,"<>"&#REF!,#REF!,"<>"&#REF!,#REF!,"<>"&#REF!,#REF!,"<>"&#REF!,#REF!,"<>"&#REF!,#REF!,"<>"&#REF!,#REF!,"<>"&#REF!,#REF!,"<>"&#REF!,#REF!,"<>"&#REF!,#REF!,"<>"&#REF!,#REF!,"<>"&#REF!,#REF!,"<>"&#REF!,#REF!,"<>"&#REF!,#REF!,"<>"&#REF!)))
B12: MASTRO | C12: Mastros Mastros com altura superior 2m deverão ser providos de pedaleira e cabo trava-quedas. | D12: - | E12: 3 | F12: 8 | G12: 3 | H12: 45 | I12: VB | K12: 30464.28 | L12: =IF(ISTEXT(K12),K12,$J12*K12) | M12: 31351.33 | N12: =IF(ISTEXT(M12),M12,$J12*M12) | O12: 15612.81 | P12: =IF(ISTEXT(O12),O12,$J12*O12) | Q12: n/a | R12: =IF(ISTEXT(Q12),Q12,$J12*Q12) | S12: 6096.7081 | T12: =IF(ISTEXT(S12),S12,$J12*S12) | U12: N/A | V12: =IF(ISTEXT(U12),U12,$J12*U12) | W12: N/A | X12: =IF(ISTEXT(W12),W12,$J12*W12) | Z12: 31914.96 | AA12: =IF(ISTEXT(Z12),Z12,$J12*Z12) | AB12: NA | AC12: =IF(ISTEXT(AB12),AB12,$J12*AB12) | AD12: 29988.23 | AE12: =IF(ISTEXT(AD12),AD12,$J12*AD12) | AF12: 15612.81 | AG12: =IF(ISTEXT(AF12),AF12,$J12*AF12) | AH12: n/a | AI12: =IF(ISTEXT(AH12),AH12,$J12*AH12) | AJ12: 6235.6917 | AK12: =IF(ISTEXT(AJ12),AJ12,$J12*AJ12) | AL12: N/A | AM12: =IF(ISTEXT(AL12),AL12,$J12*AL12) | AN12: N/A | AO12: =IF(ISTEXT(AN12),AN12,$J12*AN12) | AU12: 24845.17 | AV12: =AVERAGE(AZ12,BB12,BD12,BF12,BH12,BJ12,BL12) | AW12: =BASEDADOS[[#This Row],[VL UNIT MÉDIA]]*BASEDADOS[[#This Row],[QTDE]] | AX12: =ROUND(AU12*PARÂMETROS!$B$4,2) | AZ12: 34816.32 | BA12: =IF(ISTEXT(AZ12),AZ12,$J12*AZ12) | BB12: 34077.53 | BC12: =IF(ISTEXT(BB12),BB12,$J12*BB12) | BD12: 15612.81 | BE12: =IF(ISTEXT(BD12),BD12,$J12*BD12) | BF12: n/a | BG12: =IF(ISTEXT(BF12),BF12,$J12*BF12) | BH12: 6235.6917 | BI12: =IF(ISTEXT(BH12),BH12,$J12*BH12) | BJ12: N/A | BK12: =IF(ISTEXT(BJ12),BJ12,$J12*BJ12) | BL12: N/A | BM12: =IF(ISTEXT(BL12),BL12,$J12*BL12) | BN12: 29013.6 | BO12: =IF(ISTEXT(BN12),BN12,$J12*BN12) | BP12: NA | BQ12: =IF(ISTEXT(BP12),BP12,$J12*BP12) | BR12: 27262.02 | BS12: =IF(ISTEXT(BR12),BR12,$J12*BR12) | BT12: 15612.81 | BU12: =IF(ISTEXT(BT12),BT12,$J12*BT12) | BV12: n/a | BW12: =IF(ISTEXT(BV12),BV12,$J12*BV12) | BX12: 6235.6917 | BY12: =IF(ISTEXT(BX12),BX12,$J12*BX12) | BZ12: N/A | CA12: =IF(ISTEXT(BZ12),BZ12,$J12*BZ12) | CB12: N/A | CC12: =IF(ISTEXT(CB12),CB12,$J12*CB12) | CD12: =IF($J12="",0,IF($J12=1,_xlfn.MINIFS(BN12:CC12,BN12:CC12,">"&0),_xlfn.MINIFS(BN12:CC12,BN12:CC12,">"&0,BN12:CC12,"<>"&BN12,BN12:CC12,"<>"&BP12,BN12:CC12,"<>"&BR12,BN12:CC12,"<>"&BT12,BN12:CC12,"<>"&BV12,BN12:CC12,"<>"&BX12,BN12:CC12,"<>"&BZ12,BN12:CC12,"<>"&CB12,BN12:CC12,"<>"&#REF!,BN12:CC12,"<>"&#REF!,BN12:CC12,"<>"&#REF!,BN12:CC12,"<>"&#REF!,BN12:CC12,"<>"&#REF!,BN12:CC12,"<>"&#REF!,BN12:CC12,"<>"&#REF!,BN12:CC12,"<>"&#REF!,BN12:CC12,"<>"&#REF!,BN12:CC12,"<>"&#REF!,BN12:CC12,"<>"&#REF!,BN12:CC12,"<>"&#REF!,BN12:CC12,"<>"&#REF!,BN12:CC12,"<>"&#REF!,BN12:CC12,"<>"&#REF!,BN12:CC12,"<>"&#REF!,BN12:CC12,"<>"&#REF!,BN12:CC12,"<>"&#REF!,BN12:CC12,"<>"&#REF!,BN12:CC12,"<>"&#REF!,BN12:CC12,"<>"&#REF!,BN12:CC12,"<>"&#REF!))) | CF12: 31914.96 | CG12: =IF(ISTEXT(CF12),CF12,$J12*CF12) | CH12: NA | CI12: =IF(ISTEXT(CH12),CH12,$J12*CH12) | CJ12: 27262.02 | CK12: =IF(ISTEXT(CJ12),CJ12,$J12*CJ12) | CL12: 15612.81 | CM12: =IF(ISTEXT(CL12),CL12,$J12*CL12) | CN12: n/a | CO12: =IF(ISTEXT(CN12),CN12,$J12*CN12) | CP12: 6235.6917 | CQ12: =IF(ISTEXT(CP12),CP12,$J12*CP12) | CR12: N/A | CS12: =IF(ISTEXT(CR12),CR12,$J12*CR12) | CT12: N/A | CU12: =IF(ISTEXT(CT12),CT12,$J12*CT12) | CV12: =IF($J12="",0,IF($J12=1,_xlfn.MINIFS(CF12:CU12,CF12:CU12,">"&0),_xlfn.MINIFS(CF12:CU12,CF12:CU12,">"&0,CF12:CU12,"<>"&CF12,CF12:CU12,"<>"&CH12,CF12:CU12,"<>"&CJ12,CF12:CU12,"<>"&CL12,CF12:CU12,"<>"&CN12,CF12:CU12,"<>"&CP12,CF12:CU12,"<>"&CR12,CF12:CU12,"<>"&CT12,CF12:CU12,"<>"&#REF!,CF12:CU12,"<>"&#REF!,CF12:CU12,"<>"&#REF!,CF12:CU12,"<>"&#REF!,CF12:CU12,"<>"&#REF!,CF12:CU12,"<>"&#REF!,CF12:CU12,"<>"&#REF!,CF12:CU12,"<>"&#REF!,CF12:CU12,"<>"&#REF!,CF12:CU12,"<>"&#REF!,CF12:CU12,"<>"&#REF!,CF12:CU12,"<>"&#REF!,CF12:CU12,"<>"&#REF!,CF12:CU12,"<>"&#REF!,CF12:CU12,"<>"&#REF!,CF12:CU12,"<>"&#REF!,CF12:CU12,"<>"&#REF!,CF12:CU12,"<>"&#REF!,CF12:CU12,"<>"&#REF!,CF12:CU12,"<>"&#REF!,CF12:CU12,"<>"&#REF!,CF12:CU12,"<>"&#REF!))) | CX12: 29013.6 | CY12: =IF(ISTEXT(CX12),CX12,$J12*CX12) | CZ12: NA | DA12: =IF(ISTEXT(CZ12),CZ12,$J12*CZ12) | DB12: 27262.02 | DC12: =IF(ISTEXT(DB12),DB12,$J12*DB12) | DD12: 15612.81 | DE12: =IF(ISTEXT(DD12),DD12,$J12*DD12) | DF12: n/a | DG12: =IF(ISTEXT(DF12),DF12,$J12*DF12) | DH12: 6235.6917 | DI12: =IF(ISTEXT(DH12),DH12,$J12*DH12) | DJ12: N/A | DK12: =IF(ISTEXT(DJ12),DJ12,$J12*DJ12) | DL12: N/A | DM12: =IF(ISTEXT(DL12),DL12,$J12*DL12) | DN12: =IF($J12="",0,IF($J12=1,_xlfn.MINIFS(CX12:DM12,CX12:DM12,">"&0),_xlfn.MINIFS(CX12:DM12,CX12:DM12,">"&0,CX12:DM12,"<>"&CX12,CX12:DM12,"<>"&CZ12,CX12:DM12,"<>"&DB12,CX12:DM12,"<>"&DD12,CX12:DM12,"<>"&DF12,CX12:DM12,"<>"&DH12,CX12:DM12,"<>"&DJ12,CX12:DM12,"<>"&DL12,CX12:DM12,"<>"&#REF!,CX12:DM12,"<>"&#REF!,CX12:DM12,"<>"&#REF!,CX12:DM12,"<>"&#REF!,CX12:DM12,"<>"&#REF!,CX12:DM12,"<>"&#REF!,CX12:DM12,"<>"&#REF!,CX12:DM12,"<>"&#REF!,CX12:DM12,"<>"&#REF!,CX12:DM12,"<>"&#REF!,CX12:DM12,"<>"&#REF!,CX12:DM12,"<>"&#REF!,CX12:DM12,"<>"&#REF!,CX12:DM12,"<>"&#REF!,CX12:DM12,"<>"&#REF!,CX12:DM12,"<>"&#REF!,CX12:DM12,"<>"&#REF!,CX12:DM12,"<>"&#REF!,CX12:DM12,"<>"&#REF!,CX12:DM12,"<>"&#REF!,CX12:DM12,"<>"&#REF!,CX12:DM12,"<>"&#REF!))) | DO12: =IF($J12="",0,IF($J12=1,_xlfn.MINIFS(#REF!,#REF!,">"&0),_xlfn.MINIFS(#REF!,#REF!,">"&0,#REF!,"<>"&#REF!,#REF!,"<>"&#REF!,#REF!,"<>"&#REF!,#REF!,"<>"&#REF!,#REF!,"<>"&#REF!,#REF!,"<>"&#REF!,#REF!,"<>"&#REF!,#REF!,"<>"&#REF!,#REF!,"<>"&#REF!,#REF!,"<>"&#REF!,#REF!,"<>"&#REF!,#REF!,"<>"&#REF!,#REF!,"<>"&#REF!,#REF!,"<>"&#REF!,#REF!,"<>"&#REF!,#REF!,"<>"&#REF!,#REF!,"<>"&#REF!,#REF!,"<>"&#REF!,#REF!,"<>"&#REF!,#REF!,"<>"&#REF!,#REF!,"<>"&#REF!,#REF!,"<>"&#REF!,#REF!,"<>"&#REF!,#REF!,"<>"&#REF!,#REF!,"<>"&#REF!,#REF!,"<>"&#REF!,#REF!,"<>"&#REF!,#REF!,"<>"&#REF!,#REF!,"<>"&#REF!,#REF!,"<>"&#REF!)))
B13: MASTRO | C13: Mastros Mastros com altura superior 2m deverão ser providos de pedaleira e cabo trava-quedas. | D13: - | E13: 4 | F13: 8 | G13: 4 | H13: 45 | I13: VB | K13: 31191.93 | L13: =IF(ISTEXT(K13),K13,$J13*K13) | M13: 32918.89 | N13: =IF(ISTEXT(M13),M13,$J13*M13) | O13: 15612.81 | P13: =IF(ISTEXT(O13),O13,$J13*O13) | Q13: n/a | R13: =IF(ISTEXT(Q13),Q13,$J13*Q13) | S13: 6096.7081 | T13: =IF(ISTEXT(S13),S13,$J13*S13) | U13: N/A | V13: =IF(ISTEXT(U13),U13,$J13*U13) | W13: N/A | X13: =IF(ISTEXT(W13),W13,$J13*W13) | Z13: 32677.26 | AA13: =IF(ISTEXT(Z13),Z13,$J13*Z13) | AB13: NA | AC13: =IF(ISTEXT(AB13),AB13,$J13*AB13) | AD13: 31487.64 | AE13: =IF(ISTEXT(AD13),AD13,$J13*AD13) | AF13: 15612.81 | AG13: =IF(ISTEXT(AF13),AF13,$J13*AF13) | AH13: n/a | AI13: =IF(ISTEXT(AH13),AH13,$J13*AH13) | AJ13: 6235.6917 | AK13: =IF(ISTEXT(AJ13),AJ13,$J13*AJ13) | AL13: N/A | AM13: =IF(ISTEXT(AL13),AL13,$J13*AL13) | AN13: N/A | AO13: =IF(ISTEXT(AN13),AN13,$J13*AN13) | AU13: 25630.36 | AV13: =AVERAGE(AZ13,BB13,BD13,BF13,BH13,BJ13,BL13) | AW13: =BASEDADOS[[#This Row],[VL UNIT MÉDIA]]*BASEDADOS[[#This Row],[QTDE]] | AX13: =ROUND(AU13*PARÂMETROS!$B$4,2) | AZ13: 35647.92 | BA13: =IF(ISTEXT(AZ13),AZ13,$J13*AZ13) | BB13: 35781.41 | BC13: =IF(ISTEXT(BB13),BB13,$J13*BB13) | BD13: 15612.81 | BE13: =IF(ISTEXT(BD13),BD13,$J13*BD13) | BF13: n/a | BG13: =IF(ISTEXT(BF13),BF13,$J13*BF13) | BH13: 6235.6917 | BI13: =IF(ISTEXT(BH13),BH13,$J13*BH13) | BJ13: N/A | BK13: =IF(ISTEXT(BJ13),BJ13,$J13*BJ13) | BL13: N/A | BM13: =IF(ISTEXT(BL13),BL13,$J13*BL13) | BN13: 29706.6 | BO13: =IF(ISTEXT(BN13),BN13,$J13*BN13) | BP13: NA | BQ13: =IF(ISTEXT(BP13),BP13,$J13*BP13) | BR13: 28625.13 | BS13: =IF(ISTEXT(BR13),BR13,$J13*BR13) | BT13: 15612.81 | BU13: =IF(ISTEXT(BT13),BT13,$J13*BT13) | BV13: n/a | BW13: =IF(ISTEXT(BV13),BV13,$J13*BV13) | BX13: 6235.6917 | BY13: =IF(ISTEXT(BX13),BX13,$J13*BX13) | BZ13: N/A | CA13: =IF(ISTEXT(BZ13),BZ13,$J13*BZ13) | CB13: N/A | CC13: =IF(ISTEXT(CB13),CB13,$J13*CB13) | CD13: =IF($J13="",0,IF($J13=1,_xlfn.MINIFS(BN13:CC13,BN13:CC13,">"&0),_xlfn.MINIFS(BN13:CC13,BN13:CC13,">"&0,BN13:CC13,"<>"&BN13,BN13:CC13,"<>"&BP13,BN13:CC13,"<>"&BR13,BN13:CC13,"<>"&BT13,BN13:CC13,"<>"&BV13,BN13:CC13,"<>"&BX13,BN13:CC13,"<>"&BZ13,BN13:CC13,"<>"&CB13,BN13:CC13,"<>"&#REF!,BN13:CC13,"<>"&#REF!,BN13:CC13,"<>"&#REF!,BN13:CC13,"<>"&#REF!,BN13:CC13,"<>"&#REF!,BN13:CC13,"<>"&#REF!,BN13:CC13,"<>"&#REF!,BN13:CC13,"<>"&#REF!,BN13:CC13,"<>"&#REF!,BN13:CC13,"<>"&#REF!,BN13:CC13,"<>"&#REF!,BN13:CC13,"<>"&#REF!,BN13:CC13,"<>"&#REF!,BN13:CC13,"<>"&#REF!,BN13:CC13,"<>"&#REF!,BN13:CC13,"<>"&#REF!,BN13:CC13,"<>"&#REF!,BN13:CC13,"<>"&#REF!,BN13:CC13,"<>"&#REF!,BN13:CC13,"<>"&#REF!,BN13:CC13,"<>"&#REF!,BN13:CC13,"<>"&#REF!))) | CF13: 32677.26 | CG13: =IF(ISTEXT(CF13),CF13,$J13*CF13) | CH13: NA | CI13: =IF(ISTEXT(CH13),CH13,$J13*CH13) | CJ13: 28625.13 | CK13: =IF(ISTEXT(CJ13),CJ13,$J13*CJ13) | CL13: 15612.81 | CM13: =IF(ISTEXT(CL13),CL13,$J13*CL13) | CN13: n/a | CO13: =IF(ISTEXT(CN13),CN13,$J13*CN13) | CP13: 6235.6917 | CQ13: =IF(ISTEXT(CP13),CP13,$J13*CP13) | CR13: N/A | CS13: =IF(ISTEXT(CR13),CR13,$J13*CR13) | CT13: N/A | CU13: =IF(ISTEXT(CT13),CT13,$J13*CT13) | CV13: =IF($J13="",0,IF($J13=1,_xlfn.MINIFS(CF13:CU13,CF13:CU13,">"&0),_xlfn.MINIFS(CF13:CU13,CF13:CU13,">"&0,CF13:CU13,"<>"&CF13,CF13:CU13,"<>"&CH13,CF13:CU13,"<>"&CJ13,CF13:CU13,"<>"&CL13,CF13:CU13,"<>"&CN13,CF13:CU13,"<>"&CP13,CF13:CU13,"<>"&CR13,CF13:CU13,"<>"&CT13,CF13:CU13,"<>"&#REF!,CF13:CU13,"<>"&#REF!,CF13:CU13,"<>"&#REF!,CF13:CU13,"<>"&#REF!,CF13:CU13,"<>"&#REF!,CF13:CU13,"<>"&#REF!,CF13:CU13,"<>"&#REF!,CF13:CU13,"<>"&#REF!,CF13:CU13,"<>"&#REF!,CF13:CU13,"<>"&#REF!,CF13:CU13,"<>"&#REF!,CF13:CU13,"<>"&#REF!,CF13:CU13,"<>"&#REF!,CF13:CU13,"<>"&#REF!,CF13:CU13,"<>"&#REF!,CF13:CU13,"<>"&#REF!,CF13:CU13,"<>"&#REF!,CF13:CU13,"<>"&#REF!,CF13:CU13,"<>"&#REF!,CF13:CU13,"<>"&#REF!,CF13:CU13,"<>"&#REF!,CF13:CU13,"<>"&#REF!))) | CX13: 29706.6 | CY13: =IF(ISTEXT(CX13),CX13,$J13*CX13) | CZ13: NA | DA13: =IF(ISTEXT(CZ13),CZ13,$J13*CZ13) | DB13: 28625.13 | DC13: =IF(ISTEXT(DB13),DB13,$J13*DB13) | DD13: 15612.81 | DE13: =IF(ISTEXT(DD13),DD13,$J13*DD13) | DF13: n/a | DG13: =IF(ISTEXT(DF13),DF13,$J13*DF13) | DH13: 6235.6917 | DI13: =IF(ISTEXT(DH13),DH13,$J13*DH13) | DJ13: N/A | DK13: =IF(ISTEXT(DJ13),DJ13,$J13*DJ13) | DL13: N/A | DM13: =IF(ISTEXT(DL13),DL13,$J13*DL13) | DN13: =IF($J13="",0,IF($J13=1,_xlfn.MINIFS(CX13:DM13,CX13:DM13,">"&0),_xlfn.MINIFS(CX13:DM13,CX13:DM13,">"&0,CX13:DM13,"<>"&CX13,CX13:DM13,"<>"&CZ13,CX13:DM13,"<>"&DB13,CX13:DM13,"<>"&DD13,CX13:DM13,"<>"&DF13,CX13:DM13,"<>"&DH13,CX13:DM13,"<>"&DJ13,CX13:DM13,"<>"&DL13,CX13:DM13,"<>"&#REF!,CX13:DM13,"<>"&#REF!,CX13:DM13,"<>"&#REF!,CX13:DM13,"<>"&#REF!,CX13:DM13,"<>"&#REF!,CX13:DM13,"<>"&#REF!,CX13:DM13,"<>"&#REF!,CX13:DM13,"<>"&#REF!,CX13:DM13,"<>"&#REF!,CX13:DM13,"<>"&#REF!,CX13:DM13,"<>"&#REF!,CX13:DM13,"<>"&#REF!,CX13:DM13,"<>"&#REF!,CX13:DM13,"<>"&#REF!,CX13:DM13,"<>"&#REF!,CX13:DM13,"<>"&#REF!,CX13:DM13,"<>"&#REF!,CX13:DM13,"<>"&#REF!,CX13:DM13,"<>"&#REF!,CX13:DM13,"<>"&#REF!,CX13:DM13,"<>"&#REF!,CX13:DM13,"<>"&#REF!))) | DO13: =IF($J13="",0,IF($J13=1,_xlfn.MINIFS(#REF!,#REF!,">"&0),_xlfn.MINIFS(#REF!,#REF!,">"&0,#REF!,"<>"&#REF!,#REF!,"<>"&#REF!,#REF!,"<>"&#REF!,#REF!,"<>"&#REF!,#REF!,"<>"&#REF!,#REF!,"<>"&#REF!,#REF!,"<>"&#REF!,#REF!,"<>"&#REF!,#REF!,"<>"&#REF!,#REF!,"<>"&#REF!,#REF!,"<>"&#REF!,#REF!,"<>"&#REF!,#REF!,"<>"&#REF!,#REF!,"<>"&#REF!,#REF!,"<>"&#REF!,#REF!,"<>"&#REF!,#REF!,"<>"&#REF!,#REF!,"<>"&#REF!,#REF!,"<>"&#REF!,#REF!,"<>"&#REF!,#REF!,"<>"&#REF!,#REF!,"<>"&#REF!,#REF!,"<>"&#REF!,#REF!,"<>"&#REF!,#REF!,"<>"&#REF!,#REF!,"<>"&#REF!,#REF!,"<>"&#REF!,#REF!,"<>"&#REF!,#REF!,"<>"&#REF!,#REF!,"<>"&#REF!)))
B14: POSTE | C14: Poste de Concreto ou Fibra Simplificado Deflexão máxima 1◦0"00" | D14: Suporte RF em plataforma EV > 30m | E14: 3 | F14: 9 | G14: 3 | H14: 30 | I14: VB | K14: NA | L14: =IF(ISTEXT(K14),K14,$J14*K14) | M14: 3375 | N14: =IF(ISTEXT(M14),M14,$J14*M14) | O14: N/A | P14: =IF(ISTEXT(O14),O14,$J14*O14) | Q14: n/a | R14: =IF(ISTEXT(Q14),Q14,$J14*Q14) | S14: =IF(ISTEXT(R14),R14,$J14*R14) | T14: =IF(ISTEXT(S14),S14,$J14*S14) | U14: N/A | V14: =IF(ISTEXT(U14),U14,$J14*U14) | W14: N/A | X14: =IF(ISTEXT(W14),W14,$J14*W14) | Z14: NA | AA14: =IF(ISTEXT(Z14),Z14,$J14*Z14) | AB14: NA | AC14: =IF(ISTEXT(AB14),AB14,$J14*AB14) | AD14: 3375 | AE14: =IF(ISTEXT(AD14),AD14,$J14*AD14) | AF14: N/A | AG14: =IF(ISTEXT(AF14),AF14,$J14*AF14) | AH14: n/a | AI14: =IF(ISTEXT(AH14),AH14,$J14*AH14) | AJ14: =IF(ISTEXT(AI14),AI14,$J14*AI14) | AK14: =IF(ISTEXT(AJ14),AJ14,$J14*AJ14) | AL14: N/A | AM14: =IF(ISTEXT(AL14),AL14,$J14*AL14) | AN14: N/A | AO14: =IF(ISTEXT(AN14),AN14,$J14*AN14) | AU14: 3375 | AV14: =AVERAGE(AZ14,BB14,BD14,BF14,BH14,BJ14,BL14) | AW14: =BASEDADOS[[#This Row],[VL UNIT MÉDIA]]*BASEDADOS[[#This Row],[QTDE]] | AX14: =ROUND(AU14*PARÂMETROS!$B$4,2) | AZ14: NA | BA14: =IF(ISTEXT(AZ14),AZ14,$J14*AZ14) | BB14: 3375 | BC14: =IF(ISTEXT(BB14),BB14,$J14*BB14) | BD14: N/A | BE14: =IF(ISTEXT(BD14),BD14,$J14*BD14) | BF14: n/a | BG14: =IF(ISTEXT(BF14),BF14,$J14*BF14) | BH14: =IF(ISTEXT(BG14),BG14,$J14*BG14) | BI14: =IF(ISTEXT(BH14),BH14,$J14*BH14) | BJ14: N/A | BK14: =IF(ISTEXT(BJ14),BJ14,$J14*BJ14) | BL14: N/A | BM14: =IF(ISTEXT(BL14),BL14,$J14*BL14) | BN14: NA | BO14: =IF(ISTEXT(BN14),BN14,$J14*BN14) | BP14: NA | BQ14: =IF(ISTEXT(BP14),BP14,$J14*BP14) | BR14: 3375 | BS14: =IF(ISTEXT(BR14),BR14,$J14*BR14) | BT14: N/A | BU14: =IF(ISTEXT(BT14),BT14,$J14*BT14) | BV14: n/a | BW14: =IF(ISTEXT(BV14),BV14,$J14*BV14) | BX14: =IF(ISTEXT(BW14),BW14,$J14*BW14) | BY14: =IF(ISTEXT(BX14),BX14,$J14*BX14) | BZ14: N/A | CA14: =IF(ISTEXT(BZ14),BZ14,$J14*BZ14) | CB14: N/A | CC14: =IF(ISTEXT(CB14),CB14,$J14*CB14) | CD14: =IF($J14="",0,IF($J14=1,_xlfn.MINIFS(BN14:CC14,BN14:CC14,">"&0),_xlfn.MINIFS(BN14:CC14,BN14:CC14,">"&0,BN14:CC14,"<>"&BN14,BN14:CC14,"<>"&BP14,BN14:CC14,"<>"&BR14,BN14:CC14,"<>"&BT14,BN14:CC14,"<>"&BV14,BN14:CC14,"<>"&BX14,BN14:CC14,"<>"&BZ14,BN14:CC14,"<>"&CB14,BN14:CC14,"<>"&#REF!,BN14:CC14,"<>"&#REF!,BN14:CC14,"<>"&#REF!,BN14:CC14,"<>"&#REF!,BN14:CC14,"<>"&#REF!,BN14:CC14,"<>"&#REF!,BN14:CC14,"<>"&#REF!,BN14:CC14,"<>"&#REF!,BN14:CC14,"<>"&#REF!,BN14:CC14,"<>"&#REF!,BN14:CC14,"<>"&#REF!,BN14:CC14,"<>"&#REF!,BN14:CC14,"<>"&#REF!,BN14:CC14,"<>"&#REF!,BN14:CC14,"<>"&#REF!,BN14:CC14,"<>"&#REF!,BN14:CC14,"<>"&#REF!,BN14:CC14,"<>"&#REF!,BN14:CC14,"<>"&#REF!,BN14:CC14,"<>"&#REF!,BN14:CC14,"<>"&#REF!,BN14:CC14,"<>"&#REF!))) | CF14: NA | CG14: =IF(ISTEXT(CF14),CF14,$J14*CF14) | CH14: NA | CI14: =IF(ISTEXT(CH14),CH14,$J14*CH14) | CJ14: 3375 | CK14: =IF(ISTEXT(CJ14),CJ14,$J14*CJ14) | CL14: N/A | CM14: =IF(ISTEXT(CL14),CL14,$J14*CL14) | CN14: n/a | CO14: =IF(ISTEXT(CN14),CN14,$J14*CN14) | CP14: =IF(ISTEXT(CO14),CO14,$J14*CO14) | CQ14: =IF(ISTEXT(CP14),CP14,$J14*CP14) | CR14: N/A | CS14: =IF(ISTEXT(CR14),CR14,$J14*CR14) | CT14: N/A | CU14: =IF(ISTEXT(CT14),CT14,$J14*CT14) | CV14: =IF($J14="",0,IF($J14=1,_xlfn.MINIFS(CF14:CU14,CF14:CU14,">"&0),_xlfn.MINIFS(CF14:CU14,CF14:CU14,">"&0,CF14:CU14,"<>"&CF14,CF14:CU14,"<>"&CH14,CF14:CU14,"<>"&CJ14,CF14:CU14,"<>"&CL14,CF14:CU14,"<>"&CN14,CF14:CU14,"<>"&CP14,CF14:CU14,"<>"&CR14,CF14:CU14,"<>"&CT14,CF14:CU14,"<>"&#REF!,CF14:CU14,"<>"&#REF!,CF14:CU14,"<>"&#REF!,CF14:CU14,"<>"&#REF!,CF14:CU14,"<>"&#REF!,CF14:CU14,"<>"&#REF!,CF14:CU14,"<>"&#REF!,CF14:CU14,"<>"&#REF!,CF14:CU14,"<>"&#REF!,CF14:CU14,"<>"&#REF!,CF14:CU14,"<>"&#REF!,CF14:CU14,"<>"&#REF!,CF14:CU14,"<>"&#REF!,CF14:CU14,"<>"&#REF!,CF14:CU14,"<>"&#REF!,CF14:CU14,"<>"&#REF!,CF14:CU14,"<>"&#REF!,CF14:CU14,"<>"&#REF!,CF14:CU14,"<>"&#REF!,CF14:CU14,"<>"&#REF!,CF14:CU14,"<>"&#REF!,CF14:CU14,"<>"&#REF!))) | CX14: NA | CY14: =IF(ISTEXT(CX14),CX14,$J14*CX14) | CZ14: NA | DA14: =IF(ISTEXT(CZ14),CZ14,$J14*CZ14) | DB14: 3375 | DC14: =IF(ISTEXT(DB14),DB14,$J14*DB14) | DD14: N/A | DE14: =IF(ISTEXT(DD14),DD14,$J14*DD14) | DF14: n/a | DG14: =IF(ISTEXT(DF14),DF14,$J14*DF14) | DH14: =IF(ISTEXT(DG14),DG14,$J14*DG14) | DI14: =IF(ISTEXT(DH14),DH14,$J14*DH14) | DJ14: N/A | DK14: =IF(ISTEXT(DJ14),DJ14,$J14*DJ14) | DL14: N/A | DM14: =IF(ISTEXT(DL14),DL14,$J14*DL14) | DN14: =IF($J14="",0,IF($J14=1,_xlfn.MINIFS(CX14:DM14,CX14:DM14,">"&0),_xlfn.MINIFS(CX14:DM14,CX14:DM14,">"&0,CX14:DM14,"<>"&CX14,CX14:DM14,"<>"&CZ14,CX14:DM14,"<>"&DB14,CX14:DM14,"<>"&DD14,CX14:DM14,"<>"&DF14,CX14:DM14,"<>"&DH14,CX14:DM14,"<>"&DJ14,CX14:DM14,"<>"&DL14,CX14:DM14,"<>"&#REF!,CX14:DM14,"<>"&#REF!,CX14:DM14,"<>"&#REF!,CX14:DM14,"<>"&#REF!,CX14:DM14,"<>"&#REF!,CX14:DM14,"<>"&#REF!,CX14:DM14,"<>"&#REF!,CX14:DM14,"<>"&#REF!,CX14:DM14,"<>"&#REF!,CX14:DM14,"<>"&#REF!,CX14:DM14,"<>"&#REF!,CX14:DM14,"<>"&#REF!,CX14:DM14,"<>"&#REF!,CX14:DM14,"<>"&#REF!,CX14:DM14,"<>"&#REF!,CX14:DM14,"<>"&#REF!,CX14:DM14,"<>"&#REF!,CX14:DM14,"<>"&#REF!,CX14:DM14,"<>"&#REF!,CX14:DM14,"<>"&#REF!,CX14:DM14,"<>"&#REF!,CX14:DM14,"<>"&#REF!))) | DO14: =IF($J14="",0,IF($J14=1,_xlfn.MINIFS(#REF!,#REF!,">"&0),_xlfn.MINIFS(#REF!,#REF!,">"&0,#REF!,"<>"&#REF!,#REF!,"<>"&#REF!,#REF!,"<>"&#REF!,#REF!,"<>"&#REF!,#REF!,"<>"&#REF!,#REF!,"<>"&#REF!,#REF!,"<>"&#REF!,#REF!,"<>"&#REF!,#REF!,"<>"&#REF!,#REF!,"<>"&#REF!,#REF!,"<>"&#REF!,#REF!,"<>"&#REF!,#REF!,"<>"&#REF!,#REF!,"<>"&#REF!,#REF!,"<>"&#REF!,#REF!,"<>"&#REF!,#REF!,"<>"&#REF!,#REF!,"<>"&#REF!,#REF!,"<>"&#REF!,#REF!,"<>"&#REF!,#REF!,"<>"&#REF!,#REF!,"<>"&#REF!,#REF!,"<>"&#REF!,#REF!,"<>"&#REF!,#REF!,"<>"&#REF!,#REF!,"<>"&#REF!,#REF!,"<>"&#REF!,#REF!,"<>"&#REF!,#REF!,"<>"&#REF!,#REF!,"<>"&#REF!)))
B15: POSTE | C15: Poste de Concreto ou Fibra Simplificado Deflexão máxima 1◦0"00" | D15: Suporte RF em plataforma EV > 30m | E15: 3 | F15: 9 | G15: 3 | H15: 35 | I15: VB | K15: NA | L15: =IF(ISTEXT(K15),K15,$J15*K15) | M15: 3543.75 | N15: =IF(ISTEXT(M15),M15,$J15*M15) | O15: N/A | P15: =IF(ISTEXT(O15),O15,$J15*O15) | Q15: n/a | R15: =IF(ISTEXT(Q15),Q15,$J15*Q15) | S15: =IF(ISTEXT(R15),R15,$J15*R15) | T15: =IF(ISTEXT(S15),S15,$J15*S15) | U15: N/A | V15: =IF(ISTEXT(U15),U15,$J15*U15) | W15: N/A | X15: =IF(ISTEXT(W15),W15,$J15*W15) | Z15: NA | AA15: =IF(ISTEXT(Z15),Z15,$J15*Z15) | AB15: NA | AC15: =IF(ISTEXT(AB15),AB15,$J15*AB15) | AD15: 3543.75 | AE15: =IF(ISTEXT(AD15),AD15,$J15*AD15) | AF15: N/A | AG15: =IF(ISTEXT(AF15),AF15,$J15*AF15) | AH15: n/a | AI15: =IF(ISTEXT(AH15),AH15,$J15*AH15) | AJ15: =IF(ISTEXT(AI15),AI15,$J15*AI15) | AK15: =IF(ISTEXT(AJ15),AJ15,$J15*AJ15) | AL15: N/A | AM15: =IF(ISTEXT(AL15),AL15,$J15*AL15) | AN15: N/A | AO15: =IF(ISTEXT(AN15),AN15,$J15*AN15) | AU15: 3543.75 | AV15: =AVERAGE(AZ15,BB15,BD15,BF15,BH15,BJ15,BL15) | AW15: =BASEDADOS[[#This Row],[VL UNIT MÉDIA]]*BASEDADOS[[#This Row],[QTDE]] | AX15: =ROUND(AU15*PARÂMETROS!$B$4,2) | AZ15: NA | BA15: =IF(ISTEXT(AZ15),AZ15,$J15*AZ15) | BB15: 3543.75 | BC15: =IF(ISTEXT(BB15),BB15,$J15*BB15) | BD15: N/A | BE15: =IF(ISTEXT(BD15),BD15,$J15*BD15) | BF15: n/a | BG15: =IF(ISTEXT(BF15),BF15,$J15*BF15) | BH15: =IF(ISTEXT(BG15),BG15,$J15*BG15) | BI15: =IF(ISTEXT(BH15),BH15,$J15*BH15) | BJ15: N/A | BK15: =IF(ISTEXT(BJ15),BJ15,$J15*BJ15) | BL15: N/A | BM15: =IF(ISTEXT(BL15),BL15,$J15*BL15) | BN15: NA | BO15: =IF(ISTEXT(BN15),BN15,$J15*BN15) | BP15: NA | BQ15: =IF(ISTEXT(BP15),BP15,$J15*BP15) | BR15: 3543.75 | BS15: =IF(ISTEXT(BR15),BR15,$J15*BR15) | BT15: N/A | BU15: =IF(ISTEXT(BT15),BT15,$J15*BT15) | BV15: n/a | BW15: =IF(ISTEXT(BV15),BV15,$J15*BV15) | BX15: =IF(ISTEXT(BW15),BW15,$J15*BW15) | BY15: =IF(ISTEXT(BX15),BX15,$J15*BX15) | BZ15: N/A | CA15: =IF(ISTEXT(BZ15),BZ15,$J15*BZ15) | CB15: N/A | CC15: =IF(ISTEXT(CB15),CB15,$J15*CB15) | CD15: =IF($J15="",0,IF($J15=1,_xlfn.MINIFS(BN15:CC15,BN15:CC15,">"&0),_xlfn.MINIFS(BN15:CC15,BN15:CC15,">"&0,BN15:CC15,"<>"&BN15,BN15:CC15,"<>"&BP15,BN15:CC15,"<>"&BR15,BN15:CC15,"<>"&BT15,BN15:CC15,"<>"&BV15,BN15:CC15,"<>"&BX15,BN15:CC15,"<>"&BZ15,BN15:CC15,"<>"&CB15,BN15:CC15,"<>"&#REF!,BN15:CC15,"<>"&#REF!,BN15:CC15,"<>"&#REF!,BN15:CC15,"<>"&#REF!,BN15:CC15,"<>"&#REF!,BN15:CC15,"<>"&#REF!,BN15:CC15,"<>"&#REF!,BN15:CC15,"<>"&#REF!,BN15:CC15,"<>"&#REF!,BN15:CC15,"<>"&#REF!,BN15:CC15,"<>"&#REF!,BN15:CC15,"<>"&#REF!,BN15:CC15,"<>"&#REF!,BN15:CC15,"<>"&#REF!,BN15:CC15,"<>"&#REF!,BN15:CC15,"<>"&#REF!,BN15:CC15,"<>"&#REF!,BN15:CC15,"<>"&#REF!,BN15:CC15,"<>"&#REF!,BN15:CC15,"<>"&#REF!,BN15:CC15,"<>"&#REF!,BN15:CC15,"<>"&#REF!))) | CF15: NA | CG15: =IF(ISTEXT(CF15),CF15,$J15*CF15) | CH15: NA | CI15: =IF(ISTEXT(CH15),CH15,$J15*CH15) | CJ15: 3543.75 | CK15: =IF(ISTEXT(CJ15),CJ15,$J15*CJ15) | CL15: N/A | CM15: =IF(ISTEXT(CL15),CL15,$J15*CL15) | CN15: n/a | CO15: =IF(ISTEXT(CN15),CN15,$J15*CN15) | CP15: =IF(ISTEXT(CO15),CO15,$J15*CO15) | CQ15: =IF(ISTEXT(CP15),CP15,$J15*CP15) | CR15: N/A | CS15: =IF(ISTEXT(CR15),CR15,$J15*CR15) | CT15: N/A | CU15: =IF(ISTEXT(CT15),CT15,$J15*CT15) | CV15: =IF($J15="",0,IF($J15=1,_xlfn.MINIFS(CF15:CU15,CF15:CU15,">"&0),_xlfn.MINIFS(CF15:CU15,CF15:CU15,">"&0,CF15:CU15,"<>"&CF15,CF15:CU15,"<>"&CH15,CF15:CU15,"<>"&CJ15,CF15:CU15,"<>"&CL15,CF15:CU15,"<>"&CN15,CF15:CU15,"<>"&CP15,CF15:CU15,"<>"&CR15,CF15:CU15,"<>"&CT15,CF15:CU15,"<>"&#REF!,CF15:CU15,"<>"&#REF!,CF15:CU15,"<>"&#REF!,CF15:CU15,"<>"&#REF!,CF15:CU15,"<>"&#REF!,CF15:CU15,"<>"&#REF!,CF15:CU15,"<>"&#REF!,CF15:CU15,"<>"&#REF!,CF15:CU15,"<>"&#REF!,CF15:CU15,"<>"&#REF!,CF15:CU15,"<>"&#REF!,CF15:CU15,"<>"&#REF!,CF15:CU15,"<>"&#REF!,CF15:CU15,"<>"&#REF!,CF15:CU15,"<>"&#REF!,CF15:CU15,"<>"&#REF!,CF15:CU15,"<>"&#REF!,CF15:CU15,"<>"&#REF!,CF15:CU15,"<>"&#REF!,CF15:CU15,"<>"&#REF!,CF15:CU15,"<>"&#REF!,CF15:CU15,"<>"&#REF!))) | CX15: NA | CY15: =IF(ISTEXT(CX15),CX15,$J15*CX15) | CZ15: NA | DA15: =IF(ISTEXT(CZ15),CZ15,$J15*CZ15) | DB15: 3543.75 | DC15: =IF(ISTEXT(DB15),DB15,$J15*DB15) | DD15: N/A | DE15: =IF(ISTEXT(DD15),DD15,$J15*DD15) | DF15: n/a | DG15: =IF(ISTEXT(DF15),DF15,$J15*DF15) | DH15: =IF(ISTEXT(DG15),DG15,$J15*DG15) | DI15: =IF(ISTEXT(DH15),DH15,$J15*DH15) | DJ15: N/A | DK15: =IF(ISTEXT(DJ15),DJ15,$J15*DJ15) | DL15: N/A | DM15: =IF(ISTEXT(DL15),DL15,$J15*DL15) | DN15: =IF($J15="",0,IF($J15=1,_xlfn.MINIFS(CX15:DM15,CX15:DM15,">"&0),_xlfn.MINIFS(CX15:DM15,CX15:DM15,">"&0,CX15:DM15,"<>"&CX15,CX15:DM15,"<>"&CZ15,CX15:DM15,"<>"&DB15,CX15:DM15,"<>"&DD15,CX15:DM15,"<>"&DF15,CX15:DM15,"<>"&DH15,CX15:DM15,"<>"&DJ15,CX15:DM15,"<>"&DL15,CX15:DM15,"<>"&#REF!,CX15:DM15,"<>"&#REF!,CX15:DM15,"<>"&#REF!,CX15:DM15,"<>"&#REF!,CX15:DM15,"<>"&#REF!,CX15:DM15,"<>"&#REF!,CX15:DM15,"<>"&#REF!,CX15:DM15,"<>"&#REF!,CX15:DM15,"<>"&#REF!,CX15:DM15,"<>"&#REF!,CX15:DM15,"<>"&#REF!,CX15:DM15,"<>"&#REF!,CX15:DM15,"<>"&#REF!,CX15:DM15,"<>"&#REF!,CX15:DM15,"<>"&#REF!,CX15:DM15,"<>"&#REF!,CX15:DM15,"<>"&#REF!,CX15:DM15,"<>"&#REF!,CX15:DM15,"<>"&#REF!,CX15:DM15,"<>"&#REF!,CX15:DM15,"<>"&#REF!,CX15:DM15,"<>"&#REF!))) | DO15: =IF($J15="",0,IF($J15=1,_xlfn.MINIFS(#REF!,#REF!,">"&0),_xlfn.MINIFS(#REF!,#REF!,">"&0,#REF!,"<>"&#REF!,#REF!,"<>"&#REF!,#REF!,"<>"&#REF!,#REF!,"<>"&#REF!,#REF!,"<>"&#REF!,#REF!,"<>"&#REF!,#REF!,"<>"&#REF!,#REF!,"<>"&#REF!,#REF!,"<>"&#REF!,#REF!,"<>"&#REF!,#REF!,"<>"&#REF!,#REF!,"<>"&#REF!,#REF!,"<>"&#REF!,#REF!,"<>"&#REF!,#REF!,"<>"&#REF!,#REF!,"<>"&#REF!,#REF!,"<>"&#REF!,#REF!,"<>"&#REF!,#REF!,"<>"&#REF!,#REF!,"<>"&#REF!,#REF!,"<>"&#REF!,#REF!,"<>"&#REF!,#REF!,"<>"&#REF!,#REF!,"<>"&#REF!,#REF!,"<>"&#REF!,#REF!,"<>"&#REF!,#REF!,"<>"&#REF!,#REF!,"<>"&#REF!,#REF!,"<>"&#REF!,#REF!,"<>"&#REF!)))
B16: POSTE | C16: Poste de Concreto ou Fibra Simplificado Deflexão máxima 1◦0"00" | D16: Suporte TX em plataforma EV > 30m | E16: 3 | F16: 9 | G16: 3 | H16: 40 | I16: VB | K16: NA | L16: =IF(ISTEXT(K16),K16,$J16*K16) | M16: 3720.94 | N16: =IF(ISTEXT(M16),M16,$J16*M16) | O16: N/A | P16: =IF(ISTEXT(O16),O16,$J16*O16) | Q16: n/a | R16: =IF(ISTEXT(Q16),Q16,$J16*Q16) | S16: =IF(ISTEXT(R16),R16,$J16*R16) | T16: =IF(ISTEXT(S16),S16,$J16*S16) | U16: N/A | V16: =IF(ISTEXT(U16),U16,$J16*U16) | W16: N/A | X16: =IF(ISTEXT(W16),W16,$J16*W16) | Z16: NA | AA16: =IF(ISTEXT(Z16),Z16,$J16*Z16) | AB16: NA | AC16: =IF(ISTEXT(AB16),AB16,$J16*AB16) | AD16: 3720.94 | AE16: =IF(ISTEXT(AD16),AD16,$J16*AD16) | AF16: N/A | AG16: =IF(ISTEXT(AF16),AF16,$J16*AF16) | AH16: n/a | AI16: =IF(ISTEXT(AH16),AH16,$J16*AH16) | AJ16: =IF(ISTEXT(AI16),AI16,$J16*AI16) | AK16: =IF(ISTEXT(AJ16),AJ16,$J16*AJ16) | AL16: N/A | AM16: =IF(ISTEXT(AL16),AL16,$J16*AL16) | AN16: N/A | AO16: =IF(ISTEXT(AN16),AN16,$J16*AN16) | AU16: 3720.94 | AV16: =AVERAGE(AZ16,BB16,BD16,BF16,BH16,BJ16,BL16) | AW16: =BASEDADOS[[#This Row],[VL UNIT MÉDIA]]*BASEDADOS[[#This Row],[QTDE]] | AX16: =ROUND(AU16*PARÂMETROS!$B$4,2) | AZ16: NA | BA16: =IF(ISTEXT(AZ16),AZ16,$J16*AZ16) | BB16: 3720.94 | BC16: =IF(ISTEXT(BB16),BB16,$J16*BB16) | BD16: N/A | BE16: =IF(ISTEXT(BD16),BD16,$J16*BD16) | BF16: n/a | BG16: =IF(ISTEXT(BF16),BF16,$J16*BF16) | BH16: =IF(ISTEXT(BG16),BG16,$J16*BG16) | BI16: =IF(ISTEXT(BH16),BH16,$J16*BH16) | BJ16: N/A | BK16: =IF(ISTEXT(BJ16),BJ16,$J16*BJ16) | BL16: N/A | BM16: =IF(ISTEXT(BL16),BL16,$J16*BL16) | BN16: NA | BO16: =IF(ISTEXT(BN16),BN16,$J16*BN16) | BP16: NA | BQ16: =IF(ISTEXT(BP16),BP16,$J16*BP16) | BR16: 3720.94 | BS16: =IF(ISTEXT(BR16),BR16,$J16*BR16) | BT16: N/A | BU16: =IF(ISTEXT(BT16),BT16,$J16*BT16) | BV16: n/a | BW16: =IF(ISTEXT(BV16),BV16,$J16*BV16) | BX16: =IF(ISTEXT(BW16),BW16,$J16*BW16) | BY16: =IF(ISTEXT(BX16),BX16,$J16*BX16) | BZ16: N/A | CA16: =IF(ISTEXT(BZ16),BZ16,$J16*BZ16) | CB16: N/A | CC16: =IF(ISTEXT(CB16),CB16,$J16*CB16) | CD16: =IF($J16="",0,IF($J16=1,_xlfn.MINIFS(BN16:CC16,BN16:CC16,">"&0),_xlfn.MINIFS(BN16:CC16,BN16:CC16,">"&0,BN16:CC16,"<>"&BN16,BN16:CC16,"<>"&BP16,BN16:CC16,"<>"&BR16,BN16:CC16,"<>"&BT16,BN16:CC16,"<>"&BV16,BN16:CC16,"<>"&BX16,BN16:CC16,"<>"&BZ16,BN16:CC16,"<>"&CB16,BN16:CC16,"<>"&#REF!,BN16:CC16,"<>"&#REF!,BN16:CC16,"<>"&#REF!,BN16:CC16,"<>"&#REF!,BN16:CC16,"<>"&#REF!,BN16:CC16,"<>"&#REF!,BN16:CC16,"<>"&#REF!,BN16:CC16,"<>"&#REF!,BN16:CC16,"<>"&#REF!,BN16:CC16,"<>"&#REF!,BN16:CC16,"<>"&#REF!,BN16:CC16,"<>"&#REF!,BN16:CC16,"<>"&#REF!,BN16:CC16,"<>"&#REF!,BN16:CC16,"<>"&#REF!,BN16:CC16,"<>"&#REF!,BN16:CC16,"<>"&#REF!,BN16:CC16,"<>"&#REF!,BN16:CC16,"<>"&#REF!,BN16:CC16,"<>"&#REF!,BN16:CC16,"<>"&#REF!,BN16:CC16,"<>"&#REF!))) | CF16: NA | CG16: =IF(ISTEXT(CF16),CF16,$J16*CF16) | CH16: NA | CI16: =IF(ISTEXT(CH16),CH16,$J16*CH16) | CJ16: 3720.94 | CK16: =IF(ISTEXT(CJ16),CJ16,$J16*CJ16) | CL16: N/A | CM16: =IF(ISTEXT(CL16),CL16,$J16*CL16) | CN16: n/a | CO16: =IF(ISTEXT(CN16),CN16,$J16*CN16) | CP16: =IF(ISTEXT(CO16),CO16,$J16*CO16) | CQ16: =IF(ISTEXT(CP16),CP16,$J16*CP16) | CR16: N/A | CS16: =IF(ISTEXT(CR16),CR16,$J16*CR16) | CT16: N/A | CU16: =IF(ISTEXT(CT16),CT16,$J16*CT16) | CV16: =IF($J16="",0,IF($J16=1,_xlfn.MINIFS(CF16:CU16,CF16:CU16,">"&0),_xlfn.MINIFS(CF16:CU16,CF16:CU16,">"&0,CF16:CU16,"<>"&CF16,CF16:CU16,"<>"&CH16,CF16:CU16,"<>"&CJ16,CF16:CU16,"<>"&CL16,CF16:CU16,"<>"&CN16,CF16:CU16,"<>"&CP16,CF16:CU16,"<>"&CR16,CF16:CU16,"<>"&CT16,CF16:CU16,"<>"&#REF!,CF16:CU16,"<>"&#REF!,CF16:CU16,"<>"&#REF!,CF16:CU16,"<>"&#REF!,CF16:CU16,"<>"&#REF!,CF16:CU16,"<>"&#REF!,CF16:CU16,"<>"&#REF!,CF16:CU16,"<>"&#REF!,CF16:CU16,"<>"&#REF!,CF16:CU16,"<>"&#REF!,CF16:CU16,"<>"&#REF!,CF16:CU16,"<>"&#REF!,CF16:CU16,"<>"&#REF!,CF16:CU16,"<>"&#REF!,CF16:CU16,"<>"&#REF!,CF16:CU16,"<>"&#REF!,CF16:CU16,"<>"&#REF!,CF16:CU16,"<>"&#REF!,CF16:CU16,"<>"&#REF!,CF16:CU16,"<>"&#REF!,CF16:CU16,"<>"&#REF!,CF16:CU16,"<>"&#REF!))) | CX16: NA | CY16: =IF(ISTEXT(CX16),CX16,$J16*CX16) | CZ16: NA | DA16: =IF(ISTEXT(CZ16),CZ16,$J16*CZ16) | DB16: 3720.94 | DC16: =IF(ISTEXT(DB16),DB16,$J16*DB16) | DD16: N/A | DE16: =IF(ISTEXT(DD16),DD16,$J16*DD16) | DF16: n/a | DG16: =IF(ISTEXT(DF16),DF16,$J16*DF16) | DH16: =IF(ISTEXT(DG16),DG16,$J16*DG16) | DI16: =IF(ISTEXT(DH16),DH16,$J16*DH16) | DJ16: N/A | DK16: =IF(ISTEXT(DJ16),DJ16,$J16*DJ16) | DL16: N/A | DM16: =IF(ISTEXT(DL16),DL16,$J16*DL16) | DN16: =IF($J16="",0,IF($J16=1,_xlfn.MINIFS(CX16:DM16,CX16:DM16,">"&0),_xlfn.MINIFS(CX16:DM16,CX16:DM16,">"&0,CX16:DM16,"<>"&CX16,CX16:DM16,"<>"&CZ16,CX16:DM16,"<>"&DB16,CX16:DM16,"<>"&DD16,CX16:DM16,"<>"&DF16,CX16:DM16,"<>"&DH16,CX16:DM16,"<>"&DJ16,CX16:DM16,"<>"&DL16,CX16:DM16,"<>"&#REF!,CX16:DM16,"<>"&#REF!,CX16:DM16,"<>"&#REF!,CX16:DM16,"<>"&#REF!,CX16:DM16,"<>"&#REF!,CX16:DM16,"<>"&#REF!,CX16:DM16,"<>"&#REF!,CX16:DM16,"<>"&#REF!,CX16:DM16,"<>"&#REF!,CX16:DM16,"<>"&#REF!,CX16:DM16,"<>"&#REF!,CX16:DM16,"<>"&#REF!,CX16:DM16,"<>"&#REF!,CX16:DM16,"<>"&#REF!,CX16:DM16,"<>"&#REF!,CX16:DM16,"<>"&#REF!,CX16:DM16,"<>"&#REF!,CX16:DM16,"<>"&#REF!,CX16:DM16,"<>"&#REF!,CX16:DM16,"<>"&#REF!,CX16:DM16,"<>"&#REF!,CX16:DM16,"<>"&#REF!))) | DO16: =IF($J16="",0,IF($J16=1,_xlfn.MINIFS(#REF!,#REF!,">"&0),_xlfn.MINIFS(#REF!,#REF!,">"&0,#REF!,"<>"&#REF!,#REF!,"<>"&#REF!,#REF!,"<>"&#REF!,#REF!,"<>"&#REF!,#REF!,"<>"&#REF!,#REF!,"<>"&#REF!,#REF!,"<>"&#REF!,#REF!,"<>"&#REF!,#REF!,"<>"&#REF!,#REF!,"<>"&#REF!,#REF!,"<>"&#REF!,#REF!,"<>"&#REF!,#REF!,"<>"&#REF!,#REF!,"<>"&#REF!,#REF!,"<>"&#REF!,#REF!,"<>"&#REF!,#REF!,"<>"&#REF!,#REF!,"<>"&#REF!,#REF!,"<>"&#REF!,#REF!,"<>"&#REF!,#REF!,"<>"&#REF!,#REF!,"<>"&#REF!,#REF!,"<>"&#REF!,#REF!,"<>"&#REF!,#REF!,"<>"&#REF!,#REF!,"<>"&#REF!,#REF!,"<>"&#REF!,#REF!,"<>"&#REF!,#REF!,"<>"&#REF!,#REF!,"<>"&#REF!)))
B17: POSTE | C17: Poste de Concreto ou Fibra Simplificado Deflexão máxima 1◦0"00" | D17: SPDA | E17: 3 | F17: 9 | G17: 3 | H17: 45 | I17: VB | K17: NA | L17: =IF(ISTEXT(K17),K17,$J17*K17) | M17: 3906.98 | N17: =IF(ISTEXT(M17),M17,$J17*M17) | O17: N/A | P17: =IF(ISTEXT(O17),O17,$J17*O17) | Q17: n/a | R17: =IF(ISTEXT(Q17),Q17,$J17*Q17) | S17: =IF(ISTEXT(R17),R17,$J17*R17) | T17: =IF(ISTEXT(S17),S17,$J17*S17) | U17: N/A | V17: =IF(ISTEXT(U17),U17,$J17*U17) | W17: N/A | X17: =IF(ISTEXT(W17),W17,$J17*W17) | Z17: NA | AA17: =IF(ISTEXT(Z17),Z17,$J17*Z17) | AB17: NA | AC17: =IF(ISTEXT(AB17),AB17,$J17*AB17) | AD17: 3906.98 | AE17: =IF(ISTEXT(AD17),AD17,$J17*AD17) | AF17: N/A | AG17: =IF(ISTEXT(AF17),AF17,$J17*AF17) | AH17: n/a | AI17: =IF(ISTEXT(AH17),AH17,$J17*AH17) | AJ17: =IF(ISTEXT(AI17),AI17,$J17*AI17) | AK17: =IF(ISTEXT(AJ17),AJ17,$J17*AJ17) | AL17: N/A | AM17: =IF(ISTEXT(AL17),AL17,$J17*AL17) | AN17: N/A | AO17: =IF(ISTEXT(AN17),AN17,$J17*AN17) | AU17: 3906.98 | AV17: =AVERAGE(AZ17,BB17,BD17,BF17,BH17,BJ17,BL17) | AW17: =BASEDADOS[[#This Row],[VL UNIT MÉDIA]]*BASEDADOS[[#This Row],[QTDE]] | AX17: =ROUND(AU17*PARÂMETROS!$B$4,2) | AZ17: NA | BA17: =IF(ISTEXT(AZ17),AZ17,$J17*AZ17) | BB17: 3906.98 | BC17: =IF(ISTEXT(BB17),BB17,$J17*BB17) | BD17: N/A | BE17: =IF(ISTEXT(BD17),BD17,$J17*BD17) | BF17: n/a | BG17: =IF(ISTEXT(BF17),BF17,$J17*BF17) | BH17: =IF(ISTEXT(BG17),BG17,$J17*BG17) | BI17: =IF(ISTEXT(BH17),BH17,$J17*BH17) | BJ17: N/A | BK17: =IF(ISTEXT(BJ17),BJ17,$J17*BJ17) | BL17: N/A | BM17: =IF(ISTEXT(BL17),BL17,$J17*BL17) | BN17: NA | BO17: =IF(ISTEXT(BN17),BN17,$J17*BN17) | BP17: NA | BQ17: =IF(ISTEXT(BP17),BP17,$J17*BP17) | BR17: 3906.98 | BS17: =IF(ISTEXT(BR17),BR17,$J17*BR17) | BT17: N/A | BU17: =IF(ISTEXT(BT17),BT17,$J17*BT17) | BV17: n/a | BW17: =IF(ISTEXT(BV17),BV17,$J17*BV17) | BX17: =IF(ISTEXT(BW17),BW17,$J17*BW17) | BY17: =IF(ISTEXT(BX17),BX17,$J17*BX17) | BZ17: N/A | CA17: =IF(ISTEXT(BZ17),BZ17,$J17*BZ17) | CB17: N/A | CC17: =IF(ISTEXT(CB17),CB17,$J17*CB17) | CD17: =IF($J17="",0,IF($J17=1,_xlfn.MINIFS(BN17:CC17,BN17:CC17,">"&0),_xlfn.MINIFS(BN17:CC17,BN17:CC17,">"&0,BN17:CC17,"<>"&BN17,BN17:CC17,"<>"&BP17,BN17:CC17,"<>"&BR17,BN17:CC17,"<>"&BT17,BN17:CC17,"<>"&BV17,BN17:CC17,"<>"&BX17,BN17:CC17,"<>"&BZ17,BN17:CC17,"<>"&CB17,BN17:CC17,"<>"&#REF!,BN17:CC17,"<>"&#REF!,BN17:CC17,"<>"&#REF!,BN17:CC17,"<>"&#REF!,BN17:CC17,"<>"&#REF!,BN17:CC17,"<>"&#REF!,BN17:CC17,"<>"&#REF!,BN17:CC17,"<>"&#REF!,BN17:CC17,"<>"&#REF!,BN17:CC17,"<>"&#REF!,BN17:CC17,"<>"&#REF!,BN17:CC17,"<>"&#REF!,BN17:CC17,"<>"&#REF!,BN17:CC17,"<>"&#REF!,BN17:CC17,"<>"&#REF!,BN17:CC17,"<>"&#REF!,BN17:CC17,"<>"&#REF!,BN17:CC17,"<>"&#REF!,BN17:CC17,"<>"&#REF!,BN17:CC17,"<>"&#REF!,BN17:CC17,"<>"&#REF!,BN17:CC17,"<>"&#REF!))) | CF17: NA | CG17: =IF(ISTEXT(CF17),CF17,$J17*CF17) | CH17: NA | CI17: =IF(ISTEXT(CH17),CH17,$J17*CH17) | CJ17: 3906.98 | CK17: =IF(ISTEXT(CJ17),CJ17,$J17*CJ17) | CL17: N/A | CM17: =IF(ISTEXT(CL17),CL17,$J17*CL17) | CN17: n/a | CO17: =IF(ISTEXT(CN17),CN17,$J17*CN17) | CP17: =IF(ISTEXT(CO17),CO17,$J17*CO17) | CQ17: =IF(ISTEXT(CP17),CP17,$J17*CP17) | CR17: N/A | CS17: =IF(ISTEXT(CR17),CR17,$J17*CR17) | CT17: N/A | CU17: =IF(ISTEXT(CT17),CT17,$J17*CT17) | CV17: =IF($J17="",0,IF($J17=1,_xlfn.MINIFS(CF17:CU17,CF17:CU17,">"&0),_xlfn.MINIFS(CF17:CU17,CF17:CU17,">"&0,CF17:CU17,"<>"&CF17,CF17:CU17,"<>"&CH17,CF17:CU17,"<>"&CJ17,CF17:CU17,"<>"&CL17,CF17:CU17,"<>"&CN17,CF17:CU17,"<>"&CP17,CF17:CU17,"<>"&CR17,CF17:CU17,"<>"&CT17,CF17:CU17,"<>"&#REF!,CF17:CU17,"<>"&#REF!,CF17:CU17,"<>"&#REF!,CF17:CU17,"<>"&#REF!,CF17:CU17,"<>"&#REF!,CF17:CU17,"<>"&#REF!,CF17:CU17,"<>"&#REF!,CF17:CU17,"<>"&#REF!,CF17:CU17,"<>"&#REF!,CF17:CU17,"<>"&#REF!,CF17:CU17,"<>"&#REF!,CF17:CU17,"<>"&#REF!,CF17:CU17,"<>"&#REF!,CF17:CU17,"<>"&#REF!,CF17:CU17,"<>"&#REF!,CF17:CU17,"<>"&#REF!,CF17:CU17,"<>"&#REF!,CF17:CU17,"<>"&#REF!,CF17:CU17,"<>"&#REF!,CF17:CU17,"<>"&#REF!,CF17:CU17,"<>"&#REF!,CF17:CU17,"<>"&#REF!))) | CX17: NA | CY17: =IF(ISTEXT(CX17),CX17,$J17*CX17) | CZ17: NA | DA17: =IF(ISTEXT(CZ17),CZ17,$J17*CZ17) | DB17: 3906.98 | DC17: =IF(ISTEXT(DB17),DB17,$J17*DB17) | DD17: N/A | DE17: =IF(ISTEXT(DD17),DD17,$J17*DD17) | DF17: n/a | DG17: =IF(ISTEXT(DF17),DF17,$J17*DF17) | DH17: =IF(ISTEXT(DG17),DG17,$J17*DG17) | DI17: =IF(ISTEXT(DH17),DH17,$J17*DH17) | DJ17: N/A | DK17: =IF(ISTEXT(DJ17),DJ17,$J17*DJ17) | DL17: N/A | DM17: =IF(ISTEXT(DL17),DL17,$J17*DL17) | DN17: =IF($J17="",0,IF($J17=1,_xlfn.MINIFS(CX17:DM17,CX17:DM17,">"&0),_xlfn.MINIFS(CX17:DM17,CX17:DM17,">"&0,CX17:DM17,"<>"&CX17,CX17:DM17,"<>"&CZ17,CX17:DM17,"<>"&DB17,CX17:DM17,"<>"&DD17,CX17:DM17,"<>"&DF17,CX17:DM17,"<>"&DH17,CX17:DM17,"<>"&DJ17,CX17:DM17,"<>"&DL17,CX17:DM17,"<>"&#REF!,CX17:DM17,"<>"&#REF!,CX17:DM17,"<>"&#REF!,CX17:DM17,"<>"&#REF!,CX17:DM17,"<>"&#REF!,CX17:DM17,"<>"&#REF!,CX17:DM17,"<>"&#REF!,CX17:DM17,"<>"&#REF!,CX17:DM17,"<>"&#REF!,CX17:DM17,"<>"&#REF!,CX17:DM17,"<>"&#REF!,CX17:DM17,"<>"&#REF!,CX17:DM17,"<>"&#REF!,CX17:DM17,"<>"&#REF!,CX17:DM17,"<>"&#REF!,CX17:DM17,"<>"&#REF!,CX17:DM17,"<>"&#REF!,CX17:DM17,"<>"&#REF!,CX17:DM17,"<>"&#REF!,CX17:DM17,"<>"&#REF!,CX17:DM17,"<>"&#REF!,CX17:DM17,"<>"&#REF!))) | DO17: =IF($J17="",0,IF($J17=1,_xlfn.MINIFS(#REF!,#REF!,">"&0),_xlfn.MINIFS(#REF!,#REF!,">"&0,#REF!,"<>"&#REF!,#REF!,"<>"&#REF!,#REF!,"<>"&#REF!,#REF!,"<>"&#REF!,#REF!,"<>"&#REF!,#REF!,"<>"&#REF!,#REF!,"<>"&#REF!,#REF!,"<>"&#REF!,#REF!,"<>"&#REF!,#REF!,"<>"&#REF!,#REF!,"<>"&#REF!,#REF!,"<>"&#REF!,#REF!,"<>"&#REF!,#REF!,"<>"&#REF!,#REF!,"<>"&#REF!,#REF!,"<>"&#REF!,#REF!,"<>"&#REF!,#REF!,"<>"&#REF!,#REF!,"<>"&#REF!,#REF!,"<>"&#REF!,#REF!,"<>"&#REF!,#REF!,"<>"&#REF!,#REF!,"<>"&#REF!,#REF!,"<>"&#REF!,#REF!,"<>"&#REF!,#REF!,"<>"&#REF!,#REF!,"<>"&#REF!,#REF!,"<>"&#REF!,#REF!,"<>"&#REF!,#REF!,"<>"&#REF!)))
B18: POSTE | C18: Poste de Concreto ou Fibra Simplificado Deflexão máxima 1◦0"00" | E18: 4 | F18: 9 | G18: 4 | H18: 30 | I18: VB | K18: NA | L18: =IF(ISTEXT(K18),K18,$J18*K18) | M18: 3881.25 | N18: =IF(ISTEXT(M18),M18,$J18*M18) | O18: N/A | P18: =IF(ISTEXT(O18),O18,$J18*O18) | Q18: n/a | R18: =IF(ISTEXT(Q18),Q18,$J18*Q18) | S18: =IF(ISTEXT(R18),R18,$J18*R18) | T18: =IF(ISTEXT(S18),S18,$J18*S18) | U18: N/A | V18: =IF(ISTEXT(U18),U18,$J18*U18) | W18: N/A | X18: =IF(ISTEXT(W18),W18,$J18*W18) | Z18: NA | AA18: =IF(ISTEXT(Z18),Z18,$J18*Z18) | AB18: NA | AC18: =IF(ISTEXT(AB18),AB18,$J18*AB18) | AD18: 3881.25 | AE18: =IF(ISTEXT(AD18),AD18,$J18*AD18) | AF18: N/A | AG18: =IF(ISTEXT(AF18),AF18,$J18*AF18) | AH18: n/a | AI18: =IF(ISTEXT(AH18),AH18,$J18*AH18) | AJ18: =IF(ISTEXT(AI18),AI18,$J18*AI18) | AK18: =IF(ISTEXT(AJ18),AJ18,$J18*AJ18) | AL18: N/A | AM18: =IF(ISTEXT(AL18),AL18,$J18*AL18) | AN18: N/A | AO18: =IF(ISTEXT(AN18),AN18,$J18*AN18) | AU18: 3881.25 | AV18: =AVERAGE(AZ18,BB18,BD18,BF18,BH18,BJ18,BL18) | AW18: =BASEDADOS[[#This Row],[VL UNIT MÉDIA]]*BASEDADOS[[#This Row],[QTDE]] | AX18: =ROUND(AU18*PARÂMETROS!$B$4,2) | AZ18: NA | BA18: =IF(ISTEXT(AZ18),AZ18,$J18*AZ18) | BB18: 3881.25 | BC18: =IF(ISTEXT(BB18),BB18,$J18*BB18) | BD18: N/A | BE18: =IF(ISTEXT(BD18),BD18,$J18*BD18) | BF18: n/a | BG18: =IF(ISTEXT(BF18),BF18,$J18*BF18) | BH18: =IF(ISTEXT(BG18),BG18,$J18*BG18) | BI18: =IF(ISTEXT(BH18),BH18,$J18*BH18) | BJ18: N/A | BK18: =IF(ISTEXT(BJ18),BJ18,$J18*BJ18) | BL18: N/A | BM18: =IF(ISTEXT(BL18),BL18,$J18*BL18) | BN18: NA | BO18: =IF(ISTEXT(BN18),BN18,$J18*BN18) | BP18: NA | BQ18: =IF(ISTEXT(BP18),BP18,$J18*BP18) | BR18: 3881.25 | BS18: =IF(ISTEXT(BR18),BR18,$J18*BR18) | BT18: N/A | BU18: =IF(ISTEXT(BT18),BT18,$J18*BT18) | BV18: n/a | BW18: =IF(ISTEXT(BV18),BV18,$J18*BV18) | BX18: =IF(ISTEXT(BW18),BW18,$J18*BW18) | BY18: =IF(ISTEXT(BX18),BX18,$J18*BX18) | BZ18: N/A | CA18: =IF(ISTEXT(BZ18),BZ18,$J18*BZ18) | CB18: N/A | CC18: =IF(ISTEXT(CB18),CB18,$J18*CB18) | CD18: =IF($J18="",0,IF($J18=1,_xlfn.MINIFS(BN18:CC18,BN18:CC18,">"&0),_xlfn.MINIFS(BN18:CC18,BN18:CC18,">"&0,BN18:CC18,"<>"&BN18,BN18:CC18,"<>"&BP18,BN18:CC18,"<>"&BR18,BN18:CC18,"<>"&BT18,BN18:CC18,"<>"&BV18,BN18:CC18,"<>"&BX18,BN18:CC18,"<>"&BZ18,BN18:CC18,"<>"&CB18,BN18:CC18,"<>"&#REF!,BN18:CC18,"<>"&#REF!,BN18:CC18,"<>"&#REF!,BN18:CC18,"<>"&#REF!,BN18:CC18,"<>"&#REF!,BN18:CC18,"<>"&#REF!,BN18:CC18,"<>"&#REF!,BN18:CC18,"<>"&#REF!,BN18:CC18,"<>"&#REF!,BN18:CC18,"<>"&#REF!,BN18:CC18,"<>"&#REF!,BN18:CC18,"<>"&#REF!,BN18:CC18,"<>"&#REF!,BN18:CC18,"<>"&#REF!,BN18:CC18,"<>"&#REF!,BN18:CC18,"<>"&#REF!,BN18:CC18,"<>"&#REF!,BN18:CC18,"<>"&#REF!,BN18:CC18,"<>"&#REF!,BN18:CC18,"<>"&#REF!,BN18:CC18,"<>"&#REF!,BN18:CC18,"<>"&#REF!))) | CF18: NA | CG18: =IF(ISTEXT(CF18),CF18,$J18*CF18) | CH18: NA | CI18: =IF(ISTEXT(CH18),CH18,$J18*CH18) | CJ18: 3881.25 | CK18: =IF(ISTEXT(CJ18),CJ18,$J18*CJ18) | CL18: N/A | CM18: =IF(ISTEXT(CL18),CL18,$J18*CL18) | CN18: n/a | CO18: =IF(ISTEXT(CN18),CN18,$J18*CN18) | CP18: =IF(ISTEXT(CO18),CO18,$J18*CO18) | CQ18: =IF(ISTEXT(CP18),CP18,$J18*CP18) | CR18: N/A | CS18: =IF(ISTEXT(CR18),CR18,$J18*CR18) | CT18: N/A | CU18: =IF(ISTEXT(CT18),CT18,$J18*CT18) | CV18: =IF($J18="",0,IF($J18=1,_xlfn.MINIFS(CF18:CU18,CF18:CU18,">"&0),_xlfn.MINIFS(CF18:CU18,CF18:CU18,">"&0,CF18:CU18,"<>"&CF18,CF18:CU18,"<>"&CH18,CF18:CU18,"<>"&CJ18,CF18:CU18,"<>"&CL18,CF18:CU18,"<>"&CN18,CF18:CU18,"<>"&CP18,CF18:CU18,"<>"&CR18,CF18:CU18,"<>"&CT18,CF18:CU18,"<>"&#REF!,CF18:CU18,"<>"&#REF!,CF18:CU18,"<>"&#REF!,CF18:CU18,"<>"&#REF!,CF18:CU18,"<>"&#REF!,CF18:CU18,"<>"&#REF!,CF18:CU18,"<>"&#REF!,CF18:CU18,"<>"&#REF!,CF18:CU18,"<>"&#REF!,CF18:CU18,"<>"&#REF!,CF18:CU18,"<>"&#REF!,CF18:CU18,"<>"&#REF!,CF18:CU18,"<>"&#REF!,CF18:CU18,"<>"&#REF!,CF18:CU18,"<>"&#REF!,CF18:CU18,"<>"&#REF!,CF18:CU18,"<>"&#REF!,CF18:CU18,"<>"&#REF!,CF18:CU18,"<>"&#REF!,CF18:CU18,"<>"&#REF!,CF18:CU18,"<>"&#REF!,CF18:CU18,"<>"&#REF!))) | CX18: NA | CY18: =IF(ISTEXT(CX18),CX18,$J18*CX18) | CZ18: NA | DA18: =IF(ISTEXT(CZ18),CZ18,$J18*CZ18) | DB18: 3881.25 | DC18: =IF(ISTEXT(DB18),DB18,$J18*DB18) | DD18: N/A | DE18: =IF(ISTEXT(DD18),DD18,$J18*DD18) | DF18: n/a | DG18: =IF(ISTEXT(DF18),DF18,$J18*DF18) | DH18: =IF(ISTEXT(DG18),DG18,$J18*DG18) | DI18: =IF(ISTEXT(DH18),DH18,$J18*DH18) | DJ18: N/A | DK18: =IF(ISTEXT(DJ18),DJ18,$J18*DJ18) | DL18: N/A | DM18: =IF(ISTEXT(DL18),DL18,$J18*DL18) | DN18: =IF($J18="",0,IF($J18=1,_xlfn.MINIFS(CX18:DM18,CX18:DM18,">"&0),_xlfn.MINIFS(CX18:DM18,CX18:DM18,">"&0,CX18:DM18,"<>"&CX18,CX18:DM18,"<>"&CZ18,CX18:DM18,"<>"&DB18,CX18:DM18,"<>"&DD18,CX18:DM18,"<>"&DF18,CX18:DM18,"<>"&DH18,CX18:DM18,"<>"&DJ18,CX18:DM18,"<>"&DL18,CX18:DM18,"<>"&#REF!,CX18:DM18,"<>"&#REF!,CX18:DM18,"<>"&#REF!,CX18:DM18,"<>"&#REF!,CX18:DM18,"<>"&#REF!,CX18:DM18,"<>"&#REF!,CX18:DM18,"<>"&#REF!,CX18:DM18,"<>"&#REF!,CX18:DM18,"<>"&#REF!,CX18:DM18,"<>"&#REF!,CX18:DM18,"<>"&#REF!,CX18:DM18,"<>"&#REF!,CX18:DM18,"<>"&#REF!,CX18:DM18,"<>"&#REF!,CX18:DM18,"<>"&#REF!,CX18:DM18,"<>"&#REF!,CX18:DM18,"<>"&#REF!,CX18:DM18,"<>"&#REF!,CX18:DM18,"<>"&#REF!,CX18:DM18,"<>"&#REF!,CX18:DM18,"<>"&#REF!,CX18:DM18,"<>"&#REF!))) | DO18: =IF($J18="",0,IF($J18=1,_xlfn.MINIFS(#REF!,#REF!,">"&0),_xlfn.MINIFS(#REF!,#REF!,">"&0,#REF!,"<>"&#REF!,#REF!,"<>"&#REF!,#REF!,"<>"&#REF!,#REF!,"<>"&#REF!,#REF!,"<>"&#REF!,#REF!,"<>"&#REF!,#REF!,"<>"&#REF!,#REF!,"<>"&#REF!,#REF!,"<>"&#REF!,#REF!,"<>"&#REF!,#REF!,"<>"&#REF!,#REF!,"<>"&#REF!,#REF!,"<>"&#REF!,#REF!,"<>"&#REF!,#REF!,"<>"&#REF!,#REF!,"<>"&#REF!,#REF!,"<>"&#REF!,#REF!,"<>"&#REF!,#REF!,"<>"&#REF!,#REF!,"<>"&#REF!,#REF!,"<>"&#REF!,#REF!,"<>"&#REF!,#REF!,"<>"&#REF!,#REF!,"<>"&#REF!,#REF!,"<>"&#REF!,#REF!,"<>"&#REF!,#REF!,"<>"&#REF!,#REF!,"<>"&#REF!,#REF!,"<>"&#REF!,#REF!,"<>"&#REF!)))
B19: POSTE | C19: Poste de Concreto ou Fibra Simplificado Deflexão máxima 1◦0"00" | D19: Escada EV > 30m | E19: 4 | F19: 9 | G19: 4 | H19: 35 | I19: VB | K19: NA | L19: =IF(ISTEXT(K19),K19,$J19*K19) | M19: 4075.31 | N19: =IF(ISTEXT(M19),M19,$J19*M19) | O19: N/A | P19: =IF(ISTEXT(O19),O19,$J19*O19) | Q19: n/a | R19: =IF(ISTEXT(Q19),Q19,$J19*Q19) | S19: =IF(ISTEXT(R19),R19,$J19*R19) | T19: =IF(ISTEXT(S19),S19,$J19*S19) | U19: N/A | V19: =IF(ISTEXT(U19),U19,$J19*U19) | W19: N/A | X19: =IF(ISTEXT(W19),W19,$J19*W19) | Z19: NA | AA19: =IF(ISTEXT(Z19),Z19,$J19*Z19) | AB19: NA | AC19: =IF(ISTEXT(AB19),AB19,$J19*AB19) | AD19: 4075.31 | AE19: =IF(ISTEXT(AD19),AD19,$J19*AD19) | AF19: N/A | AG19: =IF(ISTEXT(AF19),AF19,$J19*AF19) | AH19: n/a | AI19: =IF(ISTEXT(AH19),AH19,$J19*AH19) | AJ19: =IF(ISTEXT(AI19),AI19,$J19*AI19) | AK19: =IF(ISTEXT(AJ19),AJ19,$J19*AJ19) | AL19: N/A | AM19: =IF(ISTEXT(AL19),AL19,$J19*AL19) | AN19: N/A | AO19: =IF(ISTEXT(AN19),AN19,$J19*AN19) | AU19: 4075.31 | AV19: =AVERAGE(AZ19,BB19,BD19,BF19,BH19,BJ19,BL19) | AW19: =BASEDADOS[[#This Row],[VL UNIT MÉDIA]]*BASEDADOS[[#This Row],[QTDE]] | AX19: =ROUND(AU19*PARÂMETROS!$B$4,2) | AZ19: NA | BA19: =IF(ISTEXT(AZ19),AZ19,$J19*AZ19) | BB19: 4075.31 | BC19: =IF(ISTEXT(BB19),BB19,$J19*BB19) | BD19: N/A | BE19: =IF(ISTEXT(BD19),BD19,$J19*BD19) | BF19: n/a | BG19: =IF(ISTEXT(BF19),BF19,$J19*BF19) | BH19: =IF(ISTEXT(BG19),BG19,$J19*BG19) | BI19: =IF(ISTEXT(BH19),BH19,$J19*BH19) | BJ19: N/A | BK19: =IF(ISTEXT(BJ19),BJ19,$J19*BJ19) | BL19: N/A | BM19: =IF(ISTEXT(BL19),BL19,$J19*BL19) | BN19: NA | BO19: =IF(ISTEXT(BN19),BN19,$J19*BN19) | BP19: NA | BQ19: =IF(ISTEXT(BP19),BP19,$J19*BP19) | BR19: 4075.31 | BS19: =IF(ISTEXT(BR19),BR19,$J19*BR19) | BT19: N/A | BU19: =IF(ISTEXT(BT19),BT19,$J19*BT19) | BV19: n/a | BW19: =IF(ISTEXT(BV19),BV19,$J19*BV19) | BX19: =IF(ISTEXT(BW19),BW19,$J19*BW19) | BY19: =IF(ISTEXT(BX19),BX19,$J19*BX19) | BZ19: N/A | CA19: =IF(ISTEXT(BZ19),BZ19,$J19*BZ19) | CB19: N/A | CC19: =IF(ISTEXT(CB19),CB19,$J19*CB19) | CD19: =IF($J19="",0,IF($J19=1,_xlfn.MINIFS(BN19:CC19,BN19:CC19,">"&0),_xlfn.MINIFS(BN19:CC19,BN19:CC19,">"&0,BN19:CC19,"<>"&BN19,BN19:CC19,"<>"&BP19,BN19:CC19,"<>"&BR19,BN19:CC19,"<>"&BT19,BN19:CC19,"<>"&BV19,BN19:CC19,"<>"&BX19,BN19:CC19,"<>"&BZ19,BN19:CC19,"<>"&CB19,BN19:CC19,"<>"&#REF!,BN19:CC19,"<>"&#REF!,BN19:CC19,"<>"&#REF!,BN19:CC19,"<>"&#REF!,BN19:CC19,"<>"&#REF!,BN19:CC19,"<>"&#REF!,BN19:CC19,"<>"&#REF!,BN19:CC19,"<>"&#REF!,BN19:CC19,"<>"&#REF!,BN19:CC19,"<>"&#REF!,BN19:CC19,"<>"&#REF!,BN19:CC19,"<>"&#REF!,BN19:CC19,"<>"&#REF!,BN19:CC19,"<>"&#REF!,BN19:CC19,"<>"&#REF!,BN19:CC19,"<>"&#REF!,BN19:CC19,"<>"&#REF!,BN19:CC19,"<>"&#REF!,BN19:CC19,"<>"&#REF!,BN19:CC19,"<>"&#REF!,BN19:CC19,"<>"&#REF!,BN19:CC19,"<>"&#REF!))) | CF19: NA | CG19: =IF(ISTEXT(CF19),CF19,$J19*CF19) | CH19: NA | CI19: =IF(ISTEXT(CH19),CH19,$J19*CH19) | CJ19: 4075.31 | CK19: =IF(ISTEXT(CJ19),CJ19,$J19*CJ19) | CL19: N/A | CM19: =IF(ISTEXT(CL19),CL19,$J19*CL19) | CN19: n/a | CO19: =IF(ISTEXT(CN19),CN19,$J19*CN19) | CP19: =IF(ISTEXT(CO19),CO19,$J19*CO19) | CQ19: =IF(ISTEXT(CP19),CP19,$J19*CP19) | CR19: N/A | CS19: =IF(ISTEXT(CR19),CR19,$J19*CR19) | CT19: N/A | CU19: =IF(ISTEXT(CT19),CT19,$J19*CT19) | CV19: =IF($J19="",0,IF($J19=1,_xlfn.MINIFS(CF19:CU19,CF19:CU19,">"&0),_xlfn.MINIFS(CF19:CU19,CF19:CU19,">"&0,CF19:CU19,"<>"&CF19,CF19:CU19,"<>"&CH19,CF19:CU19,"<>"&CJ19,CF19:CU19,"<>"&CL19,CF19:CU19,"<>"&CN19,CF19:CU19,"<>"&CP19,CF19:CU19,"<>"&CR19,CF19:CU19,"<>"&CT19,CF19:CU19,"<>"&#REF!,CF19:CU19,"<>"&#REF!,CF19:CU19,"<>"&#REF!,CF19:CU19,"<>"&#REF!,CF19:CU19,"<>"&#REF!,CF19:CU19,"<>"&#REF!,CF19:CU19,"<>"&#REF!,CF19:CU19,"<>"&#REF!,CF19:CU19,"<>"&#REF!,CF19:CU19,"<>"&#REF!,CF19:CU19,"<>"&#REF!,CF19:CU19,"<>"&#REF!,CF19:CU19,"<>"&#REF!,CF19:CU19,"<>"&#REF!,CF19:CU19,"<>"&#REF!,CF19:CU19,"<>"&#REF!,CF19:CU19,"<>"&#REF!,CF19:CU19,"<>"&#REF!,CF19:CU19,"<>"&#REF!,CF19:CU19,"<>"&#REF!,CF19:CU19,"<>"&#REF!,CF19:CU19,"<>"&#REF!))) | CX19: NA | CY19: =IF(ISTEXT(CX19),CX19,$J19*CX19) | CZ19: NA | DA19: =IF(ISTEXT(CZ19),CZ19,$J19*CZ19) | DB19: 4075.31 | DC19: =IF(ISTEXT(DB19),DB19,$J19*DB19) | DD19: N/A | DE19: =IF(ISTEXT(DD19),DD19,$J19*DD19) | DF19: n/a | DG19: =IF(ISTEXT(DF19),DF19,$J19*DF19) | DH19: =IF(ISTEXT(DG19),DG19,$J19*DG19) | DI19: =IF(ISTEXT(DH19),DH19,$J19*DH19) | DJ19: N/A | DK19: =IF(ISTEXT(DJ19),DJ19,$J19*DJ19) | DL19: N/A | DM19: =IF(ISTEXT(DL19),DL19,$J19*DL19) | DN19: =IF($J19="",0,IF($J19=1,_xlfn.MINIFS(CX19:DM19,CX19:DM19,">"&0),_xlfn.MINIFS(CX19:DM19,CX19:DM19,">"&0,CX19:DM19,"<>"&CX19,CX19:DM19,"<>"&CZ19,CX19:DM19,"<>"&DB19,CX19:DM19,"<>"&DD19,CX19:DM19,"<>"&DF19,CX19:DM19,"<>"&DH19,CX19:DM19,"<>"&DJ19,CX19:DM19,"<>"&DL19,CX19:DM19,"<>"&#REF!,CX19:DM19,"<>"&#REF!,CX19:DM19,"<>"&#REF!,CX19:DM19,"<>"&#REF!,CX19:DM19,"<>"&#REF!,CX19:DM19,"<>"&#REF!,CX19:DM19,"<>"&#REF!,CX19:DM19,"<>"&#REF!,CX19:DM19,"<>"&#REF!,CX19:DM19,"<>"&#REF!,CX19:DM19,"<>"&#REF!,CX19:DM19,"<>"&#REF!,CX19:DM19,"<>"&#REF!,CX19:DM19,"<>"&#REF!,CX19:DM19,"<>"&#REF!,CX19:DM19,"<>"&#REF!,CX19:DM19,"<>"&#REF!,CX19:DM19,"<>"&#REF!,CX19:DM19,"<>"&#REF!,CX19:DM19,"<>"&#REF!,CX19:DM19,"<>"&#REF!,CX19:DM19,"<>"&#REF!))) | DO19: =IF($J19="",0,IF($J19=1,_xlfn.MINIFS(#REF!,#REF!,">"&0),_xlfn.MINIFS(#REF!,#REF!,">"&0,#REF!,"<>"&#REF!,#REF!,"<>"&#REF!,#REF!,"<>"&#REF!,#REF!,"<>"&#REF!,#REF!,"<>"&#REF!,#REF!,"<>"&#REF!,#REF!,"<>"&#REF!,#REF!,"<>"&#REF!,#REF!,"<>"&#REF!,#REF!,"<>"&#REF!,#REF!,"<>"&#REF!,#REF!,"<>"&#REF!,#REF!,"<>"&#REF!,#REF!,"<>"&#REF!,#REF!,"<>"&#REF!,#REF!,"<>"&#REF!,#REF!,"<>"&#REF!,#REF!,"<>"&#REF!,#REF!,"<>"&#REF!,#REF!,"<>"&#REF!,#REF!,"<>"&#REF!,#REF!,"<>"&#REF!,#REF!,"<>"&#REF!,#REF!,"<>"&#REF!,#REF!,"<>"&#REF!,#REF!,"<>"&#REF!,#REF!,"<>"&#REF!,#REF!,"<>"&#REF!,#REF!,"<>"&#REF!,#REF!,"<>"&#REF!)))
B20: POSTE | C20: Poste de Concreto ou Fibra Simplificado Deflexão máxima 1◦0"00" | D20: Trava quedas | E20: 4 | F20: 9 | G20: 4 | H20: 40 | I20: VB | K20: NA | L20: =IF(ISTEXT(K20),K20,$J20*K20) | M20: 4279.08 | N20: =IF(ISTEXT(M20),M20,$J20*M20) | O20: N/A | P20: =IF(ISTEXT(O20),O20,$J20*O20) | Q20: n/a | R20: =IF(ISTEXT(Q20),Q20,$J20*Q20) | S20: =IF(ISTEXT(R20),R20,$J20*R20) | T20: =IF(ISTEXT(S20),S20,$J20*S20) | U20: N/A | V20: =IF(ISTEXT(U20),U20,$J20*U20) | W20: N/A | X20: =IF(ISTEXT(W20),W20,$J20*W20) | Z20: NA | AA20: =IF(ISTEXT(Z20),Z20,$J20*Z20) | AB20: NA | AC20: =IF(ISTEXT(AB20),AB20,$J20*AB20) | AD20: 4279.08 | AE20: =IF(ISTEXT(AD20),AD20,$J20*AD20) | AF20: N/A | AG20: =IF(ISTEXT(AF20),AF20,$J20*AF20) | AH20: n/a | AI20: =IF(ISTEXT(AH20),AH20,$J20*AH20) | AJ20: =IF(ISTEXT(AI20),AI20,$J20*AI20) | AK20: =IF(ISTEXT(AJ20),AJ20,$J20*AJ20) | AL20: N/A | AM20: =IF(ISTEXT(AL20),AL20,$J20*AL20) | AN20: N/A | AO20: =IF(ISTEXT(AN20),AN20,$J20*AN20) | AU20: 4279.08 | AV20: =AVERAGE(AZ20,BB20,BD20,BF20,BH20,BJ20,BL20) | AW20: =BASEDADOS[[#This Row],[VL UNIT MÉDIA]]*BASEDADOS[[#This Row],[QTDE]] | AX20: =ROUND(AU20*PARÂMETROS!$B$4,2) | AZ20: NA | BA20: =IF(ISTEXT(AZ20),AZ20,$J20*AZ20) | BB20: 4279.08 | BC20: =IF(ISTEXT(BB20),BB20,$J20*BB20) | BD20: N/A | BE20: =IF(ISTEXT(BD20),BD20,$J20*BD20) | BF20: n/a | BG20: =IF(ISTEXT(BF20),BF20,$J20*BF20) | BH20: =IF(ISTEXT(BG20),BG20,$J20*BG20) | BI20: =IF(ISTEXT(BH20),BH20,$J20*BH20) | BJ20: N/A | BK20: =IF(ISTEXT(BJ20),BJ20,$J20*BJ20) | BL20: N/A | BM20: =IF(ISTEXT(BL20),BL20,$J20*BL20) | BN20: NA | BO20: =IF(ISTEXT(BN20),BN20,$J20*BN20) | BP20: NA | BQ20: =IF(ISTEXT(BP20),BP20,$J20*BP20) | BR20: 4279.08 | BS20: =IF(ISTEXT(BR20),BR20,$J20*BR20) | BT20: N/A | BU20: =IF(ISTEXT(BT20),BT20,$J20*BT20) | BV20: n/a | BW20: =IF(ISTEXT(BV20),BV20,$J20*BV20) | BX20: =IF(ISTEXT(BW20),BW20,$J20*BW20) | BY20: =IF(ISTEXT(BX20),BX20,$J20*BX20) | BZ20: N/A | CA20: =IF(ISTEXT(BZ20),BZ20,$J20*BZ20) | CB20: N/A | CC20: =IF(ISTEXT(CB20),CB20,$J20*CB20) | CD20: =IF($J20="",0,IF($J20=1,_xlfn.MINIFS(BN20:CC20,BN20:CC20,">"&0),_xlfn.MINIFS(BN20:CC20,BN20:CC20,">"&0,BN20:CC20,"<>"&BN20,BN20:CC20,"<>"&BP20,BN20:CC20,"<>"&BR20,BN20:CC20,"<>"&BT20,BN20:CC20,"<>"&BV20,BN20:CC20,"<>"&BX20,BN20:CC20,"<>"&BZ20,BN20:CC20,"<>"&CB20,BN20:CC20,"<>"&#REF!,BN20:CC20,"<>"&#REF!,BN20:CC20,"<>"&#REF!,BN20:CC20,"<>"&#REF!,BN20:CC20,"<>"&#REF!,BN20:CC20,"<>"&#REF!,BN20:CC20,"<>"&#REF!,BN20:CC20,"<>"&#REF!,BN20:CC20,"<>"&#REF!,BN20:CC20,"<>"&#REF!,BN20:CC20,"<>"&#REF!,BN20:CC20,"<>"&#REF!,BN20:CC20,"<>"&#REF!,BN20:CC20,"<>"&#REF!,BN20:CC20,"<>"&#REF!,BN20:CC20,"<>"&#REF!,BN20:CC20,"<>"&#REF!,BN20:CC20,"<>"&#REF!,BN20:CC20,"<>"&#REF!,BN20:CC20,"<>"&#REF!,BN20:CC20,"<>"&#REF!,BN20:CC20,"<>"&#REF!))) | CF20: NA | CG20: =IF(ISTEXT(CF20),CF20,$J20*CF20) | CH20: NA | CI20: =IF(ISTEXT(CH20),CH20,$J20*CH20) | CJ20: 4279.08 | CK20: =IF(ISTEXT(CJ20),CJ20,$J20*CJ20) | CL20: N/A | CM20: =IF(ISTEXT(CL20),CL20,$J20*CL20) | CN20: n/a | CO20: =IF(ISTEXT(CN20),CN20,$J20*CN20) | CP20: =IF(ISTEXT(CO20),CO20,$J20*CO20) | CQ20: =IF(ISTEXT(CP20),CP20,$J20*CP20) | CR20: N/A | CS20: =IF(ISTEXT(CR20),CR20,$J20*CR20) | CT20: N/A | CU20: =IF(ISTEXT(CT20),CT20,$J20*CT20) | CV20: =IF($J20="",0,IF($J20=1,_xlfn.MINIFS(CF20:CU20,CF20:CU20,">"&0),_xlfn.MINIFS(CF20:CU20,CF20:CU20,">"&0,CF20:CU20,"<>"&CF20,CF20:CU20,"<>"&CH20,CF20:CU20,"<>"&CJ20,CF20:CU20,"<>"&CL20,CF20:CU20,"<>"&CN20,CF20:CU20,"<>"&CP20,CF20:CU20,"<>"&CR20,CF20:CU20,"<>"&CT20,CF20:CU20,"<>"&#REF!,CF20:CU20,"<>"&#REF!,CF20:CU20,"<>"&#REF!,CF20:CU20,"<>"&#REF!,CF20:CU20,"<>"&#REF!,CF20:CU20,"<>"&#REF!,CF20:CU20,"<>"&#REF!,CF20:CU20,"<>"&#REF!,CF20:CU20,"<>"&#REF!,CF20:CU20,"<>"&#REF!,CF20:CU20,"<>"&#REF!,CF20:CU20,"<>"&#REF!,CF20:CU20,"<>"&#REF!,CF20:CU20,"<>"&#REF!,CF20:CU20,"<>"&#REF!,CF20:CU20,"<>"&#REF!,CF20:CU20,"<>"&#REF!,CF20:CU20,"<>"&#REF!,CF20:CU20,"<>"&#REF!,CF20:CU20,"<>"&#REF!,CF20:CU20,"<>"&#REF!,CF20:CU20,"<>"&#REF!))) | CX20: NA | CY20: =IF(ISTEXT(CX20),CX20,$J20*CX20) | CZ20: NA | DA20: =IF(ISTEXT(CZ20),CZ20,$J20*CZ20) | DB20: 4279.08 | DC20: =IF(ISTEXT(DB20),DB20,$J20*DB20) | DD20: N/A | DE20: =IF(ISTEXT(DD20),DD20,$J20*DD20) | DF20: n/a | DG20: =IF(ISTEXT(DF20),DF20,$J20*DF20) | DH20: =IF(ISTEXT(DG20),DG20,$J20*DG20) | DI20: =IF(ISTEXT(DH20),DH20,$J20*DH20) | DJ20: N/A | DK20: =IF(ISTEXT(DJ20),DJ20,$J20*DJ20) | DL20: N/A | DM20: =IF(ISTEXT(DL20),DL20,$J20*DL20) | DN20: =IF($J20="",0,IF($J20=1,_xlfn.MINIFS(CX20:DM20,CX20:DM20,">"&0),_xlfn.MINIFS(CX20:DM20,CX20:DM20,">"&0,CX20:DM20,"<>"&CX20,CX20:DM20,"<>"&CZ20,CX20:DM20,"<>"&DB20,CX20:DM20,"<>"&DD20,CX20:DM20,"<>"&DF20,CX20:DM20,"<>"&DH20,CX20:DM20,"<>"&DJ20,CX20:DM20,"<>"&DL20,CX20:DM20,"<>"&#REF!,CX20:DM20,"<>"&#REF!,CX20:DM20,"<>"&#REF!,CX20:DM20,"<>"&#REF!,CX20:DM20,"<>"&#REF!,CX20:DM20,"<>"&#REF!,CX20:DM20,"<>"&#REF!,CX20:DM20,"<>"&#REF!,CX20:DM20,"<>"&#REF!,CX20:DM20,"<>"&#REF!,CX20:DM20,"<>"&#REF!,CX20:DM20,"<>"&#REF!,CX20:DM20,"<>"&#REF!,CX20:DM20,"<>"&#REF!,CX20:DM20,"<>"&#REF!,CX20:DM20,"<>"&#REF!,CX20:DM20,"<>"&#REF!,CX20:DM20,"<>"&#REF!,CX20:DM20,"<>"&#REF!,CX20:DM20,"<>"&#REF!,CX20:DM20,"<>"&#REF!,CX20:DM20,"<>"&#REF!))) | DO20: =IF($J20="",0,IF($J20=1,_xlfn.MINIFS(#REF!,#REF!,">"&0),_xlfn.MINIFS(#REF!,#REF!,">"&0,#REF!,"<>"&#REF!,#REF!,"<>"&#REF!,#REF!,"<>"&#REF!,#REF!,"<>"&#REF!,#REF!,"<>"&#REF!,#REF!,"<>"&#REF!,#REF!,"<>"&#REF!,#REF!,"<>"&#REF!,#REF!,"<>"&#REF!,#REF!,"<>"&#REF!,#REF!,"<>"&#REF!,#REF!,"<>"&#REF!,#REF!,"<>"&#REF!,#REF!,"<>"&#REF!,#REF!,"<>"&#REF!,#REF!,"<>"&#REF!,#REF!,"<>"&#REF!,#REF!,"<>"&#REF!,#REF!,"<>"&#REF!,#REF!,"<>"&#REF!,#REF!,"<>"&#REF!,#REF!,"<>"&#REF!,#REF!,"<>"&#REF!,#REF!,"<>"&#REF!,#REF!,"<>"&#REF!,#REF!,"<>"&#REF!,#REF!,"<>"&#REF!,#REF!,"<>"&#REF!,#REF!,"<>"&#REF!,#REF!,"<>"&#REF!)))
B21: POSTE | C21: Poste de Concreto ou Fibra Simplificado Deflexão máxima 1◦0"00" | D21: Trava quedas | E21: 4 | F21: 9 | G21: 4 | H21: 45 | I21: VB | K21: NA | L21: =IF(ISTEXT(K21),K21,$J21*K21) | M21: 4493.03 | N21: =IF(ISTEXT(M21),M21,$J21*M21) | O21: N/A | P21: =IF(ISTEXT(O21),O21,$J21*O21) | Q21: n/a | R21: =IF(ISTEXT(Q21),Q21,$J21*Q21) | S21: =IF(ISTEXT(R21),R21,$J21*R21) | T21: =IF(ISTEXT(S21),S21,$J21*S21) | U21: N/A | V21: =IF(ISTEXT(U21),U21,$J21*U21) | W21: N/A | X21: =IF(ISTEXT(W21),W21,$J21*W21) | Z21: NA | AA21: =IF(ISTEXT(Z21),Z21,$J21*Z21) | AB21: NA | AC21: =IF(ISTEXT(AB21),AB21,$J21*AB21) | AD21: 4493.03 | AE21: =IF(ISTEXT(AD21),AD21,$J21*AD21) | AF21: N/A | AG21: =IF(ISTEXT(AF21),AF21,$J21*AF21) | AH21: n/a | AI21: =IF(ISTEXT(AH21),AH21,$J21*AH21) | AJ21: =IF(ISTEXT(AI21),AI21,$J21*AI21) | AK21: =IF(ISTEXT(AJ21),AJ21,$J21*AJ21) | AL21: N/A | AM21: =IF(ISTEXT(AL21),AL21,$J21*AL21) | AN21: N/A | AO21: =IF(ISTEXT(AN21),AN21,$J21*AN21) | AU21: 4493.03 | AV21: =AVERAGE(AZ21,BB21,BD21,BF21,BH21,BJ21,BL21) | AW21: =BASEDADOS[[#This Row],[VL UNIT MÉDIA]]*BASEDADOS[[#This Row],[QTDE]] | AX21: =ROUND(AU21*PARÂMETROS!$B$4,2) | AZ21: NA | BA21: =IF(ISTEXT(AZ21),AZ21,$J21*AZ21) | BB21: 4493.03 | BC21: =IF(ISTEXT(BB21),BB21,$J21*BB21) | BD21: N/A | BE21: =IF(ISTEXT(BD21),BD21,$J21*BD21) | BF21: n/a | BG21: =IF(ISTEXT(BF21),BF21,$J21*BF21) | BH21: =IF(ISTEXT(BG21),BG21,$J21*BG21) | BI21: =IF(ISTEXT(BH21),BH21,$J21*BH21) | BJ21: N/A | BK21: =IF(ISTEXT(BJ21),BJ21,$J21*BJ21) | BL21: N/A | BM21: =IF(ISTEXT(BL21),BL21,$J21*BL21) | BN21: NA | BO21: =IF(ISTEXT(BN21),BN21,$J21*BN21) | BP21: NA | BQ21: =IF(ISTEXT(BP21),BP21,$J21*BP21) | BR21: 4493.03 | BS21: =IF(ISTEXT(BR21),BR21,$J21*BR21) | BT21: N/A | BU21: =IF(ISTEXT(BT21),BT21,$J21*BT21) | BV21: n/a | BW21: =IF(ISTEXT(BV21),BV21,$J21*BV21) | BX21: =IF(ISTEXT(BW21),BW21,$J21*BW21) | BY21: =IF(ISTEXT(BX21),BX21,$J21*BX21) | BZ21: N/A | CA21: =IF(ISTEXT(BZ21),BZ21,$J21*BZ21) | CB21: N/A | CC21: =IF(ISTEXT(CB21),CB21,$J21*CB21) | CD21: =IF($J21="",0,IF($J21=1,_xlfn.MINIFS(BN21:CC21,BN21:CC21,">"&0),_xlfn.MINIFS(BN21:CC21,BN21:CC21,">"&0,BN21:CC21,"<>"&BN21,BN21:CC21,"<>"&BP21,BN21:CC21,"<>"&BR21,BN21:CC21,"<>"&BT21,BN21:CC21,"<>"&BV21,BN21:CC21,"<>"&BX21,BN21:CC21,"<>"&BZ21,BN21:CC21,"<>"&CB21,BN21:CC21,"<>"&#REF!,BN21:CC21,"<>"&#REF!,BN21:CC21,"<>"&#REF!,BN21:CC21,"<>"&#REF!,BN21:CC21,"<>"&#REF!,BN21:CC21,"<>"&#REF!,BN21:CC21,"<>"&#REF!,BN21:CC21,"<>"&#REF!,BN21:CC21,"<>"&#REF!,BN21:CC21,"<>"&#REF!,BN21:CC21,"<>"&#REF!,BN21:CC21,"<>"&#REF!,BN21:CC21,"<>"&#REF!,BN21:CC21,"<>"&#REF!,BN21:CC21,"<>"&#REF!,BN21:CC21,"<>"&#REF!,BN21:CC21,"<>"&#REF!,BN21:CC21,"<>"&#REF!,BN21:CC21,"<>"&#REF!,BN21:CC21,"<>"&#REF!,BN21:CC21,"<>"&#REF!,BN21:CC21,"<>"&#REF!))) | CF21: NA | CG21: =IF(ISTEXT(CF21),CF21,$J21*CF21) | CH21: NA | CI21: =IF(ISTEXT(CH21),CH21,$J21*CH21) | CJ21: 4493.03 | CK21: =IF(ISTEXT(CJ21),CJ21,$J21*CJ21) | CL21: N/A | CM21: =IF(ISTEXT(CL21),CL21,$J21*CL21) | CN21: n/a | CO21: =IF(ISTEXT(CN21),CN21,$J21*CN21) | CP21: =IF(ISTEXT(CO21),CO21,$J21*CO21) | CQ21: =IF(ISTEXT(CP21),CP21,$J21*CP21) | CR21: N/A | CS21: =IF(ISTEXT(CR21),CR21,$J21*CR21) | CT21: N/A | CU21: =IF(ISTEXT(CT21),CT21,$J21*CT21) | CV21: =IF($J21="",0,IF($J21=1,_xlfn.MINIFS(CF21:CU21,CF21:CU21,">"&0),_xlfn.MINIFS(CF21:CU21,CF21:CU21,">"&0,CF21:CU21,"<>"&CF21,CF21:CU21,"<>"&CH21,CF21:CU21,"<>"&CJ21,CF21:CU21,"<>"&CL21,CF21:CU21,"<>"&CN21,CF21:CU21,"<>"&CP21,CF21:CU21,"<>"&CR21,CF21:CU21,"<>"&CT21,CF21:CU21,"<>"&#REF!,CF21:CU21,"<>"&#REF!,CF21:CU21,"<>"&#REF!,CF21:CU21,"<>"&#REF!,CF21:CU21,"<>"&#REF!,CF21:CU21,"<>"&#REF!,CF21:CU21,"<>"&#REF!,CF21:CU21,"<>"&#REF!,CF21:CU21,"<>"&#REF!,CF21:CU21,"<>"&#REF!,CF21:CU21,"<>"&#REF!,CF21:CU21,"<>"&#REF!,CF21:CU21,"<>"&#REF!,CF21:CU21,"<>"&#REF!,CF21:CU21,"<>"&#REF!,CF21:CU21,"<>"&#REF!,CF21:CU21,"<>"&#REF!,CF21:CU21,"<>"&#REF!,CF21:CU21,"<>"&#REF!,CF21:CU21,"<>"&#REF!,CF21:CU21,"<>"&#REF!,CF21:CU21,"<>"&#REF!))) | CX21: NA | CY21: =IF(ISTEXT(CX21),CX21,$J21*CX21) | CZ21: NA | DA21: =IF(ISTEXT(CZ21),CZ21,$J21*CZ21) | DB21: 4493.03 | DC21: =IF(ISTEXT(DB21),DB21,$J21*DB21) | DD21: N/A | DE21: =IF(ISTEXT(DD21),DD21,$J21*DD21) | DF21: n/a | DG21: =IF(ISTEXT(DF21),DF21,$J21*DF21) | DH21: =IF(ISTEXT(DG21),DG21,$J21*DG21) | DI21: =IF(ISTEXT(DH21),DH21,$J21*DH21) | DJ21: N/A | DK21: =IF(ISTEXT(DJ21),DJ21,$J21*DJ21) | DL21: N/A | DM21: =IF(ISTEXT(DL21),DL21,$J21*DL21) | DN21: =IF($J21="",0,IF($J21=1,_xlfn.MINIFS(CX21:DM21,CX21:DM21,">"&0),_xlfn.MINIFS(CX21:DM21,CX21:DM21,">"&0,CX21:DM21,"<>"&CX21,CX21:DM21,"<>"&CZ21,CX21:DM21,"<>"&DB21,CX21:DM21,"<>"&DD21,CX21:DM21,"<>"&DF21,CX21:DM21,"<>"&DH21,CX21:DM21,"<>"&DJ21,CX21:DM21,"<>"&DL21,CX21:DM21,"<>"&#REF!,CX21:DM21,"<>"&#REF!,CX21:DM21,"<>"&#REF!,CX21:DM21,"<>"&#REF!,CX21:DM21,"<>"&#REF!,CX21:DM21,"<>"&#REF!,CX21:DM21,"<>"&#REF!,CX21:DM21,"<>"&#REF!,CX21:DM21,"<>"&#REF!,CX21:DM21,"<>"&#REF!,CX21:DM21,"<>"&#REF!,CX21:DM21,"<>"&#REF!,CX21:DM21,"<>"&#REF!,CX21:DM21,"<>"&#REF!,CX21:DM21,"<>"&#REF!,CX21:DM21,"<>"&#REF!,CX21:DM21,"<>"&#REF!,CX21:DM21,"<>"&#REF!,CX21:DM21,"<>"&#REF!,CX21:DM21,"<>"&#REF!,CX21:DM21,"<>"&#REF!,CX21:DM21,"<>"&#REF!))) | DO21: =IF($J21="",0,IF($J21=1,_xlfn.MINIFS(#REF!,#REF!,">"&0),_xlfn.MINIFS(#REF!,#REF!,">"&0,#REF!,"<>"&#REF!,#REF!,"<>"&#REF!,#REF!,"<>"&#REF!,#REF!,"<>"&#REF!,#REF!,"<>"&#REF!,#REF!,"<>"&#REF!,#REF!,"<>"&#REF!,#REF!,"<>"&#REF!,#REF!,"<>"&#REF!,#REF!,"<>"&#REF!,#REF!,"<>"&#REF!,#REF!,"<>"&#REF!,#REF!,"<>"&#REF!,#REF!,"<>"&#REF!,#REF!,"<>"&#REF!,#REF!,"<>"&#REF!,#REF!,"<>"&#REF!,#REF!,"<>"&#REF!,#REF!,"<>"&#REF!,#REF!,"<>"&#REF!,#REF!,"<>"&#REF!,#REF!,"<>"&#REF!,#REF!,"<>"&#REF!,#REF!,"<>"&#REF!,#REF!,"<>"&#REF!,#REF!,"<>"&#REF!,#REF!,"<>"&#REF!,#REF!,"<>"&#REF!,#REF!,"<>"&#REF!,#REF!,"<>"&#REF!)))
B22: POSTE | C22: Poste de Concreto ou Fibra Simplificado Deflexão máxima 1◦0"00" | D22: Esteriamento Horizontal EV > 30m | E22: 5 | F22: 9 | G22: 5 | H22: 30 | I22: VB | K22: NA | L22: =IF(ISTEXT(K22),K22,$J22*K22) | M22: 4463.44 | N22: =IF(ISTEXT(M22),M22,$J22*M22) | O22: N/A | P22: =IF(ISTEXT(O22),O22,$J22*O22) | Q22: n/a | R22: =IF(ISTEXT(Q22),Q22,$J22*Q22) | S22: =IF(ISTEXT(R22),R22,$J22*R22) | T22: =IF(ISTEXT(S22),S22,$J22*S22) | U22: N/A | V22: =IF(ISTEXT(U22),U22,$J22*U22) | W22: N/A | X22: =IF(ISTEXT(W22),W22,$J22*W22) | Z22: NA | AA22: =IF(ISTEXT(Z22),Z22,$J22*Z22) | AB22: NA | AC22: =IF(ISTEXT(AB22),AB22,$J22*AB22) | AD22: 4463.44 | AE22: =IF(ISTEXT(AD22),AD22,$J22*AD22) | AF22: N/A | AG22: =IF(ISTEXT(AF22),AF22,$J22*AF22) | AH22: n/a | AI22: =IF(ISTEXT(AH22),AH22,$J22*AH22) | AJ22: =IF(ISTEXT(AI22),AI22,$J22*AI22) | AK22: =IF(ISTEXT(AJ22),AJ22,$J22*AJ22) | AL22: N/A | AM22: =IF(ISTEXT(AL22),AL22,$J22*AL22) | AN22: N/A | AO22: =IF(ISTEXT(AN22),AN22,$J22*AN22) | AU22: 4463.44 | AV22: =AVERAGE(AZ22,BB22,BD22,BF22,BH22,BJ22,BL22) | AW22: =BASEDADOS[[#This Row],[VL UNIT MÉDIA]]*BASEDADOS[[#This Row],[QTDE]] | AX22: =ROUND(AU22*PARÂMETROS!$B$4,2) | AZ22: NA | BA22: =IF(ISTEXT(AZ22),AZ22,$J22*AZ22) | BB22: 4463.44 | BC22: =IF(ISTEXT(BB22),BB22,$J22*BB22) | BD22: N/A | BE22: =IF(ISTEXT(BD22),BD22,$J22*BD22) | BF22: n/a | BG22: =IF(ISTEXT(BF22),BF22,$J22*BF22) | BH22: =IF(ISTEXT(BG22),BG22,$J22*BG22) | BI22: =IF(ISTEXT(BH22),BH22,$J22*BH22) | BJ22: N/A | BK22: =IF(ISTEXT(BJ22),BJ22,$J22*BJ22) | BL22: N/A | BM22: =IF(ISTEXT(BL22),BL22,$J22*BL22) | BN22: NA | BO22: =IF(ISTEXT(BN22),BN22,$J22*BN22) | BP22: NA | BQ22: =IF(ISTEXT(BP22),BP22,$J22*BP22) | BR22: 4463.44 | BS22: =IF(ISTEXT(BR22),BR22,$J22*BR22) | BT22: N/A | BU22: =IF(ISTEXT(BT22),BT22,$J22*BT22) | BV22: n/a | BW22: =IF(ISTEXT(BV22),BV22,$J22*BV22) | BX22: =IF(ISTEXT(BW22),BW22,$J22*BW22) | BY22: =IF(ISTEXT(BX22),BX22,$J22*BX22) | BZ22: N/A | CA22: =IF(ISTEXT(BZ22),BZ22,$J22*BZ22) | CB22: N/A | CC22: =IF(ISTEXT(CB22),CB22,$J22*CB22) | CD22: =IF($J22="",0,IF($J22=1,_xlfn.MINIFS(BN22:CC22,BN22:CC22,">"&0),_xlfn.MINIFS(BN22:CC22,BN22:CC22,">"&0,BN22:CC22,"<>"&BN22,BN22:CC22,"<>"&BP22,BN22:CC22,"<>"&BR22,BN22:CC22,"<>"&BT22,BN22:CC22,"<>"&BV22,BN22:CC22,"<>"&BX22,BN22:CC22,"<>"&BZ22,BN22:CC22,"<>"&CB22,BN22:CC22,"<>"&#REF!,BN22:CC22,"<>"&#REF!,BN22:CC22,"<>"&#REF!,BN22:CC22,"<>"&#REF!,BN22:CC22,"<>"&#REF!,BN22:CC22,"<>"&#REF!,BN22:CC22,"<>"&#REF!,BN22:CC22,"<>"&#REF!,BN22:CC22,"<>"&#REF!,BN22:CC22,"<>"&#REF!,BN22:CC22,"<>"&#REF!,BN22:CC22,"<>"&#REF!,BN22:CC22,"<>"&#REF!,BN22:CC22,"<>"&#REF!,BN22:CC22,"<>"&#REF!,BN22:CC22,"<>"&#REF!,BN22:CC22,"<>"&#REF!,BN22:CC22,"<>"&#REF!,BN22:CC22,"<>"&#REF!,BN22:CC22,"<>"&#REF!,BN22:CC22,"<>"&#REF!,BN22:CC22,"<>"&#REF!))) | CF22: NA | CG22: =IF(ISTEXT(CF22),CF22,$J22*CF22) | CH22: NA | CI22: =IF(ISTEXT(CH22),CH22,$J22*CH22) | CJ22: 4463.44 | CK22: =IF(ISTEXT(CJ22),CJ22,$J22*CJ22) | CL22: N/A | CM22: =IF(ISTEXT(CL22),CL22,$J22*CL22) | CN22: n/a | CO22: =IF(ISTEXT(CN22),CN22,$J22*CN22) | CP22: =IF(ISTEXT(CO22),CO22,$J22*CO22) | CQ22: =IF(ISTEXT(CP22),CP22,$J22*CP22) | CR22: N/A | CS22: =IF(ISTEXT(CR22),CR22,$J22*CR22) | CT22: N/A | CU22: =IF(ISTEXT(CT22),CT22,$J22*CT22) | CV22: =IF($J22="",0,IF($J22=1,_xlfn.MINIFS(CF22:CU22,CF22:CU22,">"&0),_xlfn.MINIFS(CF22:CU22,CF22:CU22,">"&0,CF22:CU22,"<>"&CF22,CF22:CU22,"<>"&CH22,CF22:CU22,"<>"&CJ22,CF22:CU22,"<>"&CL22,CF22:CU22,"<>"&CN22,CF22:CU22,"<>"&CP22,CF22:CU22,"<>"&CR22,CF22:CU22,"<>"&CT22,CF22:CU22,"<>"&#REF!,CF22:CU22,"<>"&#REF!,CF22:CU22,"<>"&#REF!,CF22:CU22,"<>"&#REF!,CF22:CU22,"<>"&#REF!,CF22:CU22,"<>"&#REF!,CF22:CU22,"<>"&#REF!,CF22:CU22,"<>"&#REF!,CF22:CU22,"<>"&#REF!,CF22:CU22,"<>"&#REF!,CF22:CU22,"<>"&#REF!,CF22:CU22,"<>"&#REF!,CF22:CU22,"<>"&#REF!,CF22:CU22,"<>"&#REF!,CF22:CU22,"<>"&#REF!,CF22:CU22,"<>"&#REF!,CF22:CU22,"<>"&#REF!,CF22:CU22,"<>"&#REF!,CF22:CU22,"<>"&#REF!,CF22:CU22,"<>"&#REF!,CF22:CU22,"<>"&#REF!,CF22:CU22,"<>"&#REF!))) | CX22: NA | CY22: =IF(ISTEXT(CX22),CX22,$J22*CX22) | CZ22: NA | DA22: =IF(ISTEXT(CZ22),CZ22,$J22*CZ22) | DB22: 4463.44 | DC22: =IF(ISTEXT(DB22),DB22,$J22*DB22) | DD22: N/A | DE22: =IF(ISTEXT(DD22),DD22,$J22*DD22) | DF22: n/a | DG22: =IF(ISTEXT(DF22),DF22,$J22*DF22) | DH22: =IF(ISTEXT(DG22),DG22,$J22*DG22) | DI22: =IF(ISTEXT(DH22),DH22,$J22*DH22) | DJ22: N/A | DK22: =IF(ISTEXT(DJ22),DJ22,$J22*DJ22) | DL22: N/A | DM22: =IF(ISTEXT(DL22),DL22,$J22*DL22) | DN22: =IF($J22="",0,IF($J22=1,_xlfn.MINIFS(CX22:DM22,CX22:DM22,">"&0),_xlfn.MINIFS(CX22:DM22,CX22:DM22,">"&0,CX22:DM22,"<>"&CX22,CX22:DM22,"<>"&CZ22,CX22:DM22,"<>"&DB22,CX22:DM22,"<>"&DD22,CX22:DM22,"<>"&DF22,CX22:DM22,"<>"&DH22,CX22:DM22,"<>"&DJ22,CX22:DM22,"<>"&DL22,CX22:DM22,"<>"&#REF!,CX22:DM22,"<>"&#REF!,CX22:DM22,"<>"&#REF!,CX22:DM22,"<>"&#REF!,CX22:DM22,"<>"&#REF!,CX22:DM22,"<>"&#REF!,CX22:DM22,"<>"&#REF!,CX22:DM22,"<>"&#REF!,CX22:DM22,"<>"&#REF!,CX22:DM22,"<>"&#REF!,CX22:DM22,"<>"&#REF!,CX22:DM22,"<>"&#REF!,CX22:DM22,"<>"&#REF!,CX22:DM22,"<>"&#REF!,CX22:DM22,"<>"&#REF!,CX22:DM22,"<>"&#REF!,CX22:DM22,"<>"&#REF!,CX22:DM22,"<>"&#REF!,CX22:DM22,"<>"&#REF!,CX22:DM22,"<>"&#REF!,CX22:DM22,"<>"&#REF!,CX22:DM22,"<>"&#REF!))) | DO22: =IF($J22="",0,IF($J22=1,_xlfn.MINIFS(#REF!,#REF!,">"&0),_xlfn.MINIFS(#REF!,#REF!,">"&0,#REF!,"<>"&#REF!,#REF!,"<>"&#REF!,#REF!,"<>"&#REF!,#REF!,"<>"&#REF!,#REF!,"<>"&#REF!,#REF!,"<>"&#REF!,#REF!,"<>"&#REF!,#REF!,"<>"&#REF!,#REF!,"<>"&#REF!,#REF!,"<>"&#REF!,#REF!,"<>"&#REF!,#REF!,"<>"&#REF!,#REF!,"<>"&#REF!,#REF!,"<>"&#REF!,#REF!,"<>"&#REF!,#REF!,"<>"&#REF!,#REF!,"<>"&#REF!,#REF!,"<>"&#REF!,#REF!,"<>"&#REF!,#REF!,"<>"&#REF!,#REF!,"<>"&#REF!,#REF!,"<>"&#REF!,#REF!,"<>"&#REF!,#REF!,"<>"&#REF!,#REF!,"<>"&#REF!,#REF!,"<>"&#REF!,#REF!,"<>"&#REF!,#REF!,"<>"&#REF!,#REF!,"<>"&#REF!,#REF!,"<>"&#REF!)))
B23: POSTE | C23: Poste de Concreto ou Fibra Simplificado Deflexão máxima 1◦0"00" | D23: Esteriamento Horizontal EV > 30m | E23: 5 | F23: 9 | G23: 5 | H23: 35 | I23: VB | K23: NA | L23: =IF(ISTEXT(K23),K23,$J23*K23) | M23: 4686.61 | N23: =IF(ISTEXT(M23),M23,$J23*M23) | O23: N/A | P23: =IF(ISTEXT(O23),O23,$J23*O23) | Q23: n/a | R23: =IF(ISTEXT(Q23),Q23,$J23*Q23) | S23: =IF(ISTEXT(R23),R23,$J23*R23) | T23: =IF(ISTEXT(S23),S23,$J23*S23) | U23: N/A | V23: =IF(ISTEXT(U23),U23,$J23*U23) | W23: N/A | X23: =IF(ISTEXT(W23),W23,$J23*W23) | Z23: NA | AA23: =IF(ISTEXT(Z23),Z23,$J23*Z23) | AB23: NA | AC23: =IF(ISTEXT(AB23),AB23,$J23*AB23) | AD23: 4686.61 | AE23: =IF(ISTEXT(AD23),AD23,$J23*AD23) | AF23: N/A | AG23: =IF(ISTEXT(AF23),AF23,$J23*AF23) | AH23: n/a | AI23: =IF(ISTEXT(AH23),AH23,$J23*AH23) | AJ23: =IF(ISTEXT(AI23),AI23,$J23*AI23) | AK23: =IF(ISTEXT(AJ23),AJ23,$J23*AJ23) | AL23: N/A | AM23: =IF(ISTEXT(AL23),AL23,$J23*AL23) | AN23: N/A | AO23: =IF(ISTEXT(AN23),AN23,$J23*AN23) | AU23: 4686.61 | AV23: =AVERAGE(AZ23,BB23,BD23,BF23,BH23,BJ23,BL23) | AW23: =BASEDADOS[[#This Row],[VL UNIT MÉDIA]]*BASEDADOS[[#This Row],[QTDE]] | AX23: =ROUND(AU23*PARÂMETROS!$B$4,2) | AZ23: NA | BA23: =IF(ISTEXT(AZ23),AZ23,$J23*AZ23) | BB23: 4686.61 | BC23: =IF(ISTEXT(BB23),BB23,$J23*BB23) | BD23: N/A | BE23: =IF(ISTEXT(BD23),BD23,$J23*BD23) | BF23: n/a | BG23: =IF(ISTEXT(BF23),BF23,$J23*BF23) | BH23: =IF(ISTEXT(BG23),BG23,$J23*BG23) | BI23: =IF(ISTEXT(BH23),BH23,$J23*BH23) | BJ23: N/A | BK23: =IF(ISTEXT(BJ23),BJ23,$J23*BJ23) | BL23: N/A | BM23: =IF(ISTEXT(BL23),BL23,$J23*BL23) | BN23: NA | BO23: =IF(ISTEXT(BN23),BN23,$J23*BN23) | BP23: NA | BQ23: =IF(ISTEXT(BP23),BP23,$J23*BP23) | BR23: 4686.61 | BS23: =IF(ISTEXT(BR23),BR23,$J23*BR23) | BT23: N/A | BU23: =IF(ISTEXT(BT23),BT23,$J23*BT23) | BV23: n/a | BW23: =IF(ISTEXT(BV23),BV23,$J23*BV23) | BX23: =IF(ISTEXT(BW23),BW23,$J23*BW23) | BY23: =IF(ISTEXT(BX23),BX23,$J23*BX23) | BZ23: N/A | CA23: =IF(ISTEXT(BZ23),BZ23,$J23*BZ23) | CB23: N/A | CC23: =IF(ISTEXT(CB23),CB23,$J23*CB23) | CD23: =IF($J23="",0,IF($J23=1,_xlfn.MINIFS(BN23:CC23,BN23:CC23,">"&0),_xlfn.MINIFS(BN23:CC23,BN23:CC23,">"&0,BN23:CC23,"<>"&BN23,BN23:CC23,"<>"&BP23,BN23:CC23,"<>"&BR23,BN23:CC23,"<>"&BT23,BN23:CC23,"<>"&BV23,BN23:CC23,"<>"&BX23,BN23:CC23,"<>"&BZ23,BN23:CC23,"<>"&CB23,BN23:CC23,"<>"&#REF!,BN23:CC23,"<>"&#REF!,BN23:CC23,"<>"&#REF!,BN23:CC23,"<>"&#REF!,BN23:CC23,"<>"&#REF!,BN23:CC23,"<>"&#REF!,BN23:CC23,"<>"&#REF!,BN23:CC23,"<>"&#REF!,BN23:CC23,"<>"&#REF!,BN23:CC23,"<>"&#REF!,BN23:CC23,"<>"&#REF!,BN23:CC23,"<>"&#REF!,BN23:CC23,"<>"&#REF!,BN23:CC23,"<>"&#REF!,BN23:CC23,"<>"&#REF!,BN23:CC23,"<>"&#REF!,BN23:CC23,"<>"&#REF!,BN23:CC23,"<>"&#REF!,BN23:CC23,"<>"&#REF!,BN23:CC23,"<>"&#REF!,BN23:CC23,"<>"&#REF!,BN23:CC23,"<>"&#REF!))) | CF23: NA | CG23: =IF(ISTEXT(CF23),CF23,$J23*CF23) | CH23: NA | CI23: =IF(ISTEXT(CH23),CH23,$J23*CH23) | CJ23: 4686.61 | CK23: =IF(ISTEXT(CJ23),CJ23,$J23*CJ23) | CL23: N/A | CM23: =IF(ISTEXT(CL23),CL23,$J23*CL23) | CN23: n/a | CO23: =IF(ISTEXT(CN23),CN23,$J23*CN23) | CP23: =IF(ISTEXT(CO23),CO23,$J23*CO23) | CQ23: =IF(ISTEXT(CP23),CP23,$J23*CP23) | CR23: N/A | CS23: =IF(ISTEXT(CR23),CR23,$J23*CR23) | CT23: N/A | CU23: =IF(ISTEXT(CT23),CT23,$J23*CT23) | CV23: =IF($J23="",0,IF($J23=1,_xlfn.MINIFS(CF23:CU23,CF23:CU23,">"&0),_xlfn.MINIFS(CF23:CU23,CF23:CU23,">"&0,CF23:CU23,"<>"&CF23,CF23:CU23,"<>"&CH23,CF23:CU23,"<>"&CJ23,CF23:CU23,"<>"&CL23,CF23:CU23,"<>"&CN23,CF23:CU23,"<>"&CP23,CF23:CU23,"<>"&CR23,CF23:CU23,"<>"&CT23,CF23:CU23,"<>"&#REF!,CF23:CU23,"<>"&#REF!,CF23:CU23,"<>"&#REF!,CF23:CU23,"<>"&#REF!,CF23:CU23,"<>"&#REF!,CF23:CU23,"<>"&#REF!,CF23:CU23,"<>"&#REF!,CF23:CU23,"<>"&#REF!,CF23:CU23,"<>"&#REF!,CF23:CU23,"<>"&#REF!,CF23:CU23,"<>"&#REF!,CF23:CU23,"<>"&#REF!,CF23:CU23,"<>"&#REF!,CF23:CU23,"<>"&#REF!,CF23:CU23,"<>"&#REF!,CF23:CU23,"<>"&#REF!,CF23:CU23,"<>"&#REF!,CF23:CU23,"<>"&#REF!,CF23:CU23,"<>"&#REF!,CF23:CU23,"<>"&#REF!,CF23:CU23,"<>"&#REF!,CF23:CU23,"<>"&#REF!))) | CX23: NA | CY23: =IF(ISTEXT(CX23),CX23,$J23*CX23) | CZ23: NA | DA23: =IF(ISTEXT(CZ23),CZ23,$J23*CZ23) | DB23: 4686.61 | DC23: =IF(ISTEXT(DB23),DB23,$J23*DB23) | DD23: N/A | DE23: =IF(ISTEXT(DD23),DD23,$J23*DD23) | DF23: n/a | DG23: =IF(ISTEXT(DF23),DF23,$J23*DF23) | DH23: =IF(ISTEXT(DG23),DG23,$J23*DG23) | DI23: =IF(ISTEXT(DH23),DH23,$J23*DH23) | DJ23: N/A | DK23: =IF(ISTEXT(DJ23),DJ23,$J23*DJ23) | DL23: N/A | DM23: =IF(ISTEXT(DL23),DL23,$J23*DL23) | DN23: =IF($J23="",0,IF($J23=1,_xlfn.MINIFS(CX23:DM23,CX23:DM23,">"&0),_xlfn.MINIFS(CX23:DM23,CX23:DM23,">"&0,CX23:DM23,"<>"&CX23,CX23:DM23,"<>"&CZ23,CX23:DM23,"<>"&DB23,CX23:DM23,"<>"&DD23,CX23:DM23,"<>"&DF23,CX23:DM23,"<>"&DH23,CX23:DM23,"<>"&DJ23,CX23:DM23,"<>"&DL23,CX23:DM23,"<>"&#REF!,CX23:DM23,"<>"&#REF!,CX23:DM23,"<>"&#REF!,CX23:DM23,"<>"&#REF!,CX23:DM23,"<>"&#REF!,CX23:DM23,"<>"&#REF!,CX23:DM23,"<>"&#REF!,CX23:DM23,"<>"&#REF!,CX23:DM23,"<>"&#REF!,CX23:DM23,"<>"&#REF!,CX23:DM23,"<>"&#REF!,CX23:DM23,"<>"&#REF!,CX23:DM23,"<>"&#REF!,CX23:DM23,"<>"&#REF!,CX23:DM23,"<>"&#REF!,CX23:DM23,"<>"&#REF!,CX23:DM23,"<>"&#REF!,CX23:DM23,"<>"&#REF!,CX23:DM23,"<>"&#REF!,CX23:DM23,"<>"&#REF!,CX23:DM23,"<>"&#REF!,CX23:DM23,"<>"&#REF!))) | DO23: =IF($J23="",0,IF($J23=1,_xlfn.MINIFS(#REF!,#REF!,">"&0),_xlfn.MINIFS(#REF!,#REF!,">"&0,#REF!,"<>"&#REF!,#REF!,"<>"&#REF!,#REF!,"<>"&#REF!,#REF!,"<>"&#REF!,#REF!,"<>"&#REF!,#REF!,"<>"&#REF!,#REF!,"<>"&#REF!,#REF!,"<>"&#REF!,#REF!,"<>"&#REF!,#REF!,"<>"&#REF!,#REF!,"<>"&#REF!,#REF!,"<>"&#REF!,#REF!,"<>"&#REF!,#REF!,"<>"&#REF!,#REF!,"<>"&#REF!,#REF!,"<>"&#REF!,#REF!,"<>"&#REF!,#REF!,"<>"&#REF!,#REF!,"<>"&#REF!,#REF!,"<>"&#REF!,#REF!,"<>"&#REF!,#REF!,"<>"&#REF!,#REF!,"<>"&#REF!,#REF!,"<>"&#REF!,#REF!,"<>"&#REF!,#REF!,"<>"&#REF!,#REF!,"<>"&#REF!,#REF!,"<>"&#REF!,#REF!,"<>"&#REF!,#REF!,"<>"&#REF!)))
